Workbook

Sheet quarterly
B1: Non_oil_GDP | C1: Private_consumption | D1: Total_FBKF | E1: Oil_GDP | F1: Gov_consumption | G1: World_GDP_growth_qoq | H1: Oil_GDP_real | I1: Trade_balance | J1: GDP | K1: US_Y_Deflator | L1: Gov_investment | M1: Gov_transfers_with_ss | N1: Gov_transfers_no_ss | O1: Hours | P1: EC_Y_Deflator | Q1: Unemployment | R1: Gov_Debt | S1: D_Gov_Debt
A2: 2000.I | B2: =oilGDPnominal!C10 -> 3290847 | C2: =consumption_investment_governme!F10 -> 2445053 | D2: =consumption_investment_governme!H10 -> 723232 | E2: =oilGDPnominal!B10 -> 332388 | F2: 175154 | G2: =worldGDP!AU214 -> 0.98529 | H2: =oilGDPreal!B9 -> 1218387 | I2: 386080 | J2: 3819126 | K2: =US_GDP_deflator!B224 -> 77.396 | L2: 148.45286 | P2: 41.80951
A3: 2000.II | B3: =oilGDPnominal!C11 -> 3806141 | C3: =consumption_investment_governme!F11 -> 2841942 | D3: =consumption_investment_governme!H11 -> 821301 | E3: =oilGDPnominal!B11 -> 369840 | F3: 389776 | G3: =worldGDP!AU215 -> 1.245711 | H3: =oilGDPreal!B10 -> 1191946 | I3: 308601 | J3: 4402479 | K3: =US_GDP_deflator!B225 -> 77.865 | L3: 187.24743 | P3: 47.2348
A4: 2000.III | B4: =oilGDPnominal!C12 -> 4150331 | C4: =consumption_investment_governme!F12 -> 3164392 | D4: =consumption_investment_governme!H12 -> 947040 | E4: =oilGDPnominal!B12 -> 460321 | F4: 516011 | G4: =worldGDP!AU216 -> 0.501401 | H4: =oilGDPreal!B11 -> 1241308 | I4: 148436 | J4: 4906653 | K4: =US_GDP_deflator!B226 -> 78.309 | L4: 226.00242 | P4: 51.38669
A5: 2000.IV | B5: =oilGDPnominal!C13 -> 4400253 | C5: =consumption_investment_governme!F13 -> 3378859 | D5: =consumption_investment_governme!H13 -> 991669 | E5: =oilGDPnominal!B13 -> 462506 | F5: 631921 | G5: =worldGDP!AU217 -> 0.556709 | H5: =oilGDPreal!B12 -> 1241168 | I5: 34412 | J5: 5190343 | K5: =US_GDP_deflator!B227 -> 78.723 | L5: 217.7125 | P5: 53.38256
A6: 2001.I | B6: =oilGDPnominal!C14 -> 5130098 | C6: =consumption_investment_governme!F14 -> 4198533 | D6: =consumption_investment_governme!H14 -> 1053487 | E6: =oilGDPnominal!B14 -> 336056 | F6: 577101 | G6: =worldGDP!AU218 -> 0.283557 | H6: =oilGDPreal!B13 -> 1255388 | I6: -61201 | J6: 5904082 | K6: =US_GDP_deflator!B228 -> 79.204 | L6: 279.94644 | P6: 60.87082
A7: 2001.II | B7: =oilGDPnominal!C15 -> 5256978 | C7: =consumption_investment_governme!F15 -> 4375885 | D7: =consumption_investment_governme!H15 -> 1147563 | E7: =oilGDPnominal!B15 -> 327311 | F7: 582004 | G7: =worldGDP!AU219 -> 0.173391 | H7: =oilGDPreal!B14 -> 1232212 | I7: -267622 | J7: 6069620 | K7: =US_GDP_deflator!B229 -> 79.683 | L7: 261.42701 | P7: 61.91965
A8: 2001.III | B8: =oilGDPnominal!C16 -> 5336981 | C8: =consumption_investment_governme!F16 -> 4454342 | D8: =consumption_investment_governme!H16 -> 1212577 | E8: =oilGDPnominal!B16 -> 322417 | F8: 551198 | G8: =worldGDP!AU220 -> -0.042376 | H8: =oilGDPreal!B15 -> 1207624 | I8: -285424 | J8: 6159609 | K8: =US_GDP_deflator!B230 -> 80.004 | L8: 290.41246 | P8: 62.79239
A9: 2001.IV | B9: =oilGDPnominal!C17 -> 5535621 | C9: =consumption_investment_governme!F17 -> 4711126 | D9: =consumption_investment_governme!H17 -> 1247952 | E9: =oilGDPnominal!B17 -> 286737 | F9: 601693 | G9: =worldGDP!AU221 -> 0.167967 | H9: =oilGDPreal!B16 -> 1197778 | I9: -437784 | J9: 6335013 | K9: =US_GDP_deflator!B231 -> 80.268 | L9: 323.53177 | P9: 63.79604
A10: 2002.I | B10: =oilGDPnominal!C18 -> 5858861 | C10: =consumption_investment_governme!F18 -> 4935609 | D10: =consumption_investment_governme!H18 -> 1388559 | E10: =oilGDPnominal!B18 -> 340321 | F10: 622826 | G10: =worldGDP!AU222 -> 0.588085 | H10: =oilGDPreal!B17 -> 1196035 | I10: -420858 | J10: 6737551 | K10: =US_GDP_deflator!B232 -> 80.533 | L10: 337.2918 | P10: 66.94994
A11: 2002.II | B11: =oilGDPnominal!C19 -> 6100775 | C11: =consumption_investment_governme!F19 -> 5165450 | D11: =consumption_investment_governme!H19 -> 1460080 | E11: =oilGDPnominal!B19 -> 394787 | F11: 689584 | G11: =worldGDP!AU223 -> 0.773728 | H11: =oilGDPreal!B18 -> 1206414 | I11: -558124 | J11: 7086627 | K11: =US_GDP_deflator!B233 -> 80.821 | L11: 391.34819 | P11: 69.43713
A12: 2002.III | B12: =oilGDPnominal!C20 -> 6290885 | C12: =consumption_investment_governme!F20 -> 5297262 | D12: =consumption_investment_governme!H20 -> 1514534 | E12: =oilGDPnominal!B20 -> 416026 | F12: 721936 | G12: =worldGDP!AU224 -> 0.527771 | H12: =oilGDPreal!B19 -> 1189068 | I12: -482251 | J12: 7294132 | K12: =US_GDP_deflator!B234 -> 81.194 | L12: 313.86603 | P12: 70.99459
A13: 2002.IV | B13: =oilGDPnominal!C21 -> 6438429 | C13: =consumption_investment_governme!F21 -> 5401579 | D13: =consumption_investment_governme!H21 -> 1543432 | E13: =oilGDPnominal!B21 -> 399758 | F13: 772712 | G13: =worldGDP!AU225 -> 0.308766 | H13: =oilGDPreal!B20 -> 1153055 | I13: -363559 | J13: 7430635 | K13: =US_GDP_deflator!B235 -> 81.654 | L13: 333.90243 | P13: 72.10427
... A16: 2003.III | B16: =oilGDPnominal!C24 -> 7045127 | C16: =consumption_investment_governme!F24 -> 5866442 | D16: =consumption_investment_governme!H24 -> 1529914 | E16: =oilGDPnominal!B24 -> 509102 | F16: 889497 | G16: =worldGDP!AU228 -> 1.077838 | H16: =oilGDPreal!B23 -> 1265059 | I16: -125719 | J16: 8120465 | K16: =US_GDP_deflator!B238 -> 82.712 | L16: 420.11015 | P16: 77.60101
A17: 2003.IV | B17: =oilGDPnominal!C25 -> 7179216 | C17: =consumption_investment_governme!F25 -> 5903082 | D17: =consumption_investment_governme!H25 -> 1554456 | E17: =oilGDPnominal!B25 -> 587169 | F17: 913976 | G17: =worldGDP!AU229 -> 1.05367 | H17: =oilGDPreal!B24 -> 1483081 | I17: -141198 | J17: 8335886 | K17: =US_GDP_deflator!B239 -> 83.201 | L17: 358.65815 | P17: 77.06994 | R17: 45.062
A18: 2004.I | B18: =oilGDPnominal!C26 -> 7593729 | C18: =consumption_investment_governme!F26 -> 6306606 | D18: =consumption_investment_governme!H26 -> 1651726 | E18: =oilGDPnominal!B26 -> 704411 | F18: 989429 | G18: =worldGDP!AU230 -> 0.790881 | H18: =oilGDPreal!B25 -> 1643486 | I18: -186745 | J18: 8849273 | K18: =US_GDP_deflator!B240 -> 83.82 | L18: 351.81579 | P18: 79.78492
A19: 2004.II | B19: =oilGDPnominal!C27 -> 7702511 | C19: =consumption_investment_governme!F27 -> 6406699 | D19: =consumption_investment_governme!H27 -> 1772561 | E19: =oilGDPnominal!B27 -> 774451 | F19: 1001661 | G19: =worldGDP!AU231 -> 0.671886 | H19: =oilGDPreal!B26 -> 1746705 | I19: -172900 | J19: 9041596 | K19: =US_GDP_deflator!B241 -> 84.504 | L19: 421.47159 | P19: 80.13788
A20: 2004.III | B20: =oilGDPnominal!C28 -> 7754905 | C20: =consumption_investment_governme!F28 -> 6405966 | D20: =consumption_investment_governme!H28 -> 1836724 | E20: =oilGDPnominal!B28 -> 847667 | F20: 984387 | G20: =worldGDP!AU232 -> 0.591195 | H20: =oilGDPreal!B27 -> 1724686 | I20: -86264 | J20: 9207469 | K20: =US_GDP_deflator!B242 -> 85.056 | L20: 348.90898 | P20: 80.74398
A21: 2004.IV | B21: =oilGDPnominal!C29 -> 8010063 | C21: =consumption_investment_governme!F29 -> 6668037 | D21: =consumption_investment_governme!H29 -> 1948114 | E21: =oilGDPnominal!B29 -> 810428 | F21: 1007289 | G21: =worldGDP!AU233 -> 0.664294 | H21: =oilGDPreal!B28 -> 1750682 | I21: -123656 | J21: 9493323 | K21: =US_GDP_deflator!B243 -> 85.712 | L21: 359.99401 | P21: 81.63167 | R21: 38.665 | S21: =R21-R17 -> -6.397
A22: 2005.I | B22: =oilGDPnominal!C30 -> 8381666 | C22: =consumption_investment_governme!F30 -> 6872973 | D22: =consumption_investment_governme!H30 -> 1970809 | E22: =oilGDPnominal!B30 -> 948146 | F22: 1067573 | G22: =worldGDP!AU234 -> 0.78374 | H22: =oilGDPreal!B29 -> 1731598 | I22: -213444 | J22: 9858210 | K22: =US_GDP_deflator!B244 -> 86.391 | L22: 462.36779 | P22: 83.74419
A23: 2005.II | B23: =oilGDPnominal!C31 -> 8568497 | C23: =consumption_investment_governme!F31 -> 7047351 | D23: =consumption_investment_governme!H31 -> 2115210 | E23: =oilGDPnominal!B31 -> 1043477 | F23: 1094043 | G23: =worldGDP!AU235 -> 0.667814 | H23: =oilGDPreal!B30 -> 1736419 | I23: -177533 | J23: 10221018 | K23: =US_GDP_deflator!B245 -> 86.996 | L23: 415.07674 | P23: 85.62904
A24: 2005.III | B24: =oilGDPnominal!C32 -> 8787060 | C24: =consumption_investment_governme!F32 -> 7124759 | D24: =consumption_investment_governme!H32 -> 2163922 | E24: =oilGDPnominal!B32 -> 1230871 | F24: 1125814 | G24: =worldGDP!AU236 -> 0.935619 | H24: =oilGDPreal!B31 -> 1692897 | I24: 176053 | J24: 10645973 | K24: =US_GDP_deflator!B246 -> 87.783 | L24: 445.0674 | P24: 89.07334
A25: 2005.IV | B25: =oilGDPnominal!C33 -> 9087352 | C25: =consumption_investment_governme!F33 -> 7390813 | D25: =consumption_investment_governme!H33 -> 2226812 | E25: =oilGDPnominal!B33 -> 1158075 | F25: 1161235 | G25: =worldGDP!AU237 -> 0.795562 | H25: =oilGDPreal!B32 -> 1779305 | I25: -143482 | J25: 10781884 | K25: =US_GDP_deflator!B247 -> 88.489 | L25: 467.22117 | P25: 88.74567 | R25: 34.7 | S25: =R25-R21 -> -3.965
A26: 2006.I | B26: =oilGDPnominal!C34 -> 9391938 | C26: =consumption_investment_governme!F34 -> 7473628 | D26: =consumption_investment_governme!H34 -> 2289331 | E26: =oilGDPnominal!B34 -> 1377519 | F26: 1180967 | G26: =worldGDP!AU238 -> 1.052975 | H26: =oilGDPreal!B33 -> 1819765 | I26: 206457 | J26: 11312589 | K26: =US_GDP_deflator!B248 -> 89.107 | L26: 481.15361 | P26: 92.1362
A27: 2006.II | B27: =oilGDPnominal!C35 -> 9556770 | C27: =consumption_investment_governme!F35 -> 7640025 | D27: =consumption_investment_governme!H35 -> 2446002 | E27: =oilGDPnominal!B35 -> 1602913 | F27: 1213810 | G27: =worldGDP!AU239 -> 0.670682 | H27: =oilGDPreal!B34 -> 1859370 | I27: 98112 | J27: 11727184 | K27: =US_GDP_deflator!B249 -> 89.852 | L27: 504.67497 | P27: 94.21676
A28: 2006.III | B28: =oilGDPnominal!C36 -> 9768533 | C28: =consumption_investment_governme!F36 -> 7792795 | D28: =consumption_investment_governme!H36 -> 2546226 | E28: =oilGDPnominal!B36 -> 1587156 | F28: 1244480 | G28: =worldGDP!AU240 -> 0.345611 | H28: =oilGDPreal!B35 -> 1842611 | I28: 18302 | J28: 11941733 | K28: =US_GDP_deflator!B250 -> 90.481 | L28: 404.98089 | P28: 94.82836
A29: 2006.IV | B29: =oilGDPnominal!C37 -> 9960546 | C29: =consumption_investment_governme!F37 -> 7974442 | D29: =consumption_investment_governme!H37 -> 2478153 | E29: =oilGDPnominal!B37 -> 1251772 | F29: 1322646 | G29: =worldGDP!AU241 -> 0.981041 | H29: =oilGDPreal!B36 -> 1748041 | I29: 124728 | J29: 11820538 | K29: =US_GDP_deflator!B251 -> 90.815 | L29: 447.35482 | P29: 93.84005 | R29: 31.128 | S29: =R29-R25 -> -3.572
A30: 2007.I | B30: =oilGDPnominal!C38 -> 10109986 | C30: =consumption_investment_governme!F38 -> 8096780 | D30: =consumption_investment_governme!H38 -> 2580234 | E30: =oilGDPnominal!B38 -> 1262814 | F30: 1349454 | G30: =worldGDP!AU242 -> 0.721112 | H30: =oilGDPreal!B37 -> 1666169 | I30: -120496 | J30: 11972101 | K30: =US_GDP_deflator!B252 -> 91.708 | L30: 656.38665 | P30: 95.40522
A31: 2007.II | B31: =oilGDPnominal!C39 -> 10287446 | C31: =consumption_investment_governme!F39 -> 8215569 | D31: =consumption_investment_governme!H39 -> 2613022 | E31: =oilGDPnominal!B39 -> 1585173 | F31: 1402301 | G31: =worldGDP!AU243 -> 0.601542 | H31: =oilGDPreal!B38 -> 1655298 | I31: 102336 | J31: 12483035 | K31: =US_GDP_deflator!B253 -> 92.301 | L31: 813.8185 | P31: 98.74745
A32: 2007.III | B32: =oilGDPnominal!C40 -> 10507783 | C32: =consumption_investment_governme!F40 -> 8348009 | D32: =consumption_investment_governme!H40 -> 2631842 | E32: =oilGDPnominal!B40 -> 1746306 | F32: 1407775 | G32: =worldGDP!AU244 -> 0.457851 | H32: =oilGDPreal!B39 -> 1691341 | I32: 281581 | J32: 12923037 | K32: =US_GDP_deflator!B254 -> 92.776 | L32: 883.07294 | P32: 100.7919
A33: 2007.IV | B33: =oilGDPnominal!C41 -> 10854414 | C33: =consumption_investment_governme!F41 -> 8540920 | D33: =consumption_investment_governme!H41 -> 2768849 | E33: =oilGDPnominal!B41 -> 2156981 | F33: 1414679 | G33: =worldGDP!AU245 -> 0.740587 | H33: =oilGDPreal!B40 -> 1738466 | I33: 387641 | J33: 13629604 | K33: =US_GDP_deflator!B255 -> 93.145 | L33: 676.94979 | O33: =[1]quarterly!$B2 -> 39.765817 | P33: 104.8736 | Q33: 4.9983546 | R33: 28.464 | S33: =R33-R29 -> -2.664
A34: 2008.I | B34: =oilGDPnominal!C42 -> 11581175 | C34: =consumption_investment_governme!F42 -> 8948763 | D34: =consumption_investment_governme!H42 -> 2970329 | E34: =oilGDPnominal!B42 -> 2450552 | F34: 1670986 | G34: =worldGDP!AU246 -> 0.172714 | H34: =oilGDPreal!B41 -> 1728166 | I34: 801868 | J34: 14505871 | K34: =US_GDP_deflator!B256 -> 93.489 | L34: 1122.0941 | M34: 1362.2188 | N34: 937.04991 | O34: =[1]quarterly!$B3 -> . | P34: 109.8631
A35: 2008.II | B35: =oilGDPnominal!C43 -> 12230997 | C35: =consumption_investment_governme!F43 -> 9312999 | D35: =consumption_investment_governme!H43 -> 3344536 | E35: =oilGDPnominal!B43 -> 2981374 | F35: 1800173 | G35: =worldGDP!AU247 -> -0.039553 | H35: =oilGDPreal!B42 -> 1679075 | I35: 296710 | J35: 15788923 | K35: =US_GDP_deflator!B257 -> 93.99 | L35: 1468.3939 | M35: 1877.05 | N35: 1429.064 | O35: =[1]quarterly!$B4 -> 39.793649 | P35: 117.495 | Q35: 5.2227055
A36: 2008.III | B36: =oilGDPnominal!C44 -> 12941154 | C36: =consumption_investment_governme!F44 -> 9664597 | D36: =consumption_investment_governme!H44 -> 3703868 | E36: =oilGDPnominal!B44 -> 2859228 | F36: 1902052 | G36: =worldGDP!AU248 -> -0.545974 | H36: =oilGDPreal!B43 -> 1694710 | I36: -315809 | J36: 16213465 | K36: =US_GDP_deflator!B258 -> 94.69 | L36: 2020.4581 | M36: 2026.8234 | N36: 1702.842 | O36: =[1]quarterly!$B5 -> . | P36: 118.4395
A37: 2008.IV | B37: =oilGDPnominal!C45 -> 13024414 | C37: =consumption_investment_governme!F45 -> 10064904 | D37: =consumption_investment_governme!H45 -> 3799781 | E37: =oilGDPnominal!B45 -> 1482008 | F37: 1933577 | G37: =worldGDP!AU249 -> -1.923925 | H37: =oilGDPreal!B44 -> 1698965 | I37: -615805 | J37: 15254376 | K37: =US_GDP_deflator!B259 -> 94.986 | L37: 2246.4671 | M37: 1826.2011 | N37: 1464.3602 | O37: =[1]quarterly!$B6 -> 39.844144 | P37: 109.589 | Q37: 5.951463 | R37: 24.229 | S37: =R37-R33 -> -4.235
A38: 2009.I | B38: =oilGDPnominal!C46 -> 13042531 | C38: =consumption_investment_governme!F46 -> 9799156 | D38: =consumption_investment_governme!H46 -> 3638386 | E38: =oilGDPnominal!B46 -> 1054725 | F38: 2020721 | G38: =worldGDP!AU250 -> -2.252955 | H38: =oilGDPreal!B45 -> 1764343 | I38: -563681 | J38: 15022003 | K38: =US_GDP_deflator!B260 -> 94.976 | L38: 1481.7728 | M38: 1383.2106 | N38: 975.54097 | O38: =[1]quarterly!$B7 -> . | P38: 109.4803
A39: 2009.II | B39: =oilGDPnominal!C47 -> 13139527 | C39: =consumption_investment_governme!F47 -> 9634405 | D39: =consumption_investment_governme!H47 -> 3538406 | E39: =oilGDPnominal!B47 -> 1525729 | F39: 2100079 | G39: =worldGDP!AU251 -> 0.155632 | H39: =oilGDPreal!B46 -> 1801773 | I39: -224241 | J39: 15588869 | K39: =US_GDP_deflator!B261 -> 94.838 | L39: 1510.2219 | M39: 1294.8698 | N39: 851.76278 | O39: =[1]quarterly!$B8 -> . | P39: 114.0894
A40: 2009.III | B40: =oilGDPnominal!C48 -> 13352010 | C40: =consumption_investment_governme!F48 -> 9658411 | D40: =consumption_investment_governme!H48 -> 3493945 | E40: =oilGDPnominal!B48 -> 1617564 | F40: 2189216 | G40: =worldGDP!AU252 -> 0.55993 | H40: =oilGDPreal!B47 -> 1667167 | I40: -212924 | J40: 15779977 | K40: =US_GDP_deflator!B262 -> 94.938 | L40: 1568.8861 | M40: 1231.5664 | N40: 804.53628 | O40: =[1]quarterly!$B9 -> . | P40: 116.2044
A41: 2009.IV | B41: =oilGDPnominal!C49 -> 13584681 | C41: =consumption_investment_governme!F49 -> 9821313 | D41: =consumption_investment_governme!H49 -> 3586952 | E41: =oilGDPnominal!B49 -> 1696508 | F41: 2271259 | G41: =worldGDP!AU253 -> 0.940041 | H41: =oilGDPreal!B48 -> 1596198 | I41: -3616 | J41: 16128837 | K41: =US_GDP_deflator!B263 -> 95.259 | L41: 1712.3944 | M41: 1814.6155 | N41: 1222.1189 | O41: =[1]quarterly!$B10 -> 38.949399 | P41: 118.6528 | Q41: 6.47131 | R41: 18.568 | S41: =R41-R37 -> -5.661
A42: 2010.I | B42: =oilGDPnominal!C50 -> 14076102 | C42: =consumption_investment_governme!F50 -> 10500363 | D42: =consumption_investment_governme!H50 -> 3975994 | E42: =oilGDPnominal!B50 -> 1998698 | F42: 2234239 | G42: =worldGDP!AU254 -> 0.619244 | H42: =oilGDPreal!B49 -> 1582738 | I42: -631341 | J42: 16762628 | K42: =US_GDP_deflator!B264 -> 95.499 | L42: 1286.8867 | M42: 2028.207 | N42: 1445.9398 | O42: =[1]quarterly!$B11 -> . | P42: 122.0892
A43: 2010.II | B43: =oilGDPnominal!C51 -> 14346146 | C43: =consumption_investment_governme!F51 -> 10805848 | D43: =consumption_investment_governme!H51 -> 4168368 | E43: =oilGDPnominal!B51 -> 2014408 | F43: 2241678 | G43: =worldGDP!AU255 -> 1.072176 | H43: =oilGDPreal!B50 -> 1646484 | I43: -648027 | J43: 17070795 | K43: =US_GDP_deflator!B265 -> 95.943 | L43: 1920.852 | M43: 1824.951 | N43: 1272.0684 | O43: =[1]quarterly!$B12 -> 38.22407 | P43: 122.4041 | Q43: 6.203129
A44: 2010.III | B44: =oilGDPnominal!C52 -> 14710837 | C44: =consumption_investment_governme!F52 -> 11235105 | D44: =consumption_investment_governme!H52 -> 4422541 | E44: =oilGDPnominal!B52 -> 1897121 | F44: 2301804 | G44: =worldGDP!AU256 -> 0.821216 | H44: =oilGDPreal!B51 -> 1660400 | I44: -1154443 | J44: 17429358 | K44: =US_GDP_deflator!B266 -> 96.222 | L44: 1718.7529 | M44: 1820.2724 | N44: 1256.3255 | O44: =[1]quarterly!$B13 -> . | P44: 122.9507
A45: 2010.IV | B45: =oilGDPnominal!C53 -> 15239690 | C45: =consumption_investment_governme!F53 -> 11470789 | D45: =consumption_investment_governme!H53 -> 4560986 | E45: =oilGDPnominal!B53 -> 2216458 | F45: 2403346 | G45: =worldGDP!AU257 -> 0.57069 | H45: =oilGDPreal!B52 -> 1782454 | I45: -705450 | J45: 18292586 | K45: =US_GDP_deflator!B267 -> 96.763 | L45: 1629.6158 | M45: 1940.8609 | N45: 1399.4451 | O45: =[1]quarterly!$B14 -> 39.534685 | P45: 125.0425 | Q45: 5.018858 | R45: 17.696 | S45: =R45-R41 -> -0.872
A46: 2011.I | B46: =oilGDPnominal!C54 -> 15576348 | C46: =consumption_investment_governme!F54 -> 11694784 | D46: =consumption_investment_governme!H54 -> 4765661 | E46: =oilGDPnominal!B54 -> 2639401 | F46: 2379105 | G46: =worldGDP!AU258 -> 0.282251 | H46: =oilGDPreal!B53 -> 1779993 | I46: -409678 | J46: 18922955 | K46: =US_GDP_deflator!B268 -> 97.283 | L46: 2166.2642 | M46: 2658.6859 | N46: 1847.3252 | O46: =[1]quarterly!$B15 -> . | P46: 127.9411
A47: 2011.II | B47: =oilGDPnominal!C55 -> 16214501 | C47: =consumption_investment_governme!F55 -> 12040630 | D47: =consumption_investment_governme!H55 -> 5002022 | E47: =oilGDPnominal!B55 -> 2829695 | F47: 2539852 | G47: =worldGDP!AU259 -> 0.385808 | H47: =oilGDPreal!B54 -> 1751648 | I47: -474267 | J47: 19728114 | K47: =US_GDP_deflator!B269 -> 97.922 | L47: 2149.221 | M47: 2943.1454 | N47: 2137.3433 | O47: =[1]quarterly!$B16 -> 39.178826 | P47: 129.9891 | Q47: 5.0231254
A48: 2011.III | B48: =oilGDPnominal!C56 -> 16702351 | C48: =consumption_investment_governme!F56 -> 12359537 | D48: =consumption_investment_governme!H56 -> 5222935 | E48: =oilGDPnominal!B56 -> 2575368 | F48: 2534436 | G48: =worldGDP!AU260 -> 0.595382 | H48: =oilGDPreal!B55 -> 1719529 | I48: -289894 | J48: 19968470 | K48: =US_GDP_deflator!B270 -> 98.553 | L48: 2196.3861 | M48: 3058.7747 | N48: 2183.6336 | O48: =[1]quarterly!$B17 -> . | P48: 129.5888
A49: 2011.IV | B49: =oilGDPnominal!C57 -> 17140786 | C49: =consumption_investment_governme!F57 -> 12562204 | D49: =consumption_investment_governme!H57 -> 5480168 | E49: =oilGDPnominal!B57 -> 2857765 | F49: 2637773 | G49: =worldGDP!AU261 -> 0.445108 | H49: =oilGDPreal!B56 -> 1674155 | I49: -608173 | J49: 20657125 | K49: =US_GDP_deflator!B271 -> 98.703 | L49: 2434.6001 | M49: 2965.5605 | N49: 2259.4176 | O49: =[1]quarterly!$B18 -> 39.388395 | P49: 132.853 | Q49: 4.2054597 | R49: 16.789 | S49: =R49-R45 -> -0.907
A50: 2012.I | B50: =oilGDPnominal!C58 -> 17523169 | C50: =consumption_investment_governme!F58 -> 12896279 | D50: =consumption_investment_governme!H58 -> 5733341 | E50: =oilGDPnominal!B58 -> 3111930 | F50: 2805829 | G50: =worldGDP!AU262 -> 0.45496 | H50: =oilGDPreal!B57 -> 1765605 | I50: -168744 | J50: 21622937 | K50: =US_GDP_deflator!B272 -> 99.32 | L50: 2516.5362 | M50: 2786.64 | N50: 2017.6733 | O50: =[1]quarterly!$B19 -> . | P50: 136.8662
A51: 2012.II | B51: =oilGDPnominal!C59 -> 17901091 | C51: =consumption_investment_governme!F59 -> 13257745 | D51: =consumption_investment_governme!H59 -> 5853906 | E51: =oilGDPnominal!B59 -> 2982818 | F51: 2847288 | G51: =worldGDP!AU263 -> 0.139623 | H51: =oilGDPreal!B58 -> 1827627 | I51: -283218 | J51: 21908844 | K51: =US_GDP_deflator!B273 -> 99.713 | L51: 2551.2157 | M51: 2982.5883 | N51: 2169.2434 | O51: =[1]quarterly!$B20 -> 38.315673 | P51: 136.3097 | Q51: 4.1126056
A52: 2012.III | B52: =oilGDPnominal!C60 -> 18130356 | C52: =consumption_investment_governme!F60 -> 13364281 | D52: =consumption_investment_governme!H60 -> 5997916 | E52: =oilGDPnominal!B60 -> 2945968 | F52: 2951086 | G52: =worldGDP!AU264 -> 0.159008 | H52: =oilGDPreal!B59 -> 1816737 | I52: -362619 | J52: 22106937 | K52: =US_GDP_deflator!B274 -> 100.225 | L52: 2682.9062 | M52: 3025.8701 | N52: 2223.0238 | O52: =[1]quarterly!$B21 -> . | P52: 136.4882
A53: 2012.IV | B53: =oilGDPnominal!C61 -> 18559188 | C53: =consumption_investment_governme!F61 -> 13489967 | D53: =consumption_investment_governme!H61 -> 6122675 | E53: =oilGDPnominal!B61 -> 2701651 | F53: 3122549 | G53: =worldGDP!AU265 -> 0.07857 | H53: =oilGDPreal!B60 -> 1731571 | I53: -435261 | J53: 22285826 | K53: =US_GDP_deflator!B275 -> 100.737 | L53: 2461.6326 | M53: 3158.3252 | N53: 2213.6073 | O53: =[1]quarterly!$B22 -> 38.943186 | P53: 136.7729 | Q53: 4.121378 | R53: 17.496 | S53: =R53-R49 -> 0.707
A54: 2013.I | B54: =oilGDPnominal!C62 -> 18979091 | C54: =consumption_investment_governme!F62 -> 13748778 | D54: =consumption_investment_governme!H62 -> 6406446 | E54: =oilGDPnominal!B62 -> 2959920 | F54: 3222907 | G54: =worldGDP!AU266 -> 0.598762 | H54: =oilGDPreal!B61 -> 1646199 | I54: -697236 | J54: 23019786 | K54: =US_GDP_deflator!B276 -> 101.139 | L54: 2998.2348 | M54: 3230.7679 | N54: 2376.7956 | O54: =[1]quarterly!$B23 -> . | P54: 139.8638
A55: 2013.II | B55: =oilGDPnominal!C63 -> 19429037 | C55: =consumption_investment_governme!F63 -> 14137037 | D55: =consumption_investment_governme!H63 -> 6509500 | E55: =oilGDPnominal!B63 -> 2866631 | F55: 3311670 | G55: =worldGDP!AU267 -> 0.498172 | H55: =oilGDPreal!B62 -> 1701157 | I55: -742732 | J55: 23441324 | K55: =US_GDP_deflator!B277 -> 101.431 | L55: 3320.7462 | M55: 3117.6802 | N55: 2258.5511 | O55: =[1]quarterly!$B24 -> 37.910163 | P55: 139.5131 | Q55: 3.913723
A56: 2013.III | B56: =oilGDPnominal!C64 -> 19890585 | C56: =consumption_investment_governme!F64 -> 14384933 | D56: =consumption_investment_governme!H64 -> 6637009 | E56: =oilGDPnominal!B64 -> 3178347 | F56: 3375221 | G56: =worldGDP!AU268 -> 0.704705 | H56: =oilGDPreal!B63 -> 1842154 | I56: -520988 | J56: 24238576 | K56: =US_GDP_deflator!B278 -> 101.918 | L56: 3644.7078 | M56: 3137.826 | N56: 2324.8917 | O56: =[1]quarterly!$B25 -> . | P56: 141.4844
A57: 2013.IV | B57: =oilGDPnominal!C65 -> 20256130 | C57: =consumption_investment_governme!F65 -> 14671139 | D57: =consumption_investment_governme!H65 -> 6658705 | E57: =oilGDPnominal!B65 -> 2974121 | F57: 3413480 | G57: =worldGDP!AU269 -> 0.535352 | H57: =oilGDPreal!B64 -> 1832244 | I57: -255165 | J57: 24429973 | K57: =US_GDP_deflator!B279 -> 102.517 | L57: 3952.7748 | M57: 3181.0536 | N57: 2301.7999 | O57: =[1]quarterly!$B26 -> 38.922977 | P57: 142.4193 | Q57: 4.1528209 | R57: 20.031 | S57: =R57-R53 -> 2.535
A58: 2014.I | B58: =oilGDPnominal!C66 -> 20681752 | C58: =consumption_investment_governme!F66 -> 14517583 | D58: =consumption_investment_governme!H66 -> 6612209 | E58: =oilGDPnominal!B66 -> 3030174 | F58: 3405399 | G58: =worldGDP!AU270 -> 0.392733 | H58: =oilGDPreal!B65 -> 1820177 | I58: 263288 | J58: 24829431 | K58: =US_GDP_deflator!B280 -> 102.937 | L58: 3255.9664 | M58: 3270.4276 | N58: 2357.6312 | O58: =[1]quarterly!$B27 -> 37.097129 | P58: 145.2347 | Q58: 4.8535189
A59: 2014.II | B59: =oilGDPnominal!C67 -> 21286897 | C59: =consumption_investment_governme!F67 -> 14911182 | D59: =consumption_investment_governme!H67 -> 6815031 | E59: =oilGDPnominal!B67 -> 3070315 | F59: 3619811 | G59: =worldGDP!AU271 -> 0.477451 | H59: =oilGDPreal!B66 -> 1805972 | I59: -277074 | J59: 25540887 | K59: =US_GDP_deflator!B281 -> 103.512 | L59: 3394.293 | M59: 3346.3264 | N59: 2482.2414 | O59: =[1]quarterly!$B28 -> 38.286171 | P59: 145.9975 | Q59: 4.6541424
A60: 2014.III | B60: =oilGDPnominal!C68 -> 21833223 | C60: =consumption_investment_governme!F68 -> 15235324 | D60: =consumption_investment_governme!H68 -> 7107289 | E60: =oilGDPnominal!B68 -> 2875783 | F60: 3692677 | G60: =worldGDP!AU272 -> 0.786243 | H60: =oilGDPreal!B67 -> 1761284 | I60: -711956 | J60: 25940400 | K60: =US_GDP_deflator!B282 -> 103.957 | L60: 3649.3816 | M60: 3280.4578 | N60: 2337.1765 | O60: =[1]quarterly!$B29 -> 37.680588 | P60: 146.2583 | Q60: 3.8966189
A61: 2014.IV | B61: =oilGDPnominal!C69 -> 21894080 | C61: =consumption_investment_governme!F69 -> 15348207 | D61: =consumption_investment_governme!H69 -> 7149702 | E61: =oilGDPnominal!B69 -> 2222517 | F61: 3825068 | G61: =worldGDP!AU273 -> 0.604721 | H61: =oilGDPreal!B68 -> 1748038 | I61: -906417 | J61: 25415613 | K61: =US_GDP_deflator!B283 -> 104.123 | L61: 3621.5185 | M61: 3268.0149 | N61: 2321.8956 | O61: =[1]quarterly!$B30 -> 37.970763 | P61: 142.9514 | Q61: 3.8003057 | R61: 27.973 | S61: =R61-R57 -> 7.942
A62: 2015.I | B62: =oilGDPnominal!C70 -> 21927458 | C62: =consumption_investment_governme!F70 -> 15462530 | D62: =consumption_investment_governme!H70 -> 6782799 | E62: =oilGDPnominal!B70 -> 1269754 | F62: 3615215 | G62: =worldGDP!AU274 -> 0.839818 | H62: =oilGDPreal!B69 -> 1720925 | I62: -906976 | J62: 25052739 | K62: =US_GDP_deflator!B284 -> 104.031 | L62: 2758.8455 | M62: 2803.6668 | N62: 1775.176 | O62: =[1]quarterly!$B31 -> 37.347193 | P62: 140.6189 | Q62: 3.8373228
A63: 2015.II | B63: =oilGDPnominal!C71 -> 21791229 | C63: =consumption_investment_governme!F71 -> 15298830 | D63: =consumption_investment_governme!H71 -> 6611841 | E63: =oilGDPnominal!B71 -> 1487119 | F63: 3611008 | G63: =worldGDP!AU275 -> 0.56266 | H63: =oilGDPreal!B70 -> 1698319 | I63: -863471 | J63: 25086195 | K63: =US_GDP_deflator!B285 -> 104.596 | L63: 3301.5659 | M63: 2813.1989 | N63: 1774.698 | O63: =[1]quarterly!$B32 -> 37.366302 | P63: 143.041 | Q63: 4.4695245
A64: 2015.III | B64: =oilGDPnominal!C72 -> 21693226 | C64: =consumption_investment_governme!F72 -> 15254879 | D64: =consumption_investment_governme!H72 -> 6482288 | E64: =oilGDPnominal!B72 -> 1250577 | F64: 3603087 | G64: =worldGDP!AU276 -> 0.511192 | H64: =oilGDPreal!B71 -> 1769317 | I64: -503537 | J64: 24779738 | K64: =US_GDP_deflator!B286 -> 104.926 | L64: 2154.9676 | M64: 2842.7651 | N64: 1768.8908 | O64: =[1]quarterly!$B33 -> 36.770738 | P64: 141.6614 | Q64: 4.2830051
A65: 2015.IV | B65: =oilGDPnominal!C73 -> 21478117 | C65: =consumption_investment_governme!F73 -> 14975671 | D65: =consumption_investment_governme!H73 -> 6513528 | E65: =oilGDPnominal!B73 -> 1145025 | F65: 3497818 | G65: =worldGDP!AU277 -> 0.299793 | H65: =oilGDPreal!B72 -> 1762405 | I65: -434096 | J65: 24371709 | K65: =US_GDP_deflator!B287 -> 104.937 | L65: 1930.4126 | M65: 2664.7105 | N65: 1576.6592 | O65: =[1]quarterly!$B34 -> 37.091328 | P65: 140.6442 | Q65: 4.7728349 | R65: 35.218 | S65: =R65-R61 -> 7.245
A66: 2016.I | B66: =oilGDPnominal!C74 -> 22334600 | C66: =consumption_investment_governme!F74 -> 15272408 | D66: =consumption_investment_governme!H74 -> 6363450 | E66: =oilGDPnominal!B74 -> 849907 | F66: 3632411 | G66: =worldGDP!AU278 -> 0.520353 | H66: =oilGDPreal!B73 -> 1757977 | I66: -90086 | J66: 24913573 | K66: =US_GDP_deflator!B288 -> 104.865 | L66: 2147.3297 | M66: 2792.5721 | N66: 1651.3737 | O66: =[1]quarterly!$B35 -> 35.415562 | P66: 144.8074 | Q66: 5.7111402
A67: 2016.II | B67: =oilGDPnominal!C75 -> 22124924 | C67: =consumption_investment_governme!F75 -> 14963699 | D67: =consumption_investment_governme!H75 -> 6222531 | E67: =oilGDPnominal!B75 -> 1106498 | F67: 3668803 | G67: =worldGDP!AU279 -> 0.362992 | H67: =oilGDPreal!B74 -> 1804990 | I67: 204498 | J67: 24926186 | K67: =US_GDP_deflator!B289 -> 105.592 | L67: 2301.1097 | M67: 2341.7587 | N67: 1251.8352 | O67: =[1]quarterly!$B36 -> 35.754432 | P67: 143.8484 | Q67: 5.322823
A68: 2016.III | B68: =oilGDPnominal!C76 -> 22108120 | C68: =consumption_investment_governme!F76 -> 14867587 | D68: =consumption_investment_governme!H76 -> 6262810 | E68: =oilGDPnominal!B76 -> 1096057 | F68: 3634828 | G68: =worldGDP!AU280 -> 0.362803 | H68: =oilGDPreal!B75 -> 1787677 | I68: 133735 | J68: 24910741 | K68: =US_GDP_deflator!B290 -> 105.95 | L68: 2939.7581 | M68: 2479.2813 | N68: 1290.055 | O68: =[1]quarterly!$B37 -> 34.800694 | P68: 143.902 | Q68: 5.2024938
A69: 2016.IV | B69: =oilGDPnominal!C77 -> 22195471 | C69: =consumption_investment_governme!F77 -> 14785998 | D69: =consumption_investment_governme!H77 -> 6231997 | E69: =oilGDPnominal!B77 -> 1222709 | F69: 3660552 | G69: =worldGDP!AU281 -> 0.892588 | H69: =oilGDPreal!B76 -> 1820505 | I69: 239791 | J69: 25187196 | K69: =US_GDP_deflator!B291 -> 106.469 | L69: 2903.1816 | M69: 2750.5562 | N69: 1505.1736 | O69: =[1]quarterly!$B38 -> 35.928595 | P69: 144.1704 | Q69: 5.2126029 | R69: 44.582 | S69: =R69-R65 -> 9.364
A70: 2017.I | B70: =oilGDPnominal!C78 -> 22866768 | C70: =consumption_investment_governme!F78 -> 15633202 | D70: =consumption_investment_governme!H78 -> 6549822 | E70: =oilGDPnominal!B78 -> 1370403 | F70: 3738191 | G70: =worldGDP!AU282 -> 0.714243 | H70: =oilGDPreal!B77 -> 1732160 | I70: 58816 | J70: 26000261 | K70: =US_GDP_deflator!B292 -> 107.01 | L70: 2622.0704 | M70: 2723.6118 | N70: 1484.0923 | O70: =[1]quarterly!$B39 -> 34.873099 | P70: 148.5905 | Q70: 4.3963009
A71: 2017.II | B71: =oilGDPnominal!C79 -> 22820041 | C71: =consumption_investment_governme!F79 -> 15645616 | D71: =consumption_investment_governme!H79 -> 6592246 | E71: =oilGDPnominal!B79 -> 1372271 | F71: 3773698 | G71: =worldGDP!AU283 -> 0.624989 | H71: =oilGDPreal!B78 -> 1786632 | I71: -231191 | J71: 25993550 | K71: =US_GDP_deflator!B293 -> 107.34 | L71: 2280.8399 | M71: 2634.7042 | N71: 1429.1333 | O71: =[1]quarterly!$B40 -> 35.478246 | P71: 146.9727 | Q71: 4.4921839
A72: 2017.III | B72: =oilGDPnominal!C80 -> 22781304 | C72: =consumption_investment_governme!F80 -> 15603095 | D72: =consumption_investment_governme!H80 -> 6635603 | E72: =oilGDPnominal!B80 -> 1368584 | F72: 3827485 | G72: =worldGDP!AU284 -> 0.723919 | H72: =oilGDPreal!B79 -> 1770356 | I72: -301557 | J72: 25960907 | K72: =US_GDP_deflator!B294 -> 107.872 | L72: 1764.8613 | M72: 2707.9588 | N72: 1446.3849 | O72: =[1]quarterly!$B41 -> 35.579561 | P72: 145.689 | Q72: 4.1385564
A73: 2017.IV | B73: =oilGDPnominal!C81 -> 22974643 | C73: =consumption_investment_governme!F81 -> 15596074 | D73: =consumption_investment_governme!H81 -> 6718585 | E73: =oilGDPnominal!B81 -> 1528719 | F73: 3857844 | G73: =worldGDP!AU285 -> 0.85884 | H73: =oilGDPreal!B80 -> 1719375 | I73: -314634 | J73: 26341144 | K73: =US_GDP_deflator!B295 -> 108.598 | L73: 1976.9927 | M73: 2726.8486 | N73: 1424.775 | O73: =[1]quarterly!$B42 -> 36.246103 | P73: 146.7278 | Q73: 4.6236508 | R73: 47.03 | S73: =R73-R69 -> 2.448
A74: 2018.I | B74: =oilGDPnominal!C82 -> 23003445 | C74: =consumption_investment_governme!F82 -> 15690603 | D74: =consumption_investment_governme!H82 -> 6900492 | E74: =oilGDPnominal!B82 -> 1614278 | F74: 3856675 | G74: =worldGDP!AU286 -> 0.583256 | H74: =oilGDPreal!B81 -> 1612950 | I74: 72036 | J74: 26510612 | K74: =US_GDP_deflator!B296 -> 109.237 | L74: 1773.1375 | M74: 2948.8317 | N74: 1574.7531 | O74: =[1]quarterly!$B43 -> 35.911531 | P74: 149.2499 | Q74: 4.4344972
A75: 2018.II | B75: =oilGDPnominal!C83 -> 23257274 | C75: =consumption_investment_governme!F83 -> 15950509 | D75: =consumption_investment_governme!H83 -> 6940983 | E75: =oilGDPnominal!B83 -> 1629986 | F75: 3960438 | G75: =worldGDP!AU287 -> 0.510527 | H75: =oilGDPreal!B82 -> 1619142 | I75: -232201 | J75: 26761827 | K75: =US_GDP_deflator!B297 -> 110.176 | L75: 1703.0424 | M75: 3326.8464 | N75: 1809.7539 | O75: =[1]quarterly!$B44 -> 35.744142 | P75: 149.1475 | Q75: 4.1371362
A76: 2018.III | B76: =oilGDPnominal!C84 -> 23360540 | C76: =consumption_investment_governme!F84 -> 16185856 | D76: =consumption_investment_governme!H84 -> 6900122 | E76: =oilGDPnominal!B84 -> 1793243 | F76: 3967589 | G76: =worldGDP!AU288 -> 0.224238 | H76: =oilGDPreal!B83 -> 1678356 | I76: -460088 | J76: 27078404 | K76: =US_GDP_deflator!B298 -> 110.614 | L76: 1710.4745 | M76: 3052.6917 | N76: 1679.2234 | O76: =[1]quarterly!$B45 -> 35.751771 | P76: 149.7631 | Q76: 4.0261331
A77: 2018.IV | B77: =oilGDPnominal!C85 -> 23415803 | C77: =consumption_investment_governme!F85 -> 16375332 | D77: =consumption_investment_governme!H85 -> 6776087 | E77: =oilGDPnominal!B85 -> 1881384 | F77: 4044508 | G77: =worldGDP!AU289 -> 0.27391 | H77: =oilGDPreal!B84 -> 1652169 | I77: -619682 | J77: 27211165 | K77: =US_GDP_deflator!B299 -> 111.14 | L77: 1271.3639 | M77: 2903.7824 | N77: 1610.3558 | O77: =[1]quarterly!$B46 -> 36.187508 | P77: 150.4715 | Q77: 3.6887066 | R77: 49.087 | S77: =R77-R73 -> 2.057
A78: 2019.I | B78: =oilGDPnominal!C86 -> 23275978 | C78: =consumption_investment_governme!F86 -> 16076224 | D78: =consumption_investment_governme!H86 -> 6645357 | E78: =oilGDPnominal!B86 -> 1656263 | F78: 3899728 | G78: =worldGDP!AU290 -> 0.633289 | H78: =oilGDPreal!B85 -> 1635569 | I78: -154524 | J78: 26914897 | K78: =US_GDP_deflator!B300 -> 111.424 | L78: 1533.6291 | M78: 3012.2159 | N78: 1556.1891 | O78: =[1]quarterly!$B47 -> 34.170604 | P78: 149.7714 | Q78: 4.6093948
A79: 2019.II | B79: =oilGDPnominal!C87 -> 23398876 | C79: =consumption_investment_governme!F87 -> 16333602 | D79: =consumption_investment_governme!H87 -> 6796735 | E79: =oilGDPnominal!B87 -> 1689993 | F79: 3898304 | G79: =worldGDP!AU291 -> 0.373454 | H79: =oilGDPreal!B86 -> 1642589 | I79: -154089 | J79: 27058331 | K79: =US_GDP_deflator!B301 -> 112.141 | L79: 1719.5593 | M79: 2998.1497 | N79: 1507.5461 | O79: =[1]quarterly!$B48 -> 34.703233 | P79: 150.2476 | Q79: 4.4480752
A80: 2019.III | B80: =oilGDPnominal!C88 -> 23374518 | C80: =consumption_investment_governme!F88 -> 16336510 | D80: =consumption_investment_governme!H88 -> 6734396 | E80: =oilGDPnominal!B88 -> 1684037 | F80: 3891915 | G80: =worldGDP!AU292 -> 0.428793 | H80: =oilGDPreal!B87 -> 1687990 | I80: 36989 | J80: 27054758 | K80: =US_GDP_deflator!B302 -> 112.531 | L80: 1664.6409 | M80: 2851.1781 | N80: 1442.2185 | O80: =[1]quarterly!$B49 -> 34.89101 | P80: 149.6776 | Q80: 4.8556321
A81: 2019.IV | B81: =oilGDPnominal!C89 -> 23332485 | C81: =consumption_investment_governme!F89 -> 16252564 | D81: =consumption_investment_governme!H89 -> 6644595 | E81: =oilGDPnominal!B89 -> 1628495 | F81: 3893234 | G81: =worldGDP!AU293 -> 0.169522 | H81: =oilGDPreal!B88 -> 1621169 | I81: 314777 | J81: 27080023 | K81: =US_GDP_deflator!B303 -> 112.95 | O81: =[1]quarterly!$B50 -> 36.164914 | P81: 151.9297 | Q81: 3.8416174 | R81: 51.411 | S81: =R81-R77 -> 2.324
A82: 2020.I | K82: =US_GDP_deflator!B304 -> 113.415

Sheet monthly
B1: Foreign_interest_rate | C1: Oil_price | D1: EMBI | E1: Government_consumption | F1: Government_wages | G1: Government_FBKF | H1: Government_transfers | I1: Consumption_taxreceipts | J1: Income_taxreceipts | K1: Laborincome_taxreceipts | L1: Capitalincome_taxreceipts | M1: Private_externaldebt | N1: Public_externaldebt | O1: Public_internaldebt | P1: rer | Q1: oil_production
A2: 36526 | B2: 5.499 | C2: =oilprice!B2 -> 22.84 | D2: =EMBI!B2 -> 3672.8 | E2: =g_consumption!B2 -> 28.343359 | F2: =g_wages!B2 -> 5.0834107 | G2: =g_fbkf!B2 -> 28.949103 | H2: =g_transfers!B2 -> 30.260721 | I2: =tax_receipts!C2 -> 56.500429 | J2: =tax_receipts!F2 -> 12.971592 | K2: =J2*tax_receipts!G2/(tax_receipts!G2+tax_receipts!H2) -> 0.50686816 | L2: =J2-K2 -> 12.464724 | M2: =debt!B2 -> 2568.8 | N2: =debt!C2 -> 13646.8 | O2: =debt!D2 -> 3303.4 | P2: =real_exchange_rate!B2 -> 214.06015
A3: 36557 | B3: 5.727 | C3: =oilprice!B3 -> 24.26 | D3: =EMBI!B3 -> 4043.05 | E3: =g_consumption!B3 -> 22.008969 | F3: =g_wages!B3 -> 76.140046 | G3: =g_fbkf!B3 -> 33.752032 | H3: =g_transfers!B3 -> 68.043456 | I3: =tax_receipts!C3 -> 53.671587 | J3: =tax_receipts!F3 -> 13.401321 | K3: =J3*tax_receipts!G3/(tax_receipts!G3+tax_receipts!H3) -> 7.2685158 | L3: =J3-K3 -> 6.132805 | M3: =debt!B3 -> 2532.9 | N3: =debt!C3 -> 13699.5 | O3: =debt!D3 -> 3289.7 | P3: =real_exchange_rate!B3 -> 196.54991
A4: 36586 | B4: 5.863913 | C4: =oilprice!B4 -> 24.88 | D4: =EMBI!B4 -> 3115.2174 | E4: =g_consumption!B4 -> 26.232688 | F4: =g_wages!B4 -> 47.612526 | G4: =g_fbkf!B4 -> 44.729746 | H4: =g_transfers!B4 -> 53.702372 | I4: =tax_receipts!C4 -> 53.359876 | J4: =tax_receipts!F4 -> 18.682313 | K4: =J4*tax_receipts!G4/(tax_receipts!G4+tax_receipts!H4) -> 2.5440414 | L4: =J4-K4 -> 16.138272 | M4: =debt!B4 -> 2440.5 | N4: =debt!C4 -> 13770 | O4: =debt!D4 -> 3295.3 | P4: =real_exchange_rate!B4 -> 183.59854
A5: 36617 | B5: 5.8215789 | C5: =oilprice!B5 -> 21.79 | D5: =EMBI!B5 -> 3372.0526 | E5: =g_consumption!B5 -> 20.681453 | F5: =g_wages!B5 -> 45.337874 | G5: =g_fbkf!B5 -> 70.471063 | H5: =g_transfers!B5 -> 72.701219 | I5: =tax_receipts!C5 -> 61.710057 | J5: =tax_receipts!F5 -> 49.929 | K5: =J5*tax_receipts!G5/(tax_receipts!G5+tax_receipts!H5) -> 6.9671429 | L5: =J5-K5 -> 42.961857 | M5: =debt!B5 -> 2381.4 | N5: =debt!C5 -> 13969.4 | O5: =debt!D5 -> 3256.9 | P5: =real_exchange_rate!B5 -> 166.29552
A6: 36647 | B6: 5.9945455 | C6: =oilprice!B6 -> 24.35 | D6: =EMBI!B6 -> 3971.7273 | E6: =g_consumption!B6 -> 28.204444 | F6: =g_wages!B6 -> 47.78272 | G6: =g_fbkf!B6 -> 58.448924 | H6: =g_transfers!B6 -> 47.719765 | I6: =tax_receipts!C6 -> 59.4237 | J6: =tax_receipts!F6 -> 19.404 | K6: =J6*tax_receipts!G6/(tax_receipts!G6+tax_receipts!H6) -> 6.9855073 | L6: =J6-K6 -> 12.418493 | M6: =debt!B6 -> 2409.7 | N6: =debt!C6 -> 14011.6 | O6: =debt!D6 -> 3230.9 | P6: =real_exchange_rate!B6 -> 155.41638
A7: 36678 | B7: 5.8618182 | C7: =oilprice!B7 -> 26.59 | D7: =EMBI!B7 -> 4416.2273 | E7: =g_consumption!B7 -> 34.471106 | F7: =g_wages!B7 -> 57.056738 | G7: =g_fbkf!B7 -> 67.945128 | H7: =g_transfers!B7 -> 65.212784 | I7: =tax_receipts!C7 -> 80.155 | J7: =tax_receipts!F7 -> 21.167 | K7: =J7*tax_receipts!G7/(tax_receipts!G7+tax_receipts!H7) -> 5.2425262 | L7: =J7-K7 -> 15.924474 | M7: =debt!B7 -> 2389 | N7: =debt!C7 -> 14073.5 | O7: =debt!D7 -> 3219.9 | P7: =real_exchange_rate!B7 -> 149.30333
A8: 36708 | B8: 6.1425 | C8: =oilprice!B8 -> 24.19 | D8: =EMBI!B8 -> 3795.75 | E8: =g_consumption!B8 -> 34.365728 | F8: =g_wages!B8 -> 62.032085 | G8: =g_fbkf!B8 -> 67.404171 | H8: =g_transfers!B8 -> 54.83377 | I8: =tax_receipts!C8 -> 75.1381 | J8: =tax_receipts!F8 -> 28.1404 | K8: =J8*tax_receipts!G8/(tax_receipts!G8+tax_receipts!H8) -> 3.7716353 | L8: =J8-K8 -> 24.368765 | M8: =debt!B8 -> 2437.3 | N8: =debt!C8 -> 13914.5 | O8: =debt!D8 -> 3207.1 | P8: =real_exchange_rate!B8 -> 145.46973
A9: 36739 | B9: 6.2773913 | C9: =oilprice!B9 -> 25.74 | D9: =EMBI!B9 -> 2574.6957 | E9: =g_consumption!B9 -> 34.603116 | F9: =g_wages!B9 -> 70.840883 | G9: =g_fbkf!B9 -> 73.141681 | H9: =g_transfers!B9 -> 87.676633 | I9: =tax_receipts!C9 -> 86.7894 | J9: =tax_receipts!F9 -> 22.751 | K9: =J9*tax_receipts!G9/(tax_receipts!G9+tax_receipts!H9) -> 8.314871 | L9: =J9-K9 -> 14.436129 | M9: =debt!B9 -> 2286.3 | N9: =debt!C9 -> 11226.3 | O9: =debt!D9 -> 3203.3 | P9: =real_exchange_rate!B9 -> 142.25779
A10: 36770 | B10: 6.175 | C10: =oilprice!B10 -> 27.96 | D10: =EMBI!B10 -> 1297.05 | E10: =g_consumption!B10 -> 34.606416 | F10: =g_wages!B10 -> 63.421064 | G10: =g_fbkf!B10 -> 86.696516 | H10: =g_transfers!B10 -> 48.793556 | I10: =tax_receipts!C10 -> 89.129 | J10: =tax_receipts!F10 -> 28.82 | K10: =J10*tax_receipts!G10/(tax_receipts!G10+tax_receipts!H10) -> 5.6641624 | L10: =J10-K10 -> 23.155838 | M10: =debt!B10 -> 2331.7 | N10: =debt!C10 -> 11257.8 | O10: =debt!D10 -> 3164.8 | P10: =real_exchange_rate!B10 -> 136.55919
A11: 36800 | B11: 6.2947619 | C11: =oilprice!B11 -> 27.91 | D11: =EMBI!B11 -> 1300.6667 | E11: =g_consumption!B11 -> 48.39668 | F11: =g_wages!B11 -> 68.159542 | G11: =g_fbkf!B11 -> 89.389387 | H11: =g_transfers!B11 -> 71.999165 | I11: =tax_receipts!C11 -> 89.424 | J11: =tax_receipts!F11 -> 25.128 | K11: =J11*tax_receipts!G11/(tax_receipts!G11+tax_receipts!H11) -> 9.2846337 | L11: =J11-K11 -> 15.843366 | M11: =debt!B11 -> 2318.4 | N11: =debt!C11 -> 11186.1 | O11: =debt!D11 -> 3129.3 | P11: =real_exchange_rate!B11 -> 132.41475
A12: 36831 | B12: 6.3561905 | C12: =oilprice!B12 -> 27.27 | D12: =EMBI!B12 -> 1352.5238 | E12: =g_consumption!B12 -> 44.926558 | F12: =g_wages!B12 -> 93.931982 | G12: =g_fbkf!B12 -> 66.72828 | H12: =g_transfers!B12 -> 69.518518 | I12: =tax_receipts!C12 -> 98.509 | J12: =tax_receipts!F12 -> 25.063 | K12: =J12*tax_receipts!G12/(tax_receipts!G12+tax_receipts!H12) -> 13.56032 | L12: =J12-K12 -> 11.50268 | M12: =debt!B12 -> 2292.7 | N12: =debt!C12 -> 11161.9 | O12: =debt!D12 -> 3113.9 | P12: =real_exchange_rate!B12 -> 129.92809
A13: 36861 | B13: 5.937 | C13: =oilprice!B13 -> 20.58 | D13: =EMBI!B13 -> 1451.1 | E13: =g_consumption!B13 -> 53.045543 | F13: =g_wages!B13 -> 123.59982 | G13: =g_fbkf!B13 -> 94.582664 | H13: =g_transfers!B13 -> 209.58083 | I13: =tax_receipts!C13 -> 106.589 | J13: =tax_receipts!F13 -> 28.029 | K13: =J13*tax_receipts!G13/(tax_receipts!G13+tax_receipts!H13) -> 7.2290678 | L13: =J13-K13 -> 20.799932 | M13: =debt!B13 -> 2229.1 | N13: =debt!C13 -> 11335.4 | O13: =debt!D13 -> 2833.5 | P13: =real_exchange_rate!B13 -> 127.33782
... A49: 37956 | B49: 0.91454545 | C49: =oilprice!B49 -> 26.1 | D49: =EMBI!B49 -> 840.36364 | E49: =g_consumption!B49 -> 81.542 | F49: =g_wages!B49 -> 303.51 | G49: =g_fbkf!B49 -> 142.4708 | H49: =g_transfers!B49 -> 113.23333 | I49: =tax_receipts!C49 -> 155.26783 | J49: =tax_receipts!F49 -> 35.373268 | K49: =J49*tax_receipts!G49/(tax_receipts!G49+tax_receipts!H49) -> 8.0676312 | L49: =J49-K49 -> 27.305637 | M49: =debt!B49 -> 5101.9 | N49: =debt!C49 -> 11493.2 | O49: =debt!D49 -> 3016.2 | P49: =real_exchange_rate!B49 -> 97.601484
A50: 37987 | B50: 0.9005 | C50: =oilprice!B50 -> 26.91 | D50: =EMBI!B50 -> 724.36842 | E50: =g_consumption!B50 -> 68.809364 | F50: =g_wages!B50 -> 183.50193 | G50: =g_fbkf!B50 -> 44.500286 | H50: =g_transfers!B50 -> 90.885417 | I50: =tax_receipts!C50 -> 177.39053 | J50: =tax_receipts!F50 -> 61.678288 | K50: =J50*tax_receipts!G50/(tax_receipts!G50+tax_receipts!H50) -> 29.214398 | L50: =J50-K50 -> 32.46389 | M50: =debt!B50 -> 5534.3 | N50: =debt!C50 -> 11471.1 | O50: =debt!D50 -> 2965.9 | P50: =real_exchange_rate!B50 -> 98.886259 | Q50: 15728.453
A51: 38018 | B51: 0.94473684 | C51: =oilprice!B51 -> 26.91 | D51: =EMBI!B51 -> 746 | E51: =g_consumption!B51 -> 75.029731 | F51: =g_wages!B51 -> 214.6163 | G51: =g_fbkf!B51 -> 100.87669 | H51: =g_transfers!B51 -> 96.719843 | I51: =tax_receipts!C51 -> 129.74246 | J51: =tax_receipts!F51 -> 32.63717 | K51: =J51*tax_receipts!G51/(tax_receipts!G51+tax_receipts!H51) -> 19.812754 | L51: =J51-K51 -> 12.824416 | M51: =debt!B51 -> 5461.4 | N51: =debt!C51 -> 11393.2 | O51: =debt!D51 -> 3056.6 | P51: =real_exchange_rate!B51 -> 98.192066 | Q51: 15163.05
A52: 38047 | B52: 0.95347826 | C52: =oilprice!B52 -> 26.28 | D52: =EMBI!B52 -> 723.59091 | E52: =g_consumption!B52 -> 73.662607 | F52: =g_wages!B52 -> 218.068 | G52: =g_fbkf!B52 -> 150.0344 | H52: =g_transfers!B52 -> 98.224714 | I52: =tax_receipts!C52 -> 158.58708 | J52: =tax_receipts!F52 -> 49.567963 | K52: =J52*tax_receipts!G52/(tax_receipts!G52+tax_receipts!H52) -> 41.576216 | L52: =J52-K52 -> 7.9917475 | M52: =debt!B52 -> 5656.4 | N52: =debt!C52 -> 11369.6 | O52: =debt!D52 -> 3159.7 | P52: =real_exchange_rate!B52 -> 97.342456 | Q52: 15210.939
A53: 38078 | B53: 0.95809524 | C53: =oilprice!B53 -> 26.96 | D53: =EMBI!B53 -> 762.95238 | E53: =g_consumption!B53 -> 82.760617 | F53: =g_wages!B53 -> 209.56601 | G53: =g_fbkf!B53 -> 134.70646 | H53: =g_transfers!B53 -> 122.58889 | I53: =tax_receipts!C53 -> 158.899 | J53: =tax_receipts!F53 -> 176.16476 | K53: =J53*tax_receipts!G53/(tax_receipts!G53+tax_receipts!H53) -> 1.5709461 | L53: =J53-K53 -> 174.59382 | M53: =debt!B53 -> 5612 | N53: =debt!C53 -> 11218.3 | O53: =debt!D53 -> 3230.1 | P53: =real_exchange_rate!B53 -> 96.762235 | Q53: 15992.684
A54: 38108 | B54: 1.0395 | C54: =oilprice!B54 -> 31.19 | D54: =EMBI!B54 -> 920.5 | E54: =g_consumption!B54 -> 83.440752 | F54: =g_wages!B54 -> 218.31842 | G54: =g_fbkf!B54 -> 146.649 | H54: =g_transfers!B54 -> 109.39675 | I54: =tax_receipts!C54 -> 157.1788 | J54: =tax_receipts!F54 -> 40.013235 | K54: =J54*tax_receipts!G54/(tax_receipts!G54+tax_receipts!H54) -> 10.863038 | L54: =J54-K54 -> 29.150197 | M54: =debt!B54 -> 5013.3 | N54: =debt!C54 -> 11236.3 | O54: =debt!D54 -> 3249.6 | P54: =real_exchange_rate!B54 -> 96.472125 | Q54: 16404.33
A55: 38139 | B55: 1.2880952 | C55: =oilprice!B55 -> 29.86 | D55: =EMBI!B55 -> 886.09091 | E55: =g_consumption!B55 -> 86.025 | F55: =g_wages!B55 -> 197.38619 | G55: =g_fbkf!B55 -> 141.81351 | H55: =g_transfers!B55 -> 125.55174 | I55: =tax_receipts!C55 -> 157.17638 | J55: =tax_receipts!F55 -> 35.306512 | K55: =J55*tax_receipts!G55/(tax_receipts!G55+tax_receipts!H55) -> 13.622886 | L55: =J55-K55 -> 21.683625 | M55: =debt!B55 -> 5389.5 | N55: =debt!C55 -> 11165.1 | O55: =debt!D55 -> 3270.9 | P55: =real_exchange_rate!B55 -> 97.601484 | Q55: 16127.136
A56: 38169 | B56: 1.357619 | C56: =oilprice!B56 -> 31.29 | D56: =EMBI!B56 -> 921.61905 | E56: =g_consumption!B56 -> 88.357 | F56: =g_wages!B56 -> 217.9766 | G56: =g_fbkf!B56 -> 109.84181 | H56: =g_transfers!B56 -> 112.18547 | I56: =tax_receipts!C56 -> 158.66888 | J56: =tax_receipts!F56 -> 77.432545 | K56: =J56*tax_receipts!G56/(tax_receipts!G56+tax_receipts!H56) -> 25.655206 | L56: =J56-K56 -> 51.777339 | M56: =debt!B56 -> 5318.7 | N56: =debt!C56 -> 11090.7 | O56: =debt!D56 -> 3325.4 | P56: =real_exchange_rate!B56 -> 98.782648 | Q56: 16451.144
A57: 38200 | B57: 1.5031818 | C57: =oilprice!B57 -> 34.05 | D57: =EMBI!B57 -> 836.13636 | E57: =g_consumption!B57 -> 91.747 | F57: =g_wages!B57 -> 210.3767 | G57: =g_fbkf!B57 -> 113.16003 | H57: =g_transfers!B57 -> 134.88116 | I57: =tax_receipts!C57 -> 162.06584 | J57: =tax_receipts!F57 -> 39.392742 | K57: =J57*tax_receipts!G57/(tax_receipts!G57+tax_receipts!H57) -> 12.894474 | L57: =J57-K57 -> 26.498268 | M57: =debt!B57 -> 5432.9 | N57: =debt!C57 -> 11028.4 | O57: =debt!D57 -> 3480.1 | P57: =real_exchange_rate!B57 -> 98.927704 | Q57: 16474.526
A58: 38231 | B58: 1.6814286 | C58: =oilprice!B58 -> 32.52 | D58: =EMBI!B58 -> 801.7619 | E58: =g_consumption!B58 -> 87.895 | F58: =g_wages!B58 -> 219.099 | G58: =g_fbkf!B58 -> 118.36218 | H58: =g_transfers!B58 -> 138.8587 | I58: =tax_receipts!C58 -> 146.16421 | J58: =tax_receipts!F58 -> 71.718163 | K58: =J58*tax_receipts!G58/(tax_receipts!G58+tax_receipts!H58) -> 19.673466 | L58: =J58-K58 -> 52.044697 | M58: =debt!B58 -> 5804 | N58: =debt!C58 -> 11072 | O58: =debt!D58 -> 3491.2 | P58: =real_exchange_rate!B58 -> 99.37323 | Q58: 15662.468
A59: 38261 | B59: 1.7945 | C59: =oilprice!B59 -> 37.18 | D59: =EMBI!B59 -> 731.05 | E59: =g_consumption!B59 -> 80.73 | F59: =g_wages!B59 -> 200.539 | G59: =g_fbkf!B59 -> 137.47891 | H59: =g_transfers!B59 -> 118.06564 | I59: =tax_receipts!C59 -> 170.9505 | J59: =tax_receipts!F59 -> 39.143948 | K59: =J59*tax_receipts!G59/(tax_receipts!G59+tax_receipts!H59) -> 3.794402 | L59: =J59-K59 -> 35.349546 | M59: =debt!B59 -> 5849.1 | N59: =debt!C59 -> 11045.3 | O59: =debt!D59 -> 3624.2 | P59: =real_exchange_rate!B59 -> 100.12959 | Q59: 16401.195
A60: 38292 | B60: 2.1075 | C60: =oilprice!B60 -> 30.58 | D60: =EMBI!B60 -> 721.95 | E60: =g_consumption!B60 -> 76.503 | F60: =g_wages!B60 -> 204.63044 | G60: =g_fbkf!B60 -> 103.92969 | H60: =g_transfers!B60 -> 138.01434 | I60: =tax_receipts!C60 -> 170.22556 | J60: =tax_receipts!F60 -> 40.903657 | K60: =J60*tax_receipts!G60/(tax_receipts!G60+tax_receipts!H60) -> 7.0681122 | L60: =J60-K60 -> 33.835544 | M60: =debt!B60 -> 6157.4 | N60: =debt!C60 -> 11051.8 | O60: =debt!D60 -> 3570.1 | P60: =real_exchange_rate!B60 -> 101.50762 | Q60: 16010.756
A61: 38322 | B61: 2.2227273 | C61: =oilprice!B61 -> 25.67 | D61: =EMBI!B61 -> 710.59091 | E61: =g_consumption!B61 -> 138.29711 | F61: =g_wages!B61 -> 291.943 | G61: =g_fbkf!B61 -> 191.56598 | H61: =g_transfers!B61 -> 184.11227 | I61: =tax_receipts!C61 -> 174.69513 | J61: =tax_receipts!F61 -> 37.97234 | K61: =J61*tax_receipts!G61/(tax_receipts!G61+tax_receipts!H61) -> 21.195 | L61: =J61-K61 -> 16.77734 | M61: =debt!B61 -> 5948.5 | N61: =debt!C61 -> 11061.6 | O61: =debt!D61 -> 3489.1 | P61: =real_exchange_rate!B61 -> 103.09286 | Q61: 16688.453
... A241: 43800 | B241: 1.5652381 | C241: =oilprice!B241 -> 54.026274 | D241: =EMBI!B241 -> 937.87097 | E241: =g_consumption!B241 -> 0 | F241: =g_wages!B241 -> 0 | G241: =g_fbkf!B241 -> 0 | H241: =g_transfers!B241 -> 0 | I241: =tax_receipts!C241 -> 560.59832 | J241: =tax_receipts!F241 -> 252.67936 | K241: =J241*tax_receipts!G241/(tax_receipts!G241+tax_receipts!H241) -> 117.6798 | L241: =J241-K241 -> 134.99956 | M241: =debt!B241 -> 11174.868 | N241: =debt!C241 -> 41495.584 | O241: =debt!D241 -> 15843.636 | P241: =real_exchange_rate!B241 -> 102.66404 | Q241: 16800.809

Sheet annual
B1: I_g | C1: I_p | D1: I_total | E1: Government_debt
A2: 2000 | B2: 957 | C2: 2526 | D2: 3483
A3: 2001 | B3: 1524 | C3: 3138 | D3: 4662
A4: 2002 | B4: 1812 | C4: 4095 | D4: 5907
A5: 2003 | B5: 1824 | C5: 4416 | D5: 6240 | E5: 45.062
A6: 2004 | B6: 1941 | C6: 5268 | D6: 7209 | E6: 38.665
A7: 2005 | B7: 1943 | C7: 6533 | D7: 8476 | E7: 34.7
A8: 2006 | B8: 1982 | C8: 7777 | D8: 9759 | E8: 31.128
A9: 2007 | B9: 3337 | C9: 7257 | D9: 10594 | E9: 28.464
A10: 2008 | B10: 4454 | C10: 9365 | D10: 13819 | E10: 24.229
A11: 2009 | B11: 6794 | C11: 7464 | D11: 14258 | E11: 18.568
A12: 2010 | B12: 7576 | C12: 9551 | D12: 17127 | E12: 17.696
A13: 2011 | B13: 8744 | C13: 11727 | D13: 20471 | E13: 16.789
A14: 2012 | B14: 11065.548 | C14: 12642.29 | D14: 23707.838 | E14: 17.496
A15: 2013 | B15: 15155 | C15: 11057 | D15: 26212 | E15: 20.031
A16: 2014 | B16: 15953 | C16: 11731 | D16: 27684 | E16: 27.973
A17: 2015 | B17: 13344 | C17: 13046 | D17: 26390 | E17: 35.218
A18: 2016 sd | B18: 11463.735 | C18: 13617.053 | D18: 25080.788 | E18: 44.582
A19: 2017 p | B19: 11096.674 | C19: 15399.582 | D19: 26496.256 | E19: 47.03
A20: 2018 p | B20: 8619.493 | C20: 18898.191 | D20: 27517.684 | E20: 49.087
A21: 2019 p | B21: 8468 | C21: 18439.554 | D21: 26908 | E21: 51.411

Sheet real_exchange_rate
B1: rer
A2: 36526 | B2: 214.06015
A3: 36557 | B3: 196.54991
A4: 36586 | B4: 183.59854
A5: 36617 | B5: 166.29552
A6: 36647 | B6: 155.41638
A7: 36678 | B7: 149.30333
A8: 36708 | B8: 145.46973
A9: 36739 | B9: 142.25779
A10: 36770 | B10: 136.55919
A11: 36800 | B11: 132.41475
A12: 36831 | B12: 129.92809
A13: 36861 | B13: 127.33782
... A241: 43800 | B241: 102.66404

Sheet debt
B1: Private_externaldebt | C1: Public_externaldebt | D1: Public_internaldebt
A2: 36526 | B2: 2568.8 | C2: 13646.8 | D2: 3303.4
A3: 36557 | B3: 2532.9 | C3: 13699.5 | D3: 3289.7
A4: 36586 | B4: 2440.5 | C4: 13770 | D4: 3295.3
A5: 36617 | B5: 2381.4 | C5: 13969.4 | D5: 3256.9
A6: 36647 | B6: 2409.7 | C6: 14011.6 | D6: 3230.9
A7: 36678 | B7: 2389 | C7: 14073.5 | D7: 3219.9
A8: 36708 | B8: 2437.3 | C8: 13914.5 | D8: 3207.1
A9: 36739 | B9: 2286.3 | C9: 11226.3 | D9: 3203.3
A10: 36770 | B10: 2331.7 | C10: 11257.8 | D10: 3164.8
A11: 36800 | B11: 2318.4 | C11: 11186.1 | D11: 3129.3
A12: 36831 | B12: 2292.7 | C12: 11161.9 | D12: 3113.9
A13: 36861 | B13: 2229.1 | C13: 11335.4 | D13: 2833.5
... A241: 43800 | B241: 11174.868 | C241: 41495.584 | D241: 15843.636

Sheet consumption_investment_governme
A1: Menú Principal
A4: OFERTA Y UTILIZACIÓN FINAL DE BIENES Y SERVICIOS
A5: Miles de US dólares
A7: Variables | B7: P.I.B. | C7: Importaciones de bienes y servicios (fob) | D7: Oferta final | E7: Demanda interna | F7: Gasto de Consumo final Hogares (*) | G7: Gasto de Consumo final Gobierno General | H7: FBKF | I7: Variación de existencias | J7: Exportaciones de bienes y servicios (fob) | K7: Utilización final | M7: trade balance
A8: Trimestres
A10: 2000.I | B10: 3819126 | C10: 1120302 | D10: 4939428 | E10: 3433046 | F10: 2445053 | G10: 175154 | H10: 723232 | I10: 89607 | J10: 1506382 | K10: 4939428 | M10: =J10-C10 -> 386080
A11: 2000.II | B11: 4402479 | C11: 1165977 | D11: 5568456 | E11: 4093878 | F11: 2841942 | G11: 389776 | H11: 821301 | I11: 40859 | J11: 1474578 | K11: 5568456 | M11: =J11-C11 -> 308601
A12: 2000.III | B12: 4906653 | C12: 1344968 | D12: 6251621 | E12: 4758217 | F12: 3164392 | G12: 516011 | H12: 947040 | I12: 130774 | J12: 1493404 | K12: 6251621 | M12: =J12-C12 -> 148436
A13: 2000.IV | B13: 5190343 | C13: 1376539 | D13: 6566882 | E13: 5155931 | F13: 3378859 | G13: 631921 | H13: 991669 | I13: 153482 | J13: 1410951 | K13: 6566882 | M13: =J13-C13 -> 34412
A14: 2001.I | B14: 5904082 | C14: 1558735 | D14: 7462817 | E14: 5965283 | F14: 4198533 | G14: 577101 | H14: 1053487 | I14: 136162 | J14: 1497534 | K14: 7462817 | M14: =J14-C14 -> -61201
A15: 2001.II | B15: 6069620 | C15: 1656183 | D15: 7725803 | E15: 6337242 | F15: 4375885 | G15: 582004 | H15: 1147563 | I15: 231790 | J15: 1388561 | K15: 7725803 | M15: =J15-C15 -> -267622
A16: 2001.III | B16: 6159609 | C16: 1693120 | D16: 7852729 | E16: 6445033 | F16: 4454342 | G16: 551198 | H16: 1212577 | I16: 226916 | J16: 1407696 | K16: 7852729 | M16: =J16-C16 -> -285424
A17: 2001.IV | B17: 6335013 | C17: 1826210 | D17: 8161223 | E17: 6772797 | F17: 4711126 | G17: 601693 | H17: 1247952 | I17: 212026 | J17: 1388426 | K17: 8161223 | M17: =J17-C17 -> -437784
A18: 2002.I | B18: 6737551 | C18: 1840720 | D18: 8578271 | E18: 7158409 | F18: 4935609 | G18: 622826 | H18: 1388559 | I18: 211415 | J18: 1419862 | K18: 8578271 | M18: =J18-C18 -> -420858
A19: 2002.II | B19: 7086627 | C19: 2073234 | D19: 9159861 | E19: 7644751 | F19: 5165450 | G19: 689584 | H19: 1460080 | I19: 329637 | J19: 1515110 | K19: 9159861 | M19: =J19-C19 -> -558124
A20: 2002.III | B20: 7294132 | C20: 2054515 | D20: 9348647 | E20: 7776383 | F20: 5297262 | G20: 721936 | H20: 1514534 | I20: 242651 | J20: 1572264 | K20: 9348647 | M20: =J20-C20 -> -482251
A21: 2002.IV | B21: 7430635 | C21: 1992169 | D21: 9422804 | E21: 7794194 | F21: 5401579 | G21: 772712 | H21: 1543432 | I21: 76471 | J21: 1628610 | K21: 9422804 | M21: =J21-C21 -> -363559
... A89: 2019.IV | B89: 26817695 | C89: 6039016 | D89: 32856711 | E89: 26502918 | F89: 16252564 | G89: 3893234 | H89: 6644595 | I89: -287475 | J89: 6353793 | K89: 32856711 | M89: =J89-C89 -> 314777
A90: 2020.I | B90: 25878598 | C90: 5721667 | D90: 31600265 | E90: 25431100 | F90: 15861715 | G90: 3655204 | H90: 6223560 | I90: -309379 | J90: 6169165 | K90: 31600265
A92: (*) incluye el gasto de consumo de las Instituciones sin fines de lucro al servicio de los hogares, ISFLSH
A93: Elaboración: BANCO CENTRAL DEL ECUADOR

Sheet oilGDPreal
A1: Menú Principal
A3: VALOR AGREGADO BRUTO PETROLERO (*) Y NO PETROLERO
B5: Miles de US dólares, 2007=100 | F5: Tasas de variación t/t-1 | J5: Tasas de variación t/t-4
A6: Industrias | B6: VALOR AGREGADO PETROLERO | C6: VALOR AGREGADO NO PETROLERO | D6: OTROS ELEMENTOS DEL PIB (**) | E6: P.I.B. | F6: VALOR AGREGADO PETROLERO | G6: VALOR AGREGADO NO PETROLERO | H6: OTROS ELEMENTOS DEL PIB (**) | I6: P.I.B. | J6: VALOR AGREGADO PETROLERO | K6: VALOR AGREGADO NO PETROLERO | L6: OTROS ELEMENTOS DEL PIB | M6: P.I.B.
A7: Trimestres
A9: 2000.I | B9: 1218387 | C9: 7505878 | D9: 410322 | E9: 9134587
A10: 2000.II | B10: 1191946 | C10: 7713590 | D10: 414878 | E10: 9320414 | F10: -2.1701643 | G10: 2.7673245 | H10: 1.1103475 | I10: 2.034323
A11: 2000.III | B11: 1241308 | C11: 7809823 | D11: 497360 | E11: 9548491 | F11: 4.141295 | G11: 1.2475773 | H11: 19.881025 | I11: 2.4470694
A12: 2000.IV | B12: 1241168 | C12: 7933267 | D12: 548483 | E12: 9722918 | F12: -0.011278426 | G12: 1.5806248 | H12: 10.278872 | I12: 1.8267494
A13: 2001.I | B13: 1255388 | C13: 7952018 | D13: 491957 | E13: 9699363 | F13: 1.145695 | G13: 0.23635912 | H13: -10.30588 | I13: -0.24226266 | J13: 3.036884 | K13: 5.9438749 | L13: 19.89535 | M13: 6.1828302
A14: 2001.II | B14: 1232212 | C14: 8044135 | D14: 526066 | E14: 9802413 | F14: -1.8461225 | G14: 1.1584104 | H14: 6.9333295 | I14: 1.0624409 | J14: 3.3781732 | K14: 4.2852291 | L14: 26.800168 | M14: 5.1714334
A15: 2001.III | B15: 1207624 | C15: 8136380 | D15: 465479 | E15: 9809483 | F15: -1.9954359 | G15: 1.1467361 | H15: -11.516996 | I15: 0.072125098 | J15: -2.7135892 | K15: 4.1813624 | L15: -6.410045 | M15: 2.7333324
A16: 2001.IV | B16: 1197778 | C16: 8244031 | D16: 488295 | E16: 9930104 | F16: -0.81532 | G16: 1.3230823 | H16: 4.9016175 | I16: 1.2296367 | J16: -3.4959006 | K16: 3.917226 | L16: -10.97354 | M16: 2.1309035
A17: 2002.I | B17: 1196035 | C17: 8307126 | D17: 560405 | E17: 10063566 | F17: -0.14551945 | G17: 0.76534162 | H17: 14.767712 | I17: 1.3440141 | J17: -4.727861 | K17: 4.4656338 | L17: 13.913411 | M17: 3.7549167
A18: 2002.II | B18: 1206414 | C18: 8426631 | D18: 572773 | E18: 10205818 | F18: 0.86778397 | G18: 1.4385842 | H18: 2.2069753 | I18: 1.4135347 | J18: -2.0936332 | K18: 4.7549674 | L18: 8.8785438 | M18: 4.1153642
A19: 2002.III | B19: 1189068 | C19: 8526636 | D19: 558504 | E19: 10274208 | F19: -1.4378149 | G19: 1.1867732 | H19: -2.4912138 | I19: 0.67010797 | J19: -1.536571 | K19: 4.7964328 | L19: 19.98479 | M19: 4.7375076
A20: 2002.IV | B20: 1153055 | C20: 8609583 | D20: 542764 | E20: 10305402 | F20: -3.0286746 | G20: 0.97279865 | H20: -2.818243 | I20: 0.30361464 | J20: -3.7338305 | K20: 4.4341415 | L20: 11.154937 | M20: 3.7793965
A21: 2003.I | B21: 1157573 | C21: 8712290 | D21: 570225 | E21: 10440088 | F21: 0.39182866 | G21: 1.1929381 | H21: 5.0594734 | I21: 1.3069456 | J21: -3.2157922 | K21: 4.8773065 | L21: 1.7523041 | M21: 3.7414372
A22: 2003.II | B22: 1071527 | C22: 8650931 | D22: 518333 | E22: 10240791 | F22: -7.4333109 | G22: -0.70428096 | H22: -9.1002674 | I22: -1.908959 | J22: -11.180822 | K22: 2.6617992 | L22: -9.504638 | M22: 0.34267709
A23: 2003.III | B23: 1265059 | C23: 8695286 | D23: 504036 | E23: 10464381 | F23: 18.061327 | G23: 0.51271938 | H23: -2.7582654 | I23: 2.1833274 | J23: 6.3908036 | K23: 1.9779195 | L23: -9.7524816 | M23: 1.8509748
A24: 2003.IV | B24: 1483081 | C24: 8827736 | D24: 505185 | E24: 10816002 | F24: 17.234137 | G24: 1.5232391 | H24: 0.22795991 | I24: 3.3601701 | J24: 28.621878 | K24: 2.5338393 | L24: -6.9236353 | M24: 4.954683
... A89: 2020.I | B89: 1666953 | C89: 15475006 | D89: 381089 | E89: 17523048 | F89: 2.8241349 | G89: -1.7128069 | H89: -28.704312 | I89: -2.1079006 | J89: 1.9188429 | K89: -1.7531735 | L89: -33.260889 | M89: -2.4206006
A91: (*) Suma del Valor Agregado de Extracción de petróleo, gas natural y del Valor Agregado de la Fabricación de productos de la refinación petróleo
A92: (**) Otros elementos del PIB incluye: otros impuestos sobre productos, subsidios sobre productos, derechos arancelarios, Impuesto al Valor Agregado (IVA)
A93: Elaboración: BANCO CENTRAL DEL ECUADOR

Sheet oilGDPnominal
A1: Menú Principal
A3: VALOR AGREGADO BRUTO PETROLERO (*) Y NO PETROLERO
B5: Miles de US dólares | F5: Deflactores implícitos, 2007 = 100
F6: Nivel | J6: Tasas de variación t/t-1 | N6: Tasas de variación t/t-4
A7: Industrias | B7: VALOR AGREGADO PETROLERO | C7: VALOR AGREGADO NO PETROLERO | D7: OTROS ELEMENTOS DEL PIB (**) | E7: P.I.B. | F7: VALOR AGREGADO PETROLERO | G7: VALOR AGREGADO NO PETROLERO | H7: OTROS ELEMENTOS DEL PIB (**) | I7: P.I.B. | J7: VALOR AGREGADO PETROLERO | K7: VALOR AGREGADO NO PETROLERO | L7: OTROS ELEMENTOS DEL PIB (**) | M7: P.I.B. | N7: VALOR AGREGADO PETROLERO | O7: VALOR AGREGADO NO PETROLERO | P7: OTROS ELEMENTOS DEL PIB | Q7: P.I.B.
A8: Trimestres
A10: 2000.I | B10: 332388 | C10: 3290847 | D10: 195891 | E10: 3819126 | F10: 27.280987 | G10: 43.843598 | H10: 47.740799 | I10: 41.809509
A11: 2000.II | B11: 369840 | C11: 3806141 | D11: 226498 | E11: 4402479 | F11: 31.028251 | G11: 49.343315 | H11: 54.593881 | I11: 47.234801 | J11: 13.735809 | K11: 12.543944 | L11: 14.35477 | M11: 12.976215
A12: 2000.III | B12: 460321 | C12: 4150331 | D12: 296001 | E12: 4906653 | F12: 37.083544 | G12: 53.142446 | H12: 59.514436 | I12: 51.386685 | J12: 19.515418 | K12: 7.6993845 | L12: 9.0130168 | M12: 8.7898838
A13: 2000.IV | B13: 462506 | C13: 4400253 | D13: 327584 | E13: 5190343 | F13: 37.263771 | G13: 55.465838 | H13: 59.725461 | I13: 53.382565 | J13: 0.486002 | K13: 4.3720067 | L13: 0.35457738 | M13: 3.8840406
A14: 2001.I | B14: 336056 | C14: 5130098 | D14: 437928 | E14: 5904082 | F14: 26.769094 | G14: 64.513159 | H14: 89.017536 | I14: 60.870822 | J14: -28.163216 | K14: 16.31152 | L14: 49.044536 | M14: 14.027534 | N14: -1.8763712 | O14: 47.143851 | P14: 86.46009 | Q14: 45.590855
A15: 2001.II | B15: 327311 | C15: 5256978 | D15: 485331 | E15: 6069620 | F15: 26.56288 | G15: 65.351688 | H15: 92.256675 | I15: 61.919652 | J15: -0.77034388 | K15: 1.29978 | L15: 3.638765 | M15: 1.7230418 | N15: -14.391307 | O15: 32.442841 | P15: 68.987209 | Q15: 31.08905
A16: 2001.III | B16: 322417 | C16: 5336981 | D16: 500211 | E16: 6159609 | F16: 26.698459 | G16: 65.594048 | H16: 107.46156 | I16: 62.792392 | J16: 0.51040666 | K16: 0.37085509 | L16: 16.481069 | M16: 1.4094717 | N16: -28.004564 | O16: 23.430614 | P16: 80.563856 | Q16: 22.195841
A17: 2001.IV | B17: 286737 | C17: 5535621 | D17: 512655 | E17: 6335013 | F17: 23.939077 | G17: 67.147018 | H17: 104.98879 | I17: 63.796039 | J17: -10.33536 | K17: 2.3675476 | L17: -2.3010773 | M17: 1.5983576 | N17: -35.757771 | O17: 21.060135 | P17: 75.785646 | Q17: 19.507257
A18: 2002.I | B18: 340321 | C18: 5858861 | D18: 538369 | E18: 6737551 | F18: 28.4541 | G18: 70.528135 | H18: 96.067844 | I18: 66.949936 | J18: 18.860473 | K18: 5.035393 | L18: -8.4970442 | M18: 4.9437196 | N18: 6.2945944 | O18: 9.3236416 | P18: 7.9201335 | Q18: 9.9869095
A19: 2002.II | B19: 394787 | C19: 6100775 | D19: 591065 | E19: 7086627 | F19: 32.724007 | G19: 72.398744 | H19: 103.19359 | I19: 69.437129 | J19: 15.006296 | K19: 2.6522882 | L19: 7.4174065 | M19: 3.7150041 | N19: 23.194497 | O19: 10.783281 | P19: 11.854873 | Q19: 12.140697
A20: 2002.III | B20: 416026 | C20: 6290885 | D20: 587221 | E20: 7294132 | F20: 34.98757 | G20: 73.779214 | H20: 105.14177 | I20: 70.994592 | J20: 6.9171335 | K20: 1.9067593 | L20: 1.8878938 | M20: 2.2429824 | N20: 31.047151 | O20: 12.478519 | P20: -2.1587156 | Q20: 13.06241
A21: 2002.IV | B21: 399758 | C21: 6438429 | D21: 592448 | E21: 7430635 | F21: 34.669465 | G21: 74.782124 | H21: 109.15389 | I21: 72.104271 | J21: -0.90919451 | K21: 1.3593393 | L21: 3.8159095 | M21: 1.5630481 | N21: 44.823732 | O21: 11.370729 | P21: 3.9671845 | Q21: 13.023116
A22: 2003.I | B22: 539520 | C22: 6906805 | D22: 565104 | E22: 8011429 | F22: 46.60786 | G22: 79.276574 | H22: 99.101933 | I22: 76.737179 | J22: 34.434897 | K22: 6.0100594 | L22: -9.2089739 | M22: 6.4252889 | N22: 63.800152 | O22: 12.404183 | P22: 3.1582781 | Q22: 14.618749
A23: 2003.II | B23: 440959 | C23: 6963355 | D23: 560764 | E23: 7965078 | F23: 41.152393 | G23: 80.49255 | H23: 108.18605 | I23: 77.777957 | J23: -11.705036 | K23: 1.5338412 | L23: 9.1664375 | M23: 1.3562891 | N23: 25.755972 | O23: 11.179485 | P23: 4.8379596 | Q23: 12.012058
A24: 2003.III | B24: 509102 | C24: 7045127 | D24: 566236 | E24: 8120465 | F24: 40.24334 | G24: 81.022372 | H24: 112.34039 | I24: 77.601007 | J24: -2.2089903 | K24: 0.65822476 | L24: 3.8399942 | M24: -0.22750676 | N24: 15.021822 | O24: 9.8173432 | P24: 6.8465812 | Q24: 9.305519
A25: 2003.IV | B25: 587169 | C25: 7179216 | D25: 569501 | E25: 8335886 | F25: 39.591162 | G25: 81.325676 | H25: 112.73118 | I25: 77.069938 | J25: -1.6205874 | K25: 0.37434587 | L25: 0.3478618 | M25: -0.68435841 | N25: 14.196057 | O25: 8.7501562 | P25: 3.2772917 | Q25: 6.8867856
... A90: 2020.I | B90: 1432939 | C90: 22867309 | D90: 1578350 | E90: 25878598 | F90: 85.961572 | G90: 147.76931 | H90: 414.16834 | I90: 147.6832 | J90: -14.425138 | K90: -0.28577173 | L90: 19.232542 | M90: -1.4238949 | N90: -15.112466 | O90: -0.0026269547 | P90: 29.545197 | Q90: -0.88672862
A92: (*) Suma del Valor Agregado de Extracción de petróleo, gas natural y del Valor Agregado de la Fabricación de productos de la refinación petróleo
A93: (**) Otros elementos del PIB incluye: otros impuestos sobre productos, subsidios sobre productos, derechos arancelarios, Impuesto al Valor Agregado (IVA)
A94: Elaboración: BANCO CENTRAL DEL ECUADOR

Sheet worldGDP
A1: Subject | B1: Measure | C1: Period | D1: Australia | E1: Austria | F1: Belgium | G1: Canada | H1: Chile | I1: Colombia | J1: Czech Republic | K1: Denmark | L1: Estonia | M1: Finland | N1: France | O1: Germany | P1: Greece | Q1: Hungary | R1: Iceland | S1: Ireland | T1: Israel | U1: Italy | V1: Japan | W1: Korea | X1: Latvia | Y1: Lithuania | Z1: Luxembourg | AA1: Mexico | AB1: Netherlands | AC1: New Zealand | AD1: Norway | AE1: Poland | AF1: Portugal | AG1: Slovak Republic | AH1: Slovenia | AI1: Spain | AJ1: Sweden | AK1: Switzerland | AL1: Turkey | AM1: United Kingdom | AN1: United States | AO1: Euro area (19 countries) | AP1: European Union – 27 countries (from 01/02/2020) | AQ1: G7 | AR1: NAFTA | AS1: OECD - Europe | AT1: G20 | AU1: OECD - Total | AV1: Argentina | AW1: Brazil | AX1: Bulgaria | AY1: China (People's Republic of) | AZ1: India | BA1: Indonesia | BB1: Romania | BC1: Russia | BD1: Saudi Arabia | BE1: South Africa
D2: Percentage | E2: Percentage | F2: Percentage | G2: Percentage | H2: Percentage | I2: Percentage | J2: Percentage | K2: Percentage | L2: Percentage | M2: Percentage | N2: Percentage | O2: Percentage | P2: Percentage | Q2: Percentage | R2: Percentage | S2: Percentage | T2: Percentage | U2: Percentage | V2: Percentage | W2: Percentage | X2: Percentage | Y2: Percentage | Z2: Percentage | AA2: Percentage | AB2: Percentage | AC2: Percentage | AD2: Percentage | AE2: Percentage | AF2: Percentage | AG2: Percentage | AH2: Percentage | AI2: Percentage | AJ2: Percentage | AK2: Percentage | AL2: Percentage | AM2: Percentage | AN2: Percentage | AO2: Percentage | AP2: Percentage | AQ2: Percentage | AR2: Percentage | AS2: Percentage | AT2: Percentage | AU2: Percentage | AV2: Percentage | AW2: Percentage | AX2: Percentage | AY2: Percentage | AZ2: Percentage | BA2: Percentage | BB2: Percentage | BC2: Percentage | BD2: Percentage | BE2: Percentage
A3: B1_GE: Gross domestic product - expenditure approach | B3: GPSA: Growth rate compared to previous quarter, seasonally adjusted | C3: Q2-1947 | D3: .. | E3: .. | F3: .. | G3: .. | H3: .. | I3: .. | J3: .. | K3: .. | L3: .. | M3: .. | N3: .. | O3: .. | P3: .. | Q3: .. | R3: .. | S3: .. | T3: .. | U3: .. | V3: .. | W3: .. | X3: .. | Y3: .. | Z3: .. | AA3: .. | AB3: .. | AC3: .. | AD3: .. | AE3: .. | AF3: .. | AG3: .. | AH3: .. | AI3: .. | AJ3: .. | AK3: .. | AL3: .. | AM3: .. | AN3: -0.266691 | AO3: .. | AP3: .. | AQ3: .. | AR3: .. | AS3: .. | AT3: .. | AU3: .. | AV3: .. | AW3: .. | AX3: .. | AY3: .. | AZ3: .. | BA3: .. | BB3: .. | BC3: .. | BD3: .. | BE3: ..
C4: Q3-1947 | D4: .. | E4: .. | F4: .. | G4: .. | H4: .. | I4: .. | J4: .. | K4: .. | L4: .. | M4: .. | N4: .. | O4: .. | P4: .. | Q4: .. | R4: .. | S4: .. | T4: .. | U4: .. | V4: .. | W4: .. | X4: .. | Y4: .. | Z4: .. | AA4: .. | AB4: .. | AC4: .. | AD4: .. | AE4: .. | AF4: .. | AG4: .. | AH4: .. | AI4: .. | AJ4: .. | AK4: .. | AL4: .. | AM4: .. | AN4: -0.206496 | AO4: .. | AP4: .. | AQ4: .. | AR4: .. | AS4: .. | AT4: .. | AU4: .. | AV4: .. | AW4: .. | AX4: .. | AY4: .. | AZ4: .. | BA4: .. | BB4: .. | BC4: .. | BD4: .. | BE4: ..
C5: Q4-1947 | D5: .. | E5: .. | F5: .. | G5: .. | H5: .. | I5: .. | J5: .. | K5: .. | L5: .. | M5: .. | N5: .. | O5: .. | P5: .. | Q5: .. | R5: .. | S5: .. | T5: .. | U5: .. | V5: .. | W5: .. | X5: .. | Y5: .. | Z5: .. | AA5: .. | AB5: .. | AC5: .. | AD5: .. | AE5: .. | AF5: .. | AG5: .. | AH5: .. | AI5: .. | AJ5: .. | AK5: .. | AL5: .. | AM5: .. | AN5: 1.564208 | AO5: .. | AP5: .. | AQ5: .. | AR5: .. | AS5: .. | AT5: .. | AU5: .. | AV5: .. | AW5: .. | AX5: .. | AY5: .. | AZ5: .. | BA5: .. | BB5: .. | BC5: .. | BD5: .. | BE5: ..
C6: Q1-1948 | D6: .. | E6: .. | F6: .. | G6: .. | H6: .. | I6: .. | J6: .. | K6: .. | L6: .. | M6: .. | N6: .. | O6: .. | P6: .. | Q6: .. | R6: .. | S6: .. | T6: .. | U6: .. | V6: .. | W6: .. | X6: .. | Y6: .. | Z6: .. | AA6: .. | AB6: .. | AC6: .. | AD6: .. | AE6: .. | AF6: .. | AG6: .. | AH6: .. | AI6: .. | AJ6: .. | AK6: .. | AL6: .. | AM6: .. | AN6: 1.504256 | AO6: .. | AP6: .. | AQ6: .. | AR6: .. | AS6: .. | AT6: .. | AU6: .. | AV6: .. | AW6: .. | AX6: .. | AY6: .. | AZ6: .. | BA6: .. | BB6: .. | BC6: .. | BD6: .. | BE6: ..
C7: Q2-1948 | D7: .. | E7: .. | F7: .. | G7: .. | H7: .. | I7: .. | J7: .. | K7: .. | L7: .. | M7: .. | N7: .. | O7: .. | P7: .. | Q7: .. | R7: .. | S7: .. | T7: .. | U7: .. | V7: .. | W7: .. | X7: .. | Y7: .. | Z7: .. | AA7: .. | AB7: .. | AC7: .. | AD7: .. | AE7: .. | AF7: .. | AG7: .. | AH7: .. | AI7: .. | AJ7: .. | AK7: .. | AL7: .. | AM7: .. | AN7: 1.650658 | AO7: .. | AP7: .. | AQ7: .. | AR7: .. | AS7: .. | AT7: .. | AU7: .. | AV7: .. | AW7: .. | AX7: .. | AY7: .. | AZ7: .. | BA7: .. | BB7: .. | BC7: .. | BD7: .. | BE7: ..
C8: Q3-1948 | D8: .. | E8: .. | F8: .. | G8: .. | H8: .. | I8: .. | J8: .. | K8: .. | L8: .. | M8: .. | N8: .. | O8: .. | P8: .. | Q8: .. | R8: .. | S8: .. | T8: .. | U8: .. | V8: .. | W8: .. | X8: .. | Y8: .. | Z8: .. | AA8: .. | AB8: .. | AC8: .. | AD8: .. | AE8: .. | AF8: .. | AG8: .. | AH8: .. | AI8: .. | AJ8: .. | AK8: .. | AL8: .. | AM8: .. | AN8: 0.572897 | AO8: .. | AP8: .. | AQ8: .. | AR8: .. | AS8: .. | AT8: .. | AU8: .. | AV8: .. | AW8: .. | AX8: .. | AY8: .. | AZ8: .. | BA8: .. | BB8: .. | BC8: .. | BD8: .. | BE8: ..
C9: Q4-1948 | D9: .. | E9: .. | F9: .. | G9: .. | H9: .. | I9: .. | J9: .. | K9: .. | L9: .. | M9: .. | N9: .. | O9: .. | P9: .. | Q9: .. | R9: .. | S9: .. | T9: .. | U9: .. | V9: .. | W9: .. | X9: .. | Y9: .. | Z9: .. | AA9: .. | AB9: .. | AC9: .. | AD9: .. | AE9: .. | AF9: .. | AG9: .. | AH9: .. | AI9: .. | AJ9: .. | AK9: .. | AL9: .. | AM9: .. | AN9: 0.111742 | AO9: .. | AP9: .. | AQ9: .. | AR9: .. | AS9: .. | AT9: .. | AU9: .. | AV9: .. | AW9: .. | AX9: .. | AY9: .. | AZ9: .. | BA9: .. | BB9: .. | BC9: .. | BD9: .. | BE9: ..
C10: Q1-1949 | D10: .. | E10: .. | F10: .. | G10: .. | H10: .. | I10: .. | J10: .. | K10: .. | L10: .. | M10: .. | N10: .. | O10: .. | P10: .. | Q10: .. | R10: .. | S10: .. | T10: .. | U10: .. | V10: .. | W10: .. | X10: .. | Y10: .. | Z10: .. | AA10: .. | AB10: .. | AC10: .. | AD10: .. | AE10: .. | AF10: .. | AG10: .. | AH10: .. | AI10: .. | AJ10: .. | AK10: .. | AL10: .. | AM10: .. | AN10: -1.377951 | AO10: .. | AP10: .. | AQ10: .. | AR10: .. | AS10: .. | AT10: .. | AU10: .. | AV10: .. | AW10: .. | AX10: .. | AY10: .. | AZ10: .. | BA10: .. | BB10: .. | BC10: .. | BD10: .. | BE10: ..
C11: Q2-1949 | D11: .. | E11: .. | F11: .. | G11: .. | H11: .. | I11: .. | J11: .. | K11: .. | L11: .. | M11: .. | N11: .. | O11: .. | P11: .. | Q11: .. | R11: .. | S11: .. | T11: .. | U11: .. | V11: .. | W11: .. | X11: .. | Y11: .. | Z11: .. | AA11: .. | AB11: .. | AC11: .. | AD11: .. | AE11: .. | AF11: .. | AG11: .. | AH11: .. | AI11: .. | AJ11: .. | AK11: .. | AL11: .. | AM11: .. | AN11: -0.341097 | AO11: .. | AP11: .. | AQ11: .. | AR11: .. | AS11: .. | AT11: .. | AU11: .. | AV11: .. | AW11: .. | AX11: .. | AY11: .. | AZ11: .. | BA11: .. | BB11: .. | BC11: .. | BD11: .. | BE11: ..
C12: Q3-1949 | D12: .. | E12: .. | F12: .. | G12: .. | H12: .. | I12: .. | J12: .. | K12: .. | L12: .. | M12: .. | N12: .. | O12: .. | P12: .. | Q12: .. | R12: .. | S12: .. | T12: .. | U12: .. | V12: .. | W12: .. | X12: .. | Y12: .. | Z12: .. | AA12: .. | AB12: .. | AC12: .. | AD12: .. | AE12: .. | AF12: .. | AG12: .. | AH12: .. | AI12: .. | AJ12: .. | AK12: .. | AL12: .. | AM12: .. | AN12: 1.032415 | AO12: .. | AP12: .. | AQ12: .. | AR12: .. | AS12: .. | AT12: .. | AU12: .. | AV12: .. | AW12: .. | AX12: .. | AY12: .. | AZ12: .. | BA12: .. | BB12: .. | BC12: .. | BD12: .. | BE12: ..
C13: Q4-1949 | D13: .. | E13: .. | F13: .. | G13: .. | H13: .. | I13: .. | J13: .. | K13: .. | L13: .. | M13: .. | N13: .. | O13: .. | P13: .. | Q13: .. | R13: .. | S13: .. | T13: .. | U13: .. | V13: .. | W13: .. | X13: .. | Y13: .. | Z13: .. | AA13: .. | AB13: .. | AC13: .. | AD13: .. | AE13: .. | AF13: .. | AG13: .. | AH13: .. | AI13: .. | AJ13: .. | AK13: .. | AL13: .. | AM13: .. | AN13: -0.839275 | AO13: .. | AP13: .. | AQ13: .. | AR13: .. | AS13: .. | AT13: .. | AU13: .. | AV13: .. | AW13: .. | AX13: .. | AY13: .. | AZ13: .. | BA13: .. | BB13: .. | BC13: .. | BD13: .. | BE13: ..
C14: Q1-1950 | D14: .. | E14: .. | F14: .. | G14: .. | H14: .. | I14: .. | J14: .. | K14: .. | L14: .. | M14: .. | N14: .. | O14: .. | P14: .. | Q14: .. | R14: .. | S14: .. | T14: .. | U14: .. | V14: .. | W14: .. | X14: .. | Y14: .. | Z14: .. | AA14: .. | AB14: .. | AC14: .. | AD14: .. | AE14: .. | AF14: .. | AG14: .. | AH14: .. | AI14: .. | AJ14: .. | AK14: .. | AL14: .. | AM14: .. | AN14: 3.930121 | AO14: .. | AP14: .. | AQ14: .. | AR14: .. | AS14: .. | AT14: .. | AU14: .. | AV14: .. | AW14: .. | AX14: .. | AY14: .. | AZ14: .. | BA14: .. | BB14: .. | BC14: .. | BD14: .. | BE14: ..
C15: Q2-1950 | D15: .. | E15: .. | F15: .. | G15: .. | H15: .. | I15: .. | J15: .. | K15: .. | L15: .. | M15: .. | N15: .. | O15: .. | P15: .. | Q15: .. | R15: .. | S15: .. | T15: .. | U15: .. | V15: .. | W15: .. | X15: .. | Y15: .. | Z15: .. | AA15: .. | AB15: .. | AC15: .. | AD15: .. | AE15: .. | AF15: .. | AG15: .. | AH15: .. | AI15: .. | AJ15: .. | AK15: .. | AL15: .. | AM15: .. | AN15: 3.049835 | AO15: .. | AP15: .. | AQ15: .. | AR15: .. | AS15: .. | AT15: .. | AU15: .. | AV15: .. | AW15: .. | AX15: .. | AY15: .. | AZ15: .. | BA15: .. | BB15: .. | BC15: .. | BD15: .. | BE15: ..
... C34: Q1-1955 | D34: .. | E34: .. | F34: .. | G34: .. | H34: .. | I34: .. | J34: .. | K34: .. | L34: .. | M34: .. | N34: .. | O34: .. | P34: .. | Q34: .. | R34: .. | S34: .. | T34: .. | U34: .. | V34: .. | W34: .. | X34: .. | Y34: .. | Z34: .. | AA34: .. | AB34: .. | AC34: .. | AD34: .. | AE34: .. | AF34: .. | AG34: .. | AH34: .. | AI34: .. | AJ34: .. | AK34: .. | AL34: .. | AM34: .. | AN34: 2.856249 | AO34: .. | AP34: .. | AQ34: .. | AR34: .. | AS34: .. | AT34: .. | AU34: .. | AV34: .. | AW34: .. | AX34: .. | AY34: .. | AZ34: .. | BA34: .. | BB34: .. | BC34: .. | BD34: .. | BE34: ..
C35: Q2-1955 | D35: .. | E35: .. | F35: .. | G35: .. | H35: .. | I35: .. | J35: .. | K35: .. | L35: .. | M35: .. | N35: .. | O35: .. | P35: .. | Q35: .. | R35: .. | S35: .. | T35: .. | U35: .. | V35: .. | W35: .. | X35: .. | Y35: .. | Z35: .. | AA35: .. | AB35: .. | AC35: .. | AD35: .. | AE35: .. | AF35: .. | AG35: .. | AH35: .. | AI35: .. | AJ35: .. | AK35: .. | AL35: .. | AM35: 0.065066 | AN35: 1.627179 | AO35: .. | AP35: .. | AQ35: .. | AR35: .. | AS35: .. | AT35: .. | AU35: .. | AV35: .. | AW35: .. | AX35: .. | AY35: .. | AZ35: .. | BA35: .. | BB35: .. | BC35: .. | BD35: .. | BE35: ..
C36: Q3-1955 | D36: .. | E36: .. | F36: .. | G36: .. | H36: .. | I36: .. | J36: .. | K36: .. | L36: .. | M36: .. | N36: .. | O36: .. | P36: .. | Q36: .. | R36: .. | S36: .. | T36: .. | U36: .. | V36: .. | W36: .. | X36: .. | Y36: .. | Z36: .. | AA36: .. | AB36: .. | AC36: .. | AD36: .. | AE36: .. | AF36: .. | AG36: .. | AH36: .. | AI36: .. | AJ36: .. | AK36: .. | AL36: .. | AM36: 2.022856 | AN36: 1.350478 | AO36: .. | AP36: .. | AQ36: .. | AR36: .. | AS36: .. | AT36: .. | AU36: .. | AV36: .. | AW36: .. | AX36: .. | AY36: .. | AZ36: .. | BA36: .. | BB36: .. | BC36: .. | BD36: .. | BE36: ..
C37: Q4-1955 | D37: .. | E37: .. | F37: .. | G37: .. | H37: .. | I37: .. | J37: .. | K37: .. | L37: .. | M37: .. | N37: .. | O37: .. | P37: .. | Q37: .. | R37: .. | S37: .. | T37: .. | U37: .. | V37: .. | W37: .. | X37: .. | Y37: .. | Z37: .. | AA37: .. | AB37: .. | AC37: .. | AD37: .. | AE37: .. | AF37: .. | AG37: .. | AH37: .. | AI37: .. | AJ37: .. | AK37: .. | AL37: .. | AM37: -0.523844 | AN37: 0.600325 | AO37: .. | AP37: .. | AQ37: .. | AR37: .. | AS37: .. | AT37: .. | AU37: .. | AV37: .. | AW37: .. | AX37: .. | AY37: .. | AZ37: .. | BA37: .. | BB37: .. | BC37: .. | BD37: .. | BE37: ..
C38: Q1-1956 | D38: .. | E38: .. | F38: .. | G38: .. | H38: .. | I38: .. | J38: .. | K38: .. | L38: .. | M38: .. | N38: .. | O38: .. | P38: .. | Q38: .. | R38: .. | S38: .. | T38: .. | U38: .. | V38: .. | W38: .. | X38: .. | Y38: .. | Z38: .. | AA38: .. | AB38: .. | AC38: .. | AD38: .. | AE38: .. | AF38: .. | AG38: .. | AH38: .. | AI38: .. | AJ38: .. | AK38: .. | AL38: .. | AM38: 1.172568 | AN38: -0.388406 | AO38: .. | AP38: .. | AQ38: .. | AR38: .. | AS38: .. | AT38: .. | AU38: .. | AV38: .. | AW38: .. | AX38: .. | AY38: .. | AZ38: .. | BA38: .. | BB38: .. | BC38: .. | BD38: .. | BE38: ..
C39: Q2-1956 | D39: .. | E39: .. | F39: .. | G39: .. | H39: .. | I39: .. | J39: .. | K39: .. | L39: .. | M39: .. | N39: .. | O39: .. | P39: .. | Q39: .. | R39: .. | S39: .. | T39: .. | U39: .. | V39: .. | W39: .. | X39: .. | Y39: .. | Z39: .. | AA39: .. | AB39: .. | AC39: .. | AD39: .. | AE39: .. | AF39: .. | AG39: .. | AH39: .. | AI39: .. | AJ39: .. | AK39: .. | AL39: .. | AM39: -0.216875 | AN39: 0.826333 | AO39: .. | AP39: .. | AQ39: .. | AR39: .. | AS39: .. | AT39: .. | AU39: .. | AV39: .. | AW39: .. | AX39: .. | AY39: .. | AZ39: .. | BA39: .. | BB39: .. | BC39: .. | BD39: .. | BE39: ..
C40: Q3-1956 | D40: .. | E40: .. | F40: .. | G40: .. | H40: .. | I40: .. | J40: .. | K40: .. | L40: .. | M40: .. | N40: .. | O40: .. | P40: .. | Q40: .. | R40: .. | S40: .. | T40: .. | U40: .. | V40: .. | W40: .. | X40: .. | Y40: .. | Z40: .. | AA40: .. | AB40: .. | AC40: .. | AD40: .. | AE40: .. | AF40: .. | AG40: .. | AH40: .. | AI40: .. | AJ40: .. | AK40: .. | AL40: .. | AM40: -0.116497 | AN40: -0.089833 | AO40: .. | AP40: .. | AQ40: .. | AR40: .. | AS40: .. | AT40: .. | AU40: .. | AV40: .. | AW40: .. | AX40: .. | AY40: .. | AZ40: .. | BA40: .. | BB40: .. | BC40: .. | BD40: .. | BE40: ..
C41: Q4-1956 | D41: .. | E41: .. | F41: .. | G41: .. | H41: .. | I41: .. | J41: .. | K41: .. | L41: .. | M41: .. | N41: .. | O41: .. | P41: .. | Q41: .. | R41: .. | S41: .. | T41: .. | U41: .. | V41: .. | W41: .. | X41: .. | Y41: .. | Z41: .. | AA41: .. | AB41: .. | AC41: .. | AD41: .. | AE41: .. | AF41: .. | AG41: .. | AH41: .. | AI41: .. | AJ41: .. | AK41: .. | AL41: .. | AM41: 0.469144 | AN41: 1.645929 | AO41: .. | AP41: .. | AQ41: .. | AR41: .. | AS41: .. | AT41: .. | AU41: .. | AV41: .. | AW41: .. | AX41: .. | AY41: .. | AZ41: .. | BA41: .. | BB41: .. | BC41: .. | BD41: .. | BE41: ..
C42: Q1-1957 | D42: .. | E42: .. | F42: .. | G42: .. | H42: .. | I42: .. | J42: .. | K42: .. | L42: .. | M42: .. | N42: .. | O42: .. | P42: .. | Q42: .. | R42: .. | S42: .. | T42: .. | U42: .. | V42: .. | W42: .. | X42: .. | Y42: .. | Z42: .. | AA42: .. | AB42: .. | AC42: .. | AD42: .. | AE42: .. | AF42: .. | AG42: .. | AH42: .. | AI42: .. | AJ42: .. | AK42: .. | AL42: .. | AM42: 2.000364 | AN42: 0.640392 | AO42: .. | AP42: .. | AQ42: .. | AR42: .. | AS42: .. | AT42: .. | AU42: .. | AV42: .. | AW42: .. | AX42: .. | AY42: .. | AZ42: .. | BA42: .. | BB42: .. | BC42: .. | BD42: .. | BE42: ..
C43: Q2-1957 | D43: .. | E43: .. | F43: .. | G43: .. | H43: .. | I43: .. | J43: .. | K43: .. | L43: .. | M43: .. | N43: .. | O43: .. | P43: .. | Q43: .. | R43: .. | S43: .. | T43: .. | U43: .. | V43: .. | W43: .. | X43: .. | Y43: .. | Z43: .. | AA43: .. | AB43: .. | AC43: .. | AD43: .. | AE43: .. | AF43: .. | AG43: .. | AH43: .. | AI43: .. | AJ43: .. | AK43: .. | AL43: .. | AM43: 0.010192 | AN43: -0.219102 | AO43: .. | AP43: .. | AQ43: .. | AR43: .. | AS43: .. | AT43: .. | AU43: .. | AV43: .. | AW43: .. | AX43: .. | AY43: .. | AZ43: .. | BA43: .. | BB43: .. | BC43: .. | BD43: .. | BE43: ..
C44: Q3-1957 | D44: .. | E44: .. | F44: .. | G44: .. | H44: .. | I44: .. | J44: .. | K44: .. | L44: .. | M44: .. | N44: .. | O44: .. | P44: .. | Q44: .. | R44: .. | S44: .. | T44: .. | U44: .. | V44: .. | W44: .. | X44: .. | Y44: .. | Z44: .. | AA44: .. | AB44: .. | AC44: .. | AD44: .. | AE44: .. | AF44: .. | AG44: .. | AH44: .. | AI44: .. | AJ44: .. | AK44: .. | AL44: .. | AM44: -0.614013 | AN44: 0.979883 | AO44: .. | AP44: .. | AQ44: .. | AR44: .. | AS44: .. | AT44: .. | AU44: .. | AV44: .. | AW44: .. | AX44: .. | AY44: .. | AZ44: .. | BA44: .. | BB44: .. | BC44: .. | BD44: .. | BE44: ..
C45: Q4-1957 | D45: .. | E45: .. | F45: .. | G45: .. | H45: .. | I45: .. | J45: .. | K45: .. | L45: .. | M45: .. | N45: .. | O45: .. | P45: .. | Q45: .. | R45: .. | S45: .. | T45: .. | U45: .. | V45: .. | W45: .. | X45: .. | Y45: .. | Z45: .. | AA45: .. | AB45: .. | AC45: .. | AD45: .. | AE45: .. | AF45: .. | AG45: .. | AH45: .. | AI45: .. | AJ45: .. | AK45: .. | AL45: .. | AM45: 0.198245 | AN45: -1.034588 | AO45: .. | AP45: .. | AQ45: .. | AR45: .. | AS45: .. | AT45: .. | AU45: .. | AV45: .. | AW45: .. | AX45: .. | AY45: .. | AZ45: .. | BA45: .. | BB45: .. | BC45: .. | BD45: .. | BE45: ..
C46: Q1-1958 | D46: .. | E46: .. | F46: .. | G46: .. | H46: .. | I46: .. | J46: .. | K46: .. | L46: .. | M46: .. | N46: .. | O46: .. | P46: .. | Q46: .. | R46: .. | S46: .. | T46: .. | U46: .. | V46: .. | W46: .. | X46: .. | Y46: .. | Z46: .. | AA46: .. | AB46: .. | AC46: .. | AD46: .. | AE46: .. | AF46: .. | AG46: .. | AH46: .. | AI46: .. | AJ46: .. | AK46: .. | AL46: .. | AM46: 2.20111 | AN46: -2.595847 | AO46: .. | AP46: .. | AQ46: .. | AR46: .. | AS46: .. | AT46: .. | AU46: .. | AV46: .. | AW46: .. | AX46: .. | AY46: .. | AZ46: .. | BA46: .. | BB46: .. | BC46: .. | BD46: .. | BE46: ..
... C54: Q1-1960 | D54: .. | E54: .. | F54: .. | G54: .. | H54: .. | I54: .. | J54: .. | K54: .. | L54: .. | M54: .. | N54: .. | O54: .. | P54: .. | Q54: .. | R54: .. | S54: .. | T54: .. | U54: .. | V54: .. | W54: .. | X54: .. | Y54: .. | Z54: .. | AA54: .. | AB54: .. | AC54: .. | AD54: .. | AE54: .. | AF54: .. | AG54: .. | AH54: .. | AI54: .. | AJ54: .. | AK54: .. | AL54: .. | AM54: 2.511293 | AN54: 2.247298 | AO54: .. | AP54: .. | AQ54: .. | AR54: .. | AS54: .. | AT54: .. | AU54: .. | AV54: .. | AW54: .. | AX54: .. | AY54: .. | AZ54: .. | BA54: .. | BB54: .. | BC54: .. | BD54: .. | BE54: ..
C55: Q2-1960 | D55: 2.767342 | E55: 2.339305 | F55: 1.231745 | G55: .. | H55: .. | I55: .. | J55: .. | K55: 0.622803 | L55: .. | M55: 2.221382 | N55: 0.37571 | O55: 1.779654 | P55: 3.419559 | Q55: .. | R55: -0.358006 | S55: 1.359769 | T55: .. | U55: 1.467603 | V55: 0.184344 | W55: 4.496005 | X55: .. | Y55: .. | Z55: 1.082788 | AA55: 0.998135 | AB55: 2.334749 | AC55: .. | AD55: 0.76486 | AE55: .. | AF55: 0.646962 | AG55: .. | AH55: .. | AI55: 2.055865 | AJ55: 1.355258 | AK55: 2.027767 | AL55: .. | AM55: -0.734399 | AN55: -0.539387 | AO55: .. | AP55: .. | AQ55: .. | AR55: .. | AS55: .. | AT55: .. | AU55: .. | AV55: .. | AW55: .. | AX55: .. | AY55: .. | AZ55: .. | BA55: .. | BB55: .. | BC55: .. | BD55: .. | BE55: 1.630733
C56: Q3-1960 | D56: 0.225656 | E56: 1.25508 | F56: 1.223443 | G56: .. | H56: .. | I56: .. | J56: .. | K56: 1.020444 | L56: .. | M56: 1.115974 | N56: 0.748561 | O56: 3.456686 | P56: 3.324659 | Q56: .. | R56: -0.361266 | S56: 1.348899 | T56: .. | U56: 1.468635 | V56: 3.434517 | W56: -1.111563 | X56: .. | Y56: .. | Z56: 1.077075 | AA56: 0.993701 | AB56: -1.71053 | AC56: .. | AD56: 1.223773 | AE56: .. | AF56: 0.927049 | AG56: .. | AH56: .. | AI56: 2.797369 | AJ56: 1.626155 | AK56: 3.665932 | AL56: .. | AM56: 1.513397 | AN56: 0.489275 | AO56: .. | AP56: .. | AQ56: .. | AR56: .. | AS56: .. | AT56: .. | AU56: .. | AV56: .. | AW56: .. | AX56: .. | AY56: .. | AZ56: .. | BA56: .. | BB56: .. | BC56: .. | BD56: .. | BE56: 1.842597
C57: Q4-1960 | D57: -0.199631 | E57: 1.386295 | F57: 1.21526 | G57: .. | H57: .. | I57: .. | J57: .. | K57: 1.407604 | L57: .. | M57: 1.944553 | N57: 1.185218 | O57: 1.022068 | P57: 3.235265 | Q57: .. | R57: -0.364558 | S57: 1.338219 | T57: .. | U57: 0.076755 | V57: 3.843475 | W57: 0.596299 | X57: .. | Y57: .. | Z57: 1.071421 | AA57: 0.9893 | AB57: 1.112932 | AC57: .. | AD57: 1.66812 | AE57: .. | AF57: 1.200127 | AG57: .. | AH57: .. | AI57: 2.013019 | AJ57: 1.871301 | AK57: 0.04389 | AL57: .. | AM57: 0.627601 | AN57: -1.283434 | AO57: .. | AP57: .. | AQ57: .. | AR57: .. | AS57: .. | AT57: .. | AU57: .. | AV57: .. | AW57: .. | AX57: .. | AY57: .. | AZ57: .. | BA57: .. | BB57: .. | BC57: .. | BD57: .. | BE57: 0.987063
C58: Q1-1961 | D58: 0.300797 | E58: 2.805842 | F58: 1.193447 | G58: .. | H58: .. | I58: .. | J58: .. | K58: 1.779961 | L58: .. | M58: 3.483736 | N58: 1.608374 | O58: 1.011728 | P58: 3.097725 | Q58: .. | R58: -0.352241 | S58: 1.308897 | T58: .. | U58: 3.582778 | V58: 3.039762 | W58: 3.200927 | X58: .. | Y58: .. | Z58: 1.049261 | AA58: 0.973395 | AB58: 0.347489 | AC58: .. | AD58: 2.092318 | AE58: .. | AF58: 1.464149 | AG58: .. | AH58: .. | AI58: 2.858311 | AJ58: 1.936295 | AK58: 3.421946 | AL58: .. | AM58: 1.616632 | AN58: 0.675029 | AO58: .. | AP58: .. | AQ58: .. | AR58: .. | AS58: .. | AT58: .. | AU58: .. | AV58: .. | AW58: .. | AX58: .. | AY58: .. | AZ58: .. | BA58: .. | BB58: .. | BC58: .. | BD58: .. | BE58: 0.72532
C59: Q2-1961 | D59: -1.097616 | E59: -0.349959 | F59: 1.167163 | G59: 2.529317 | H59: .. | I59: .. | J59: .. | K59: 1.800291 | L59: .. | M59: 0.737143 | N59: 1.600329 | O59: -0.539334 | P59: 2.990154 | Q59: .. | R59: -0.361198 | S59: 1.282233 | T59: .. | U59: 2.115493 | V59: 2.131382 | W59: 4.316423 | X59: .. | Y59: .. | Z59: 1.031952 | AA59: 0.954347 | AB59: -1.39306 | AC59: .. | AD59: 1.621275 | AE59: .. | AF59: 1.532257 | AG59: .. | AH59: .. | AI59: 4.44113 | AJ59: 0.363512 | AK59: 1.355571 | AL59: .. | AM59: 0.437242 | AN59: 1.697479 | AO59: .. | AP59: .. | AQ59: .. | AR59: .. | AS59: 0.853292 | AT59: .. | AU59: .. | AV59: .. | AW59: .. | AX59: .. | AY59: .. | AZ59: .. | BA59: .. | BB59: .. | BC59: .. | BD59: .. | BE59: -0.436987
C60: Q3-1961 | D60: -0.715607 | E60: 1.256452 | F60: 1.275744 | G60: 2.409293 | H60: .. | I60: .. | J60: .. | K60: 1.819056 | L60: .. | M60: 0.514003 | N60: 1.592219 | O60: 2.052513 | P60: 1.260398 | Q60: .. | R60: 0.979254 | S60: 0.967543 | T60: .. | U60: 2.330642 | V60: 1.918909 | W60: -1.825247 | X60: .. | Y60: .. | Z60: 0.610606 | AA60: 1.007542 | AB60: 0.117012 | AC60: .. | AD60: 1.174078 | AE60: .. | AF60: 1.596982 | AG60: .. | AH60: .. | AI60: 2.042475 | AJ60: 1.386708 | AK60: 1.242126 | AL60: .. | AM60: -0.508876 | AN60: 1.919639 | AO60: .. | AP60: .. | AQ60: .. | AR60: .. | AS60: 1.319684 | AT60: .. | AU60: .. | AV60: .. | AW60: .. | AX60: .. | AY60: .. | AZ60: .. | BA60: .. | BB60: .. | BC60: .. | BD60: .. | BE60: 2.233625
C61: Q4-1961 | D61: 1.139175 | E61: 0.227988 | F61: 1.381074 | G61: 1.39682 | H61: .. | I61: .. | J61: .. | K61: 1.836176 | L61: .. | M61: 2.261307 | N61: 1.699022 | O61: 0.455605 | P61: -0.503747 | Q61: .. | R61: 2.389213 | S61: 0.635146 | T61: .. | U61: 1.913145 | V61: 4.587968 | W61: 1.297044 | X61: .. | Y61: .. | Z61: 0.165051 | AA61: 1.057329 | AB61: 1.605199 | AC61: .. | AD61: 0.743972 | AE61: .. | AF61: 1.658387 | AG61: .. | AH61: .. | AI61: 2.821708 | AJ61: 0.50326 | AK61: 1.958044 | AL61: .. | AM61: -0.173696 | AN61: 1.961109 | AO61: .. | AP61: .. | AQ61: .. | AR61: .. | AS61: 1.057013 | AT61: .. | AU61: .. | AV61: .. | AW61: .. | AX61: .. | AY61: .. | AZ61: .. | BA61: .. | BB61: .. | BC61: .. | BD61: .. | BE61: 0.909
C62: Q1-1962 | D62: 2.8068 | E62: 1.46331 | F62: 1.346942 | G62: 2.650176 | H62: .. | I62: .. | J62: .. | K62: 1.85187 | L62: .. | M62: 1.346843 | N62: 1.800279 | O62: 1.473352 | P62: -0.505157 | Q62: .. | R62: 2.324875 | S62: 0.623615 | T62: .. | U62: 1.479935 | V62: 1.342398 | W62: 1.99193 | X62: .. | Y62: .. | Z62: 0.160319 | AA62: 1.038747 | AB62: 2.720945 | AC62: .. | AD62: 0.325072 | AE62: .. | AF62: 1.716391 | AG62: .. | AH62: .. | AI62: 2.365594 | AJ62: 0.27719 | AK62: 0.575396 | AL62: .. | AM62: 0.435365 | AN62: 1.783599 | AO62: .. | AP62: .. | AQ62: .. | AR62: .. | AS62: 1.333867 | AT62: .. | AU62: .. | AV62: .. | AW62: .. | AX62: .. | AY62: .. | AZ62: .. | BA62: .. | BB62: .. | BC62: .. | BD62: .. | BE62: 2.586581
C63: Q2-1962 | D63: 1.915084 | E63: -0.021812 | F63: 1.322268 | G63: 0.735856 | H63: .. | I63: .. | J63: .. | K63: 1.123347 | L63: .. | M63: -2.533564 | N63: 1.615682 | O63: 1.042344 | P63: -0.501022 | Q63: .. | R63: 2.243607 | S63: 0.616917 | T63: .. | U63: 1.076641 | V63: 1.398082 | W63: -1.868168 | X63: .. | Y63: .. | Z63: 0.16172 | AA63: 1.01864 | AB63: 2.087974 | AC63: .. | AD63: 0.498362 | AE63: .. | AF63: 1.625878 | AG63: .. | AH63: .. | AI63: 2.326176 | AJ63: 1.761047 | AK63: 1.155195 | AL63: .. | AM63: 0.970165 | AN63: 0.903672 | AO63: .. | AP63: .. | AQ63: 1.037677 | AR63: 0.898502 | AS63: 1.187819 | AT63: .. | AU63: 1.07384 | AV63: .. | AW63: .. | AX63: .. | AY63: .. | AZ63: .. | BA63: .. | BB63: .. | BC63: .. | BD63: .. | BE63: 0.640571
C64: Q3-1962 | D64: 0.809857 | E64: 0.839158 | F64: 1.116325 | G64: 1.316875 | H64: .. | I64: .. | J64: .. | K64: 0.423811 | L64: .. | M64: 1.952451 | N64: 1.439785 | O64: 2.39521 | P64: 1.289493 | Q64: .. | R64: 2.41455 | S64: 0.962294 | T64: .. | U64: 0.60037 | V64: 1.221843 | W64: 2.92745 | X64: .. | Y64: .. | Z64: 0.423165 | AA64: 1.402494 | AB64: 3.147562 | AC64: .. | AD64: 0.669292 | AE64: .. | AF64: 1.539338 | AG64: .. | AH64: .. | AI64: 2.449013 | AJ64: 2.44721 | AK64: 1.370741 | AL64: .. | AM64: 0.597242 | AN64: 1.228508 | AO64: .. | AP64: .. | AQ64: 1.297202 | AR64: 1.246269 | AS64: 1.547647 | AT64: .. | AU64: 1.381876 | AV64: .. | AW64: .. | AX64: .. | AY64: .. | AZ64: .. | BA64: .. | BB64: .. | BC64: .. | BD64: .. | BE64: 1.952028
C65: Q4-1962 | D65: 1.795389 | E65: 0.090983 | F65: 0.896895 | G65: 2.037445 | H65: .. | I65: .. | J65: .. | K65: -0.262186 | L65: .. | M65: 1.778152 | N65: 1.251797 | O65: -0.216174 | P65: 3.16425 | Q65: .. | R65: 2.573507 | S65: 1.318175 | T65: .. | U65: 1.501587 | V65: 2.089625 | W65: 2.880018 | X65: .. | Y65: .. | Z65: 0.698328 | AA65: 1.79142 | AB65: -0.341937 | AC65: .. | AD65: 0.837129 | AE65: .. | AF65: 1.456391 | AG65: .. | AH65: .. | AI65: 0.268262 | AJ65: 0.824052 | AK65: 0.645239 | AL65: .. | AM65: -0.353459 | AN65: 0.328861 | AO65: .. | AP65: .. | AQ65: 0.590094 | AR65: 0.550452 | AS65: 0.550854 | AT65: .. | AU65: 0.703482 | AV65: .. | AW65: .. | AX65: .. | AY65: .. | AZ65: .. | BA65: .. | BB65: .. | BC65: .. | BD65: .. | BE65: 1.280861
C66: Q1-1963 | D66: 2.308567 | E66: 0.367611 | F66: 0.881896 | G66: 0.60711 | H66: .. | I66: .. | J66: .. | K66: -0.948882 | L66: .. | M66: -0.934115 | N66: -1.665799 | O66: -3.498026 | P66: 3.049262 | Q66: .. | R66: 2.485089 | S66: 1.289556 | T66: .. | U66: 0.663828 | V66: 1.3667 | W66: 5.859394 | X66: .. | Y66: .. | Z66: 0.696456 | AA66: 1.750783 | AB66: -6.272858 | AC66: .. | AD66: 1.001036 | AE66: .. | AF66: 1.376694 | AG66: .. | AH66: .. | AI66: 5.752953 | AJ66: -1.027403 | AK66: -0.905599 | AL66: .. | AM66: 0.458141 | AN66: 1.091605 | AO66: .. | AP66: .. | AQ66: 0.157421 | AR66: 1.097796 | AS66: -0.639533 | AT66: .. | AU66: 0.365234 | AV66: .. | AW66: .. | AX66: .. | AY66: .. | AZ66: .. | BA66: .. | BB66: .. | BC66: .. | BD66: .. | BE66: 1.322738
C67: Q2-1963 | D67: -1.302552 | E67: 2.915281 | F67: 0.866731 | G67: 1.462353 | H67: .. | I67: .. | J67: .. | K67: 0.138766 | L67: .. | M67: 1.982457 | N67: 4.465475 | O67: 4.484412 | P67: 2.928359 | Q67: .. | R67: 2.408237 | S67: 1.263608 | T67: .. | U67: 2.741399 | V67: 2.943448 | W67: -2.35856 | X67: .. | Y67: .. | Z67: 0.677529 | AA67: 1.701509 | AB67: 8.940364 | AC67: .. | AD67: 1.05742 | AE67: .. | AF67: 1.411944 | AG67: .. | AH67: .. | AI67: 0.08289 | AJ67: 3.823815 | AK67: 3.835381 | AL67: .. | AM67: 4.336478 | AN67: 1.122124 | AO67: .. | AP67: .. | AQ67: 2.451297 | AR67: 1.185722 | AS67: 3.614157 | AT67: .. | AU67: 2.369837 | AV67: .. | AW67: .. | AX67: .. | AY67: .. | AZ67: .. | BA67: .. | BB67: .. | BC67: .. | BD67: .. | BE67: 2.644227
C68: Q3-1963 | D68: 4.103855 | E68: 1.087485 | F68: 1.449747 | G68: 0.777884 | H68: .. | I68: .. | J68: .. | K68: 1.233792 | L68: .. | M68: 1.044761 | N68: 3.298802 | O68: 3.469248 | P68: 2.367085 | Q68: .. | R68: 2.521478 | S68: 1.121534 | T68: .. | U68: 1.641305 | V68: 2.93239 | W68: 3.295069 | X68: .. | Y68: .. | Z68: 1.569827 | AA68: 2.353728 | AB68: 2.402534 | AC68: .. | AD68: 1.111931 | AE68: .. | AF68: 1.445411 | AG68: .. | AH68: .. | AI68: 2.157735 | AJ68: 1.854547 | AK68: 2.228738 | AL68: .. | AM68: 0.473232 | AN68: 2.198426 | AO68: .. | AP68: .. | AQ68: 2.257853 | AR68: 2.101318 | AS68: 2.161235 | AT68: .. | AU68: 2.231263 | AV68: .. | AW68: .. | AX68: .. | AY68: .. | AZ68: .. | BA68: .. | BB68: .. | BC68: .. | BD68: .. | BE68: 2.639167
C69: Q4-1963 | D69: 2.142695 | E69: 2.038743 | F69: 2.0445 | G69: 3.138727 | H69: .. | I69: .. | J69: .. | K69: 2.3006 | L69: .. | M69: 2.116156 | N69: 0.311287 | O69: 0.483966 | P69: 1.796958 | Q69: .. | R69: 2.621829 | S69: 0.968148 | T69: .. | U69: 1.028412 | V69: 3.445524 | W69: 0.093359 | X69: .. | Y69: .. | Z69: 2.483196 | AA69: 2.998675 | AB69: 2.105749 | AC69: .. | AD69: 1.16463 | AE69: .. | AF69: 1.477253 | AG69: .. | AH69: .. | AI69: 1.861636 | AJ69: 0.877163 | AK69: 1.086478 | AL69: .. | AM69: 2.284469 | AN69: 0.655596 | AO69: .. | AP69: .. | AQ69: 1.166889 | AR69: 0.995469 | AS69: 1.19925 | AT69: .. | AU69: 1.298963 | AV69: .. | AW69: .. | AX69: .. | AY69: .. | AZ69: .. | BA69: .. | BB69: .. | BC69: .. | BD69: .. | BE69: 1.762171
C70: Q1-1964 | D70: -0.159554 | E70: 1.006058 | F70: 1.987689 | G70: 2.480652 | H70: .. | I70: .. | J70: .. | K70: 3.306403 | L70: .. | M70: 1.262609 | N70: 1.882604 | O70: 1.375907 | P70: 1.745429 | Q70: .. | R70: 2.529644 | S70: 0.946944 | T70: .. | U70: 1.482283 | V70: 3.189414 | W70: 5.970535 | X70: .. | Y70: .. | Z70: 2.403891 | AA70: 2.887235 | AB70: 1.337372 | AC70: .. | AD70: 1.21533 | AE70: .. | AF70: 1.507421 | AG70: .. | AH70: .. | AI70: 0.565485 | AJ70: 2.477562 | AK70: 0.124763 | AL70: .. | AM70: 0.588959 | AN70: 2.108279 | AO70: .. | AP70: .. | AQ70: 1.919979 | AR70: 2.189191 | AS70: 1.28597 | AT70: .. | AU70: 1.822486 | AV70: .. | AW70: .. | AX70: .. | AY70: .. | AZ70: .. | BA70: .. | BB70: .. | BC70: .. | BD70: .. | BE70: 1.873092
C71: Q2-1964 | D71: 2.467874 | E71: 1.447899 | F71: 1.943286 | G71: 0.368547 | H71: .. | I71: .. | J71: .. | K71: 2.609488 | L71: .. | M71: 0.867411 | N71: 0.958921 | O71: 1.221775 | P71: 1.715967 | Q71: .. | R71: 2.464763 | S71: 0.939508 | T71: .. | U71: -1.011877 | V71: 2.412495 | W71: -2.874867 | X71: .. | Y71: .. | Z71: 2.340656 | AA71: 2.799082 | AB71: 0.864345 | AC71: .. | AD71: 1.28977 | AE71: .. | AF71: 1.69271 | AG71: .. | AH71: .. | AI71: 1.648014 | AJ71: 0.541844 | AK71: 3.526249 | AL71: .. | AM71: 1.770649 | AN71: 1.088705 | AO71: .. | AP71: .. | AQ71: 1.099874 | AR71: 1.149523 | AS71: 1.084336 | AT71: .. | AU71: 1.226775 | AV71: .. | AW71: .. | AX71: .. | AY71: .. | AZ71: .. | BA71: .. | BB71: .. | BC71: .. | BD71: .. | BE71: 1.809867
C72: Q3-1964 | D72: 0.620006 | E72: 0.900528 | F72: 1.344338 | G72: 1.042062 | H72: .. | I72: .. | J72: .. | K72: 1.967067 | L72: .. | M72: 1.604947 | N72: 1.226255 | O72: 1.039094 | P72: 2.157618 | Q72: .. | R72: 1.990518 | S72: 0.720306 | T72: .. | U72: -0.168904 | V72: 1.544361 | W72: 6.805402 | X72: .. | Y72: .. | Z72: 1.266756 | AA72: 2.10163 | AB72: 1.889447 | AC72: .. | AD72: 1.36121 | AE72: .. | AF72: 1.868849 | AG72: .. | AH72: .. | AI72: 0.751293 | AJ72: 1.99575 | AK72: -0.546061 | AL72: .. | AM72: 0.397641 | AN72: 1.562301 | AO72: .. | AP72: .. | AQ72: 1.19592 | AR72: 1.559959 | AS72: 0.816921 | AT72: .. | AU72: 1.223824 | AV72: .. | AW72: .. | AX72: .. | AY72: .. | AZ72: .. | BA72: .. | BB72: .. | BC72: .. | BD72: .. | BE72: 0.939569
C73: Q4-1964 | D73: 2.843349 | E73: 2.854332 | F73: 0.747162 | G73: 0.539892 | H73: .. | I73: .. | J73: .. | K73: 1.364174 | L73: .. | M73: -0.64069 | N73: 0.903739 | O73: 1.360336 | P73: 2.592613 | Q73: .. | R73: 1.526308 | S73: 0.496768 | T73: .. | U73: -0.418483 | V73: 1.250663 | W73: 4.019546 | X73: .. | Y73: .. | Z73: 0.198349 | AA73: 1.422457 | AB73: 1.04979 | AC73: .. | AD73: 1.429614 | AE73: .. | AF73: 2.035035 | AG73: .. | AH73: .. | AI73: 2.17416 | AJ73: 1.07015 | AK73: -0.611582 | AL73: .. | AM73: 1.505971 | AN73: 0.308893 | AO73: .. | AP73: .. | AQ73: 0.66262 | AR73: 0.403434 | AS73: 1.00937 | AT73: .. | AU73: 0.813377 | AV73: .. | AW73: .. | AX73: .. | AY73: .. | AZ73: .. | BA73: .. | BB73: .. | BC73: .. | BD73: .. | BE73: 2.924273
C74: Q1-1965 | D74: 0.83881 | E74: -1.031716 | F74: 0.733465 | G74: 3.147915 | H74: .. | I74: .. | J74: .. | K74: 0.788471 | L74: .. | M74: 3.226252 | N74: 0.221995 | O74: 1.636564 | P74: 2.508262 | Q74: .. | R74: 1.496513 | S74: 0.487566 | T74: .. | U74: 1.350147 | V74: 0.813162 | W74: 1.278574 | X74: .. | Y74: .. | Z74: 0.191471 | AA74: 1.390494 | AB74: 2.887565 | AC74: .. | AD74: 1.494926 | AE74: .. | AF74: 2.191015 | AG74: .. | AH74: .. | AI74: 2.128163 | AJ74: 1.970919 | AK74: 2.485869 | AL74: .. | AM74: -0.272873 | AN74: 2.419765 | AO74: .. | AP74: .. | AQ74: 1.664547 | AR74: 2.402823 | AS74: 1.078998 | AT74: .. | AU74: 1.630144 | AV74: .. | AW74: .. | AX74: .. | AY74: .. | AZ74: .. | BA74: .. | BB74: .. | BC74: .. | BD74: .. | BE74: 1.923998
... C163: Q2-1987 | D163: 1.567668 | E163: 1.764855 | F163: 1.111189 | G163: 1.291593 | H163: .. | I163: .. | J163: .. | K163: 3.024837 | L163: .. | M163: 1.741914 | N163: 1.11615 | O163: 2.244994 | P163: -1.894337 | Q163: .. | R163: 1.964999 | S163: 1.567871 | T163: .. | U163: 1.514382 | V163: 2.095595 | W163: 4.953212 | X163: .. | Y163: .. | Z163: 0.428521 | AA163: 2.736231 | AB163: 1.642376 | AC163: .. | AD163: 2.197221 | AE163: .. | AF163: 1.600811 | AG163: .. | AH163: .. | AI163: 1.496058 | AJ163: 2.212031 | AK163: 0.803005 | AL163: .. | AM163: 1.466913 | AN163: 1.078898 | AO163: .. | AP163: .. | AQ163: 1.454219 | AR163: 1.253333 | AS163: 1.732947 | AT163: .. | AU163: 1.632483 | AV163: .. | AW163: .. | AX163: .. | AY163: .. | AZ163: .. | BA163: .. | BB163: .. | BC163: .. | BD163: .. | BE163: 0.356603
C164: Q3-1987 | D164: 1.818314 | E164: 1.21496 | F164: 1.397513 | G164: 1.522052 | H164: .. | I164: .. | J164: .. | K164: -1.381496 | L164: .. | M164: 0.388183 | N164: 0.810534 | O164: 0.692121 | P164: 0.298791 | Q164: .. | R164: 1.03947 | S164: 1.556645 | T164: .. | U164: 0.288642 | V164: 2.000278 | W164: 0.975698 | X164: .. | Y164: .. | Z164: 0.946731 | AA164: 0.107061 | AB164: 1.146137 | AC164: 0.548754 | AD164: -2.607487 | AE164: .. | AF164: 1.547363 | AG164: .. | AH164: .. | AI164: 2.065203 | AJ164: 1.136552 | AK164: 0.945474 | AL164: .. | AM164: 2.429689 | AN164: 0.867612 | AO164: .. | AP164: .. | AQ164: 1.136776 | AR164: 0.846255 | AS164: 1.067103 | AT164: .. | AU164: 1.106668 | AV164: .. | AW164: .. | AX164: .. | AY164: .. | AZ164: .. | BA164: .. | BB164: .. | BC164: .. | BD164: .. | BE164: 0.364928
C165: Q4-1987 | D165: 2.016821 | E165: 0.810185 | F165: 1.290633 | G165: 1.291892 | H165: .. | I165: .. | J165: .. | K165: 0.595972 | L165: .. | M165: 1.970042 | N165: 1.600155 | O165: 1.5999 | P165: 5.882252 | Q165: .. | R165: 0.103176 | S165: 1.428591 | T165: .. | U165: 1.075995 | V165: 2.574799 | W165: 2.035329 | X165: .. | Y165: .. | Z165: 1.65454 | AA165: 1.208327 | AB165: 0.814298 | AC165: 0.467134 | AD165: 1.813508 | AE165: .. | AF165: 1.197491 | AG165: .. | AH165: .. | AI165: 2.045736 | AJ165: 0.31108 | AK165: 0.918114 | AL165: .. | AM165: 1.132434 | AN165: 1.717053 | AO165: .. | AP165: .. | AQ165: 1.723944 | AR165: 1.634339 | AS165: 1.765625 | AT165: .. | AU165: 1.815513 | AV165: .. | AW165: .. | AX165: .. | AY165: .. | AZ165: .. | BA165: .. | BB165: .. | BC165: .. | BD165: .. | BE165: 1.227632
C166: Q1-1988 | D166: 0.433466 | E166: -1.010978 | F166: 0.99036 | G166: 1.457933 | H166: .. | I166: .. | J166: .. | K166: 0.980073 | L166: .. | M166: 1.273351 | N166: 1.264735 | O166: -0.906973 | P166: 2.302851 | Q166: .. | R166: -0.472976 | S166: 1.270741 | T166: .. | U166: 1.47171 | V166: 2.387213 | W166: 7.703239 | X166: .. | Y166: .. | Z166: 2.222718 | AA166: -0.675506 | AB166: 0.131302 | AC166: -0.380015 | AD166: -0.373494 | AE166: .. | AF166: 4.556632 | AG166: .. | AH166: .. | AI166: 0.321543 | AJ166: 0.478468 | AK166: 0.428505 | AL166: .. | AM166: 1.782169 | AN166: 0.516626 | AO166: .. | AP166: .. | AQ166: 0.945677 | AR166: 0.47723 | AS166: 0.421317 | AT166: .. | AU166: 0.833368 | AV166: .. | AW166: .. | AX166: .. | AY166: .. | AZ166: .. | BA166: .. | BB166: .. | BC166: .. | BD166: .. | BE166: 1.502943
C167: Q2-1988 | D167: 0.071219 | E167: 1.835161 | F167: 0.93208 | G167: 0.885658 | H167: .. | I167: .. | J167: .. | K167: 0.055031 | L167: .. | M167: 0.804068 | N167: 0.66777 | O167: 1.812832 | P167: -3.711947 | Q167: .. | R167: -0.622176 | S167: 1.13657 | T167: .. | U167: 0.63527 | V167: -0.145997 | W167: -2.160737 | X167: .. | Y167: .. | Z167: 2.612815 | AA167: -0.320853 | AB167: 0.761872 | AC167: -0.47604 | AD167: -1.53304 | AE167: .. | AF167: 0.454994 | AG167: .. | AH167: .. | AI167: 1.223182 | AJ167: 0.193407 | AK167: 0.765038 | AL167: .. | AM167: 0.589479 | AN167: 1.313867 | AO167: .. | AP167: .. | AQ167: 0.939647 | AR167: 1.124559 | AS167: 0.741034 | AT167: .. | AU167: 0.714338 | AV167: .. | AW167: .. | AX167: .. | AY167: .. | AZ167: .. | BA167: .. | BB167: .. | BC167: .. | BD167: .. | BE167: 0.710055
C168: Q3-1988 | D168: 0.825655 | E168: 1.661264 | F168: 1.228906 | G168: 0.009099 | H168: .. | I168: .. | J168: .. | K168: -1.901254 | L168: .. | M168: 1.231672 | N168: 1.322 | O168: 1.133076 | P168: 0.73964 | Q168: .. | R168: -0.413715 | S168: 1.018049 | T168: .. | U168: 1.313966 | V168: 2.230947 | W168: 3.145655 | X168: .. | Y168: .. | Z168: 2.880656 | AA168: 0.123422 | AB168: 0.851589 | AC168: 0.223529 | AD168: 0.845117 | AE168: .. | AF168: 0.762613 | AG168: .. | AH168: .. | AI168: 1.802908 | AJ168: 0.165339 | AK168: 1.11191 | AL168: .. | AM168: 1.523026 | AN168: 0.585929 | AO168: .. | AP168: .. | AQ168: 1.087841 | AR168: 0.496444 | AS168: 1.169016 | AT168: .. | AU168: 1.06066 | AV168: .. | AW168: .. | AX168: .. | AY168: .. | AZ168: .. | BA168: .. | BB168: .. | BC168: .. | BD168: .. | BE168: 1.344919
C169: Q4-1988 | D169: 1.551811 | E169: 1.1833 | F169: 0.979885 | G169: 0.697441 | H169: .. | I169: .. | J169: .. | K169: 2.460193 | L169: .. | M169: 1.850135 | N169: 0.946941 | O169: 1.177547 | P169: 1.817496 | Q169: .. | R169: -0.057924 | S169: 1.010502 | T169: .. | U169: 1.193897 | V169: 1.053824 | W169: 3.254636 | X169: .. | Y169: .. | Z169: 2.926296 | AA169: 1.992231 | AB169: 0.93033 | AC169: -0.881404 | AD169: 0.14305 | AE169: .. | AF169: 1.31919 | AG169: .. | AH169: .. | AI169: -0.224282 | AJ169: 2.116757 | AK169: 1.397197 | AL169: .. | AM169: 0.861136 | AN169: 1.332496 | AO169: .. | AP169: .. | AQ169: 1.163047 | AR169: 1.343148 | AS169: 0.913789 | AT169: .. | AU169: 1.164258 | AV169: .. | AW169: .. | AX169: .. | AY169: .. | AZ169: .. | BA169: .. | BB169: .. | BC169: .. | BD169: .. | BE169: 0.93898
C170: Q1-1989 | D170: 1.028487 | E170: 0.82314 | F170: 0.76019 | G170: 1.14072 | H170: .. | I170: .. | J170: .. | K170: 1.1303 | L170: .. | M170: 1.194585 | N170: 1.383199 | O170: 1.045143 | P170: 3.492845 | Q170: .. | R170: 0.198631 | S170: 1.20653 | T170: .. | U170: 0.621204 | V170: 2.69804 | W170: 0.043278 | X170: .. | Y170: .. | Z170: 2.648368 | AA170: 1.873678 | AB170: 1.517732 | AC170: 1.273783 | AD170: -0.65375 | AE170: .. | AF170: 3.766029 | AG170: .. | AH170: .. | AI170: 2.35813 | AJ170: 0.164712 | AK170: 0.441225 | AL170: .. | AM170: 0.440741 | AN170: 1.016602 | AO170: .. | AP170: .. | AQ170: 1.263731 | AR170: 1.107297 | AS170: 0.938769 | AT170: .. | AU170: 1.228831 | AV170: .. | AW170: .. | AX170: .. | AY170: .. | AZ170: .. | BA170: .. | BB170: .. | BC170: .. | BD170: .. | BE170: 0.619316
C171: Q2-1989 | D171: 2.122421 | E171: 0.475649 | F171: 0.961124 | G171: 0.382183 | H171: .. | I171: .. | J171: .. | K171: -2.001584 | L171: .. | M171: 1.757608 | N171: 0.748617 | O171: 0.402548 | P171: -1.108916 | Q171: .. | R171: 0.315227 | S171: 1.581667 | T171: .. | U171: 0.432397 | V171: -1.305732 | W171: 1.460586 | X171: .. | Y171: .. | Z171: 2.140821 | AA171: 0.038206 | AB171: 1.245802 | AC171: 0.587381 | AD171: 1.179425 | AE171: .. | AF171: -1.414135 | AG171: .. | AH171: .. | AI171: 0.984089 | AJ171: 0.675412 | AK171: 1.631376 | AL171: .. | AM171: 0.658382 | AN171: 0.763269 | AO171: .. | AP171: .. | AQ171: 0.312289 | AR171: 0.664096 | AS171: 0.559471 | AT171: .. | AU171: 0.395002 | AV171: .. | AW171: .. | AX171: .. | AY171: .. | AZ171: .. | BA171: .. | BB171: .. | BC171: .. | BD171: .. | BE171: 0.433857
C172: Q3-1989 | D172: 0.810961 | E172: 0.829098 | F172: 0.371448 | G172: 0.357793 | H172: .. | I172: .. | J172: .. | K172: -1.486353 | L172: .. | M172: 1.178507 | N172: 1.175499 | O172: 0.913245 | P172: -1.37456 | Q172: .. | R172: 0.322138 | S172: 2.164625 | T172: .. | U172: 1.042437 | V172: 1.749678 | W172: 2.564383 | X172: .. | Y172: .. | Z172: 1.463473 | AA172: 1.864124 | AB172: 0.877682 | AC172: -1.127209 | AD172: 0.973231 | AE172: .. | AF172: 1.972954 | AG172: .. | AH172: .. | AI172: 1.33968 | AJ172: 0.030822 | AK172: 1.059046 | AL172: .. | AM172: 0.099652 | AN172: 0.740881 | AO172: .. | AP172: .. | AQ172: 0.921983 | AR172: 0.81672 | AS172: 0.90325 | AT172: .. | AU172: 0.994397 | AV172: .. | AW172: .. | AX172: .. | AY172: .. | AZ172: .. | BA172: .. | BB172: .. | BC172: .. | BD172: .. | BE172: 0.080345
C173: Q4-1989 | D173: -0.267811 | E173: 1.300396 | F173: 1.298638 | G173: -0.213453 | H173: .. | I173: .. | J173: .. | K173: 1.657639 | L173: .. | M173: 0.047319 | N173: 1.290842 | O173: 1.158806 | P173: 4.286398 | Q173: .. | R173: 0.28022 | S173: 2.59353 | T173: .. | U173: 1.02914 | V173: 3.098252 | W173: 4.129776 | X173: .. | Y173: .. | Z173: 0.900854 | AA173: -0.881772 | AB173: 0.805274 | AC173: -0.191663 | AD173: 0.69976 | AE173: .. | AF173: 0.832613 | AG173: .. | AH173: .. | AI173: -0.166005 | AJ173: 1.30721 | AK173: 1.33132 | AL173: .. | AM173: 0.095106 | AN173: 0.197047 | AO173: .. | AP173: .. | AQ173: 0.926207 | AR173: 0.06172 | AS173: 1.040718 | AT173: .. | AU173: 0.949252 | AV173: .. | AW173: .. | AX173: .. | AY173: .. | AZ173: .. | BA173: .. | BB173: .. | BC173: .. | BD173: .. | BE173: -0.618832
C174: Q1-1990 | D174: 0.823224 | E174: 1.232355 | F174: 1.563246 | G174: 0.94276 | H174: .. | I174: .. | J174: .. | K174: -0.555739 | L174: .. | M174: 1.347185 | N174: 0.678601 | O174: 2.075707 | P174: 0.943454 | Q174: .. | R174: 0.261792 | S174: 2.52529 | T174: .. | U174: 0.398617 | V174: -0.475764 | W174: 1.018551 | X174: .. | Y174: .. | Z174: 0.788354 | AA174: 2.174245 | AB174: 1.253437 | AC174: -0.171127 | AD174: -0.363566 | AE174: .. | AF174: 1.017439 | AG174: .. | AH174: .. | AI174: 0.876019 | AJ174: 0.212357 | AK174: 1.541258 | AL174: .. | AM174: 0.673994 | AN174: 1.09279 | AO174: .. | AP174: .. | AQ174: 0.800913 | AR174: 1.182536 | AS174: 1.23941 | AT174: .. | AU174: 0.969089 | AV174: .. | AW174: .. | AX174: .. | AY174: .. | AZ174: .. | BA174: .. | BB174: .. | BC174: .. | BD174: .. | BE174: 0.080051
C175: Q2-1990 | D175: 0.134418 | E175: 1.078143 | F175: -0.353728 | G175: -0.414113 | H175: .. | I175: .. | J175: .. | K175: 2.248686 | L175: .. | M175: -1.384869 | N175: 0.352894 | O175: 0.49166 | P175: -2.784216 | Q175: .. | R175: 0.279188 | S175: 2.05928 | T175: .. | U175: 0.304784 | V175: 3.15397 | W175: 2.230622 | X175: .. | Y175: .. | Z175: 1.144336 | AA175: 2.169802 | AB175: 0.836914 | AC175: -0.013316 | AD175: 1.08035 | AE175: .. | AF175: 1.870297 | AG175: .. | AH175: .. | AI175: 1.699634 | AJ175: -0.305109 | AK175: 0.293292 | AL175: .. | AM175: 0.513654 | AN175: 0.362908 | AO175: .. | AP175: .. | AQ175: 0.837182 | AR175: 0.472719 | AS175: 0.582145 | AT175: .. | AU175: 0.906568 | AV175: .. | AW175: .. | AX175: .. | AY175: .. | AZ175: .. | BA175: 2.465261 | BB175: .. | BC175: .. | BD175: .. | BE175: -0.082522
C176: Q3-1990 | D176: -0.590346 | E176: 0.826363 | F176: 0.132865 | G176: -0.707548 | H176: .. | I176: .. | J176: .. | K176: 0.288459 | L176: .. | M176: -2.104898 | N176: 0.443623 | O176: 2.105935 | P176: -6.848248 | Q176: .. | R176: 0.327839 | S176: 1.25767 | T176: .. | U176: 0.160345 | V176: 1.676742 | W176: 3.232928 | X176: .. | Y176: .. | Z176: 1.933531 | AA176: 1.364137 | AB176: 1.362325 | AC176: 0.903646 | AD176: -0.983756 | AE176: .. | AF176: 0.698607 | AG176: .. | AH176: .. | AI176: -0.298469 | AJ176: -0.792885 | AK176: -0.24896 | AL176: .. | AM176: -1.044013 | AN176: 0.066523 | AO176: .. | AP176: .. | AQ176: 0.499472 | AR176: 0.131046 | AS176: 0.070204 | AT176: .. | AU176: 0.369308 | AV176: .. | AW176: .. | AX176: .. | AY176: .. | AZ176: .. | BA176: 1.005079 | BB176: .. | BC176: .. | BD176: .. | BE176: -0.084042
C177: Q4-1990 | D177: 0.579294 | E177: 0.683751 | F177: 1.213354 | G177: -0.891197 | H177: .. | I177: .. | J177: .. | K177: -1.073962 | L177: .. | M177: -0.59637 | N177: 0.247763 | O177: 1.760421 | P177: 10.427888 | Q177: .. | R177: 0.316546 | S177: 0.454682 | T177: .. | U177: -0.649584 | V177: -0.18998 | W177: 2.033266 | X177: .. | Y177: .. | Z177: 2.632888 | AA177: 1.270954 | AB177: 0.792733 | AC177: 1.179382 | AD177: 2.677891 | AE177: .. | AF177: 2.658981 | AG177: .. | AH177: .. | AI177: 3.781683 | AJ177: 1.135943 | AK177: -0.133363 | AL177: .. | AM177: -0.344053 | AN177: -0.910379 | AO177: .. | AP177: .. | AQ177: -0.325976 | AR177: -0.696704 | AS177: 1.22906 | AT177: .. | AU177: 0.247306 | AV177: .. | AW177: .. | AX177: .. | AY177: .. | AZ177: .. | BA177: 1.332368 | BB177: .. | BC177: .. | BD177: .. | BE177: 0.092815
C178: Q1-1991 | D178: -1.292161 | E178: 0.692705 | F178: -0.431525 | G178: -1.427069 | H178: .. | I178: .. | J178: .. | K178: 0.295591 | L178: .. | M178: -1.991179 | N178: -0.037878 | O178: 2.82758 | P178: 0.425654 | Q178: .. | R178: 0.148932 | S178: 0.024823 | T178: .. | U178: 1.973555 | V178: 0.871317 | W178: 3.750176 | X178: .. | Y178: .. | Z178: 2.708053 | AA178: 0.275608 | AB178: -0.406318 | AC178: -2.422439 | AD178: 0.848437 | AE178: .. | AF178: -2.330577 | AG178: .. | AH178: .. | AI178: -1.921754 | AJ178: -0.311367 | AK178: -0.319655 | AL178: .. | AM178: -0.291811 | AN178: -0.467844 | AO178: .. | AP178: .. | AQ178: 0.350533 | AR178: -0.465995 | AS178: 0.339839 | AT178: .. | AU178: 0.118395 | AV178: .. | AW178: .. | AX178: .. | AY178: .. | AZ178: .. | BA178: 3.568991 | BB178: .. | BC178: .. | BD178: .. | BE178: -0.795423
C179: Q2-1991 | D179: -0.132475 | E179: 0.912164 | F179: 1.167533 | G179: 0.466261 | H179: .. | I179: .. | J179: .. | K179: 1.078705 | L179: .. | M179: -1.158097 | N179: 0.339423 | O179: -0.529389 | P179: -1.718026 | Q179: .. | R179: -0.147786 | S179: 0.022641 | T179: .. | U179: -0.547241 | V179: 1.186411 | W179: 1.661478 | X179: .. | Y179: .. | Z179: 2.245889 | AA179: 1.530226 | AB179: 1.17201 | AC179: -0.67886 | AD179: 0.523108 | AE179: .. | AF179: 1.962589 | AG179: .. | AH179: .. | AI179: 1.219275 | AJ179: -1.147189 | AK179: -0.523819 | AL179: .. | AM179: -0.126066 | AN179: 0.779719 | AO179: .. | AP179: .. | AQ179: 0.479369 | AR179: 0.83126 | AS179: 0.129944 | AT179: .. | AU179: 0.587675 | AV179: .. | AW179: .. | AX179: .. | AY179: .. | AZ179: .. | BA179: 2.555984 | BB179: .. | BC179: .. | BD179: .. | BE179: -0.225649
C180: Q3-1991 | D180: 0.41466 | E180: 1.109097 | F180: 0.674732 | G180: 0.133908 | H180: .. | I180: .. | J180: .. | K180: 0.740824 | L180: .. | M180: -2.048741 | N180: 0.325151 | O180: -0.204698 | P180: 1.849351 | Q180: .. | R180: -0.591564 | S180: 0.38784 | T180: .. | U180: 0.03582 | V180: -0.221379 | W180: 2.145297 | X180: .. | Y180: .. | Z180: 1.345213 | AA180: 0.185943 | AB180: 0.408865 | AC180: 0.316478 | AD180: -0.244444 | AE180: .. | AF180: 1.073591 | AG180: .. | AH180: .. | AI180: 0.755272 | AJ180: -0.485888 | AK180: 0.041996 | AL180: .. | AM180: -0.2184 | AN180: 0.505297 | AO180: .. | AP180: .. | AQ180: 0.170086 | AR180: 0.444809 | AS180: 0.218173 | AT180: .. | AU180: 0.296343 | AV180: .. | AW180: .. | AX180: .. | AY180: .. | AZ180: .. | BA180: 1.339736 | BB180: .. | BC180: .. | BD180: .. | BE180: -0.038786
C181: Q4-1991 | D181: 0.069077 | E181: 0.611831 | F181: 0.505904 | G181: 0.184531 | H181: .. | I181: .. | J181: .. | K181: -0.985146 | L181: .. | M181: -1.155161 | N181: 0.418603 | O181: 1.299062 | P181: -0.378223 | Q181: .. | R181: -0.985794 | S181: 0.845025 | T181: .. | U181: 1.173646 | V181: 0.702333 | W181: 2.503572 | X181: .. | Y181: .. | Z181: 0.419942 | AA181: 1.806169 | AB181: 1.109337 | AC181: 0.648451 | AD181: 0.73335 | AE181: .. | AF181: 0.023667 | AG181: .. | AH181: .. | AI181: 0.497512 | AJ181: -0.154936 | AK181: 0.102257 | AL181: .. | AM181: 0.173724 | AN181: 0.348499 | AO181: .. | AP181: .. | AQ181: 0.573831 | AR181: 0.483196 | AS181: 0.683864 | AT181: .. | AU181: 0.633878 | AV181: .. | AW181: .. | AX181: .. | AY181: .. | AZ181: .. | BA181: 1.533549 | BB181: .. | BC181: .. | BD181: .. | BE181: -0.172065
C182: Q1-1992 | D182: 0.747731 | E182: 0.383704 | F182: 1.401939 | G182: 0.072894 | H182: .. | I182: .. | J182: .. | K182: 1.441056 | L182: .. | M182: 0.311182 | N182: 1.026992 | O182: 1.508485 | P182: 2.217449 | Q182: .. | R182: -1.109031 | S182: 1.078896 | T182: .. | U182: 0.268946 | V182: 0.031101 | W182: 1.780393 | X182: .. | Y182: .. | Z182: -0.075741 | AA182: -0.008741 | AB182: 0.707698 | AC182: 0.28485 | AD182: 2.12664 | AE182: .. | AF182: 1.76895 | AG182: .. | AH182: .. | AI182: 0.997701 | AJ182: 0.917573 | AK182: 0.608871 | AL182: .. | AM182: 0.007226 | AN182: 1.197052 | AO182: .. | AP182: .. | AQ182: 0.803723 | AR182: 0.988912 | AS182: 1.012055 | AT182: .. | AU182: 0.877079 | AV182: .. | AW182: .. | AX182: .. | AY182: .. | AZ182: .. | BA182: 1.091365 | BB182: .. | BC182: .. | BD182: .. | BE182: -0.700748
C183: Q2-1992 | D183: 0.716676 | E183: 0.47917 | F183: -1.215734 | G183: 0.122115 | H183: .. | I183: .. | J183: .. | K183: -0.798038 | L183: .. | M183: -1.106439 | N183: -0.08105 | O183: -0.771283 | P183: -3.066087 | Q183: .. | R183: -0.95096 | S183: 1.070613 | T183: .. | U183: -0.057245 | V183: 0.350154 | W183: 0.701695 | X183: .. | Y183: .. | Z183: -0.073511 | AA183: 1.639826 | AB183: -0.918964 | AC183: -0.00779 | AD183: 0.521346 | AE183: .. | AF183: -0.919372 | AG183: .. | AH183: .. | AI183: -1.303955 | AJ183: -0.513648 | AK183: -0.248539 | AL183: .. | AM183: -0.118015 | AN183: 1.084353 | AO183: .. | AP183: .. | AQ183: 0.427817 | AR183: 1.067669 | AS183: -0.513786 | AT183: .. | AU183: 0.300656 | AV183: .. | AW183: .. | AX183: .. | AY183: .. | AZ183: .. | BA183: 1.290625 | BB183: .. | BC183: .. | BD183: .. | BE183: -0.613373
C184: Q3-1992 | D184: 1.012494 | E184: 0.079119 | F184: 0.308941 | G184: 0.536985 | H184: .. | I184: .. | J184: .. | K184: 2.712643 | L184: .. | M184: -0.857412 | N184: 0.039768 | O184: -0.174215 | P184: 1.54795 | Q184: .. | R184: -0.519061 | S184: 0.86266 | T184: .. | U184: -0.222056 | V184: 0.117665 | W184: 0.067624 | X184: .. | Y184: .. | Z184: 0.357165 | AA184: 0.928578 | AB184: 0.30421 | AC184: -0.723685 | AD184: 1.310151 | AE184: .. | AF184: -0.34596 | AG184: .. | AH184: .. | AI184: 0.063867 | AJ184: -1.447436 | AK184: -0.753634 | AL184: .. | AM184: 0.636932 | AN184: 0.988272 | AO184: .. | AP184: .. | AQ184: 0.486856 | AR184: 0.948824 | AS184: 0.234814 | AT184: .. | AU184: 0.514019 | AV184: .. | AW184: .. | AX184: .. | AY184: .. | AZ184: .. | BA184: 3.468743 | BB184: .. | BC184: .. | BD184: .. | BE184: -1.157736
C185: Q4-1992 | D185: 2.055323 | E185: -0.302467 | F185: -1.232574 | G185: 0.568911 | H185: .. | I185: .. | J185: .. | K185: -0.440451 | L185: .. | M185: -0.738267 | N185: -0.2164 | O185: -0.308767 | P185: -0.532171 | Q185: .. | R185: 0.034808 | S185: 0.61684 | T185: .. | U185: -0.689307 | V185: -0.637501 | W185: 1.560678 | X185: .. | Y185: .. | Z185: 0.920053 | AA185: 0.083307 | AB185: 0.376705 | AC185: 1.246262 | AD185: -0.715902 | AE185: .. | AF185: -0.159542 | AG185: .. | AH185: .. | AI185: -0.651596 | AJ185: -1.3723 | AK185: -0.710536 | AL185: .. | AM185: 0.696567 | AN185: 1.043165 | AO185: .. | AP185: .. | AQ185: 0.313201 | AR185: 0.911977 | AS185: -0.216619 | AT185: .. | AU185: 0.271304 | AV185: .. | AW185: .. | AX185: .. | AY185: .. | AZ185: .. | BA185: 0.502289 | BB185: .. | BC185: .. | BD185: .. | BE185: -0.849714
C186: Q1-1993 | D186: 0.693628 | E186: -0.239481 | F186: -0.759719 | G186: 0.639946 | H186: .. | I186: .. | J186: .. | K186: -1.201042 | L186: .. | M186: 0.251461 | N186: -0.622904 | O186: -0.733959 | P186: -2.653931 | Q186: .. | R186: 0.530908 | S186: 0.500612 | T186: .. | U186: -0.139465 | V186: 1.126858 | W186: 1.990658 | X186: .. | Y186: .. | Z186: 1.277109 | AA186: -0.066284 | AB186: 0.615913 | AC186: 1.634308 | AD186: -0.658 | AE186: .. | AF186: -1.318635 | AG186: .. | AH186: .. | AI186: -0.932984 | AJ186: -1.759533 | AK186: 0.043779 | AL186: .. | AM186: 0.723362 | AN186: 0.1674 | AO186: .. | AP186: .. | AQ186: 0.210578 | AR186: 0.179233 | AS186: -0.200063 | AT186: .. | AU186: 0.211417 | AV186: .. | AW186: .. | AX186: .. | AY186: .. | AZ186: .. | BA186: 1.921954 | BB186: .. | BC186: .. | BD186: .. | BE186: 0.885902
C187: Q2-1993 | D187: 0.563039 | E187: 0.570549 | F187: 1.010258 | G187: 0.910433 | H187: .. | I187: .. | J187: .. | K187: -0.413519 | L187: .. | M187: -0.183707 | N187: 0.069557 | O187: -0.027136 | P187: 1.709362 | Q187: .. | R187: 0.904944 | S187: 0.530792 | T187: .. | U187: -0.241254 | V187: -0.633146 | W187: 2.565332 | X187: .. | Y187: .. | Z187: 1.392368 | AA187: 0.28159 | AB187: 0.249896 | AC187: 2.216041 | AD187: 1.736163 | AE187: .. | AF187: 0.050114 | AG187: 1.390938 | AH187: .. | AI187: -0.006775 | AJ187: 1.220529 | AK187: 0.773674 | AL187: .. | AM187: 0.495765 | AN187: 0.58242 | AO187: .. | AP187: .. | AQ187: 0.201305 | AR187: 0.576972 | AS187: 0.508459 | AT187: .. | AU187: 0.430339 | AV187: 2.852959 | AW187: .. | AX187: .. | AY187: .. | AZ187: .. | BA187: 1.146154 | BB187: .. | BC187: .. | BD187: .. | BE187: 1.096857
C188: Q3-1993 | D188: 0.106079 | E188: 1.019557 | F188: 0.316448 | G188: 0.953047 | H188: .. | I188: .. | J188: .. | K188: 0.165747 | L188: .. | M188: 0.612303 | N188: 0.156527 | O188: 0.597099 | P188: 0.340401 | Q188: .. | R188: 1.210699 | S188: 0.713413 | T188: .. | U188: -0.157709 | V188: -0.717862 | W188: 1.843683 | X188: .. | Y188: .. | Z188: 1.336456 | AA188: 1.089796 | AB188: 0.817258 | AC188: 2.021146 | AD188: 1.992508 | AE188: .. | AF188: 0.695529 | AG188: 1.159825 | AH188: .. | AI188: 1.203187 | AJ188: 1.242977 | AK188: 0.220969 | AL188: .. | AM188: 0.787833 | AN188: 0.477315 | AO188: .. | AP188: .. | AQ188: 0.249829 | AR188: 0.572936 | AS188: 0.508326 | AT188: .. | AU188: 0.399106 | AV188: 2.010236 | AW188: .. | AX188: .. | AY188: .. | AZ188: .. | BA188: 3.35959 | BB188: .. | BC188: .. | BD188: .. | BE188: 1.439518
C189: Q4-1993 | D189: 1.850849 | E189: 0.702701 | F189: 0.952397 | G189: 0.431684 | H189: .. | I189: .. | J189: .. | K189: 2.188264 | L189: .. | M189: 0.742252 | N189: 0.20767 | O189: -0.094431 | P189: 0.199288 | Q189: .. | R189: 1.341705 | S189: 1.002046 | T189: .. | U189: 0.733131 | V189: 0.630002 | W189: 1.913664 | X189: .. | Y189: .. | Z189: 1.162644 | AA189: 1.26084 | AB189: -0.620387 | AC189: 0.934331 | AD189: 3.557926 | AE189: .. | AF189: 0.335462 | AG189: 1.506507 | AH189: .. | AI189: 0.376846 | AJ189: 0.05316 | AK189: 0.480108 | AL189: .. | AM189: 0.663723 | AN189: 1.360113 | AO189: .. | AP189: .. | AQ189: 0.842935 | AR189: 1.281122 | AS189: 0.412614 | AT189: .. | AU189: 0.867483 | AV189: 0.805455 | AW189: .. | AX189: .. | AY189: .. | AZ189: .. | BA189: 3.340133 | BB189: .. | BC189: .. | BD189: .. | BE189: 0.740852
C190: Q1-1994 | D190: 1.67445 | E190: 0.321516 | F190: 0.703595 | G190: 1.473569 | H190: .. | I190: .. | J190: .. | K190: 1.222447 | L190: .. | M190: 0.652979 | N190: 0.753358 | O190: 1.400839 | P190: -0.79253 | Q190: .. | R190: 1.202459 | S190: 1.350758 | T190: .. | U190: 0.761669 | V190: 0.857894 | W190: 2.916856 | X190: .. | Y190: .. | Z190: 0.949749 | AA190: 1.001237 | AB190: 1.496532 | AC190: 1.527094 | AD190: -1.140089 | AE190: .. | AF190: 0.338694 | AG190: 1.788229 | AH190: .. | AI190: 0.827092 | AJ190: 1.050465 | AK190: 0.466317 | AL190: .. | AM190: 1.175703 | AN190: 0.970216 | AO190: .. | AP190: .. | AQ190: 1.003991 | AR190: 1.008906 | AS190: 0.736506 | AT190: .. | AU190: 0.941968 | AV190: 1.421339 | AW190: .. | AX190: .. | AY190: .. | AZ190: .. | BA190: 0.913822 | BB190: .. | BC190: .. | BD190: .. | BE190: -0.142492
C191: Q2-1994 | D191: 1.248578 | E191: 0.172232 | F191: 1.149796 | G191: 1.461329 | H191: .. | I191: .. | J191: 0.96711 | K191: 2.928827 | L191: .. | M191: 0.884649 | N191: 1.064656 | O191: 0.239678 | P191: 1.218187 | Q191: .. | R191: 0.853415 | S191: 1.729524 | T191: .. | U191: 0.723639 | V191: -0.487152 | W191: 1.631592 | X191: .. | Y191: .. | Z191: 0.753365 | AA191: 2.115978 | AB191: 1.150385 | AC191: 0.672665 | AD191: 2.328959 | AE191: .. | AF191: 1.295818 | AG191: 1.218534 | AH191: .. | AI191: 0.219253 | AJ191: 1.064856 | AK191: -0.319434 | AL191: .. | AM191: 1.166949 | AN191: 1.355046 | AO191: .. | AP191: .. | AQ191: 0.826879 | AR191: 1.433233 | AS191: -0.038497 | AT191: .. | AU191: 0.577505 | AV191: 2.06826 | AW191: .. | AX191: .. | AY191: .. | AZ191: .. | BA191: 2.742164 | BB191: .. | BC191: .. | BD191: .. | BE191: 1.084857
C192: Q3-1994 | D192: 0.76275 | E192: 0.906741 | F192: 0.279731 | G192: 1.278408 | H192: .. | I192: .. | J192: 1.359144 | K192: -0.468872 | L192: .. | M192: 2.24553 | N192: 0.583053 | O192: 0.71732 | P192: 2.68223 | Q192: .. | R192: 0.306349 | S192: 2.188892 | T192: .. | U192: 0.623469 | V192: 1.13338 | W192: 1.682264 | X192: .. | Y192: .. | Z192: 0.557057 | AA192: 0.829187 | AB192: 0.758168 | AC192: 1.705266 | AD192: -1.358604 | AE192: .. | AF192: 0.45219 | AG192: 1.899671 | AH192: .. | AI192: 0.793995 | AJ192: 1.107003 | AK192: 0.690416 | AL192: .. | AM192: 1.142816 | AN192: 0.584515 | AO192: .. | AP192: .. | AQ192: 0.767293 | AR192: 0.659141 | AS192: 1.021613 | AT192: .. | AU192: 0.895471 | AV192: 0.252391 | AW192: .. | AX192: .. | AY192: .. | AZ192: .. | BA192: -0.037292 | BB192: .. | BC192: .. | BD192: .. | BE192: 1.124755
C193: Q4-1994 | D193: 0.968372 | E193: 1.350074 | F193: 1.682112 | G193: 0.729647 | H193: .. | I193: .. | J193: 2.186255 | K193: 2.508937 | L193: .. | M193: 2.53254 | N193: 0.879058 | O193: 1.160648 | P193: -0.821639 | Q193: .. | R193: -0.182251 | S193: 2.532276 | T193: .. | U193: 0.938947 | V193: -0.412296 | W193: 3.930372 | X193: .. | Y193: .. | Z193: 0.383916 | AA193: 1.119214 | AB193: 0.946898 | AC193: 1.31208 | AD193: 3.952132 | AE193: .. | AF193: 1.201951 | AG193: 1.416355 | AH193: .. | AI193: 0.374223 | AJ193: 1.518328 | AK193: 0.337664 | AL193: .. | AM193: 0.606516 | AN193: 1.145524 | AO193: .. | AP193: .. | AQ193: 0.784939 | AR193: 1.111785 | AS193: 1.095669 | AT193: .. | AU193: 0.971584 | AV193: 1.240935 | AW193: .. | AX193: .. | AY193: .. | AZ193: .. | BA193: -0.051386 | BB193: .. | BC193: .. | BD193: .. | BE193: 1.669118
C194: Q1-1995 | D194: -0.02851 | E194: 0.83618 | F194: -0.054236 | G194: 0.929487 | H194: .. | I194: .. | J194: 1.708042 | K194: 0.514219 | L194: .. | M194: -0.83645 | N194: 0.555433 | O194: -0.338987 | P194: -0.038825 | Q194: .. | R194: -3.564529 | S194: 3.818071 | T194: .. | U194: 1.255575 | V194: 1.149186 | W194: 2.090489 | X194: .. | Y194: .. | Z194: -0.157725 | AA194: -5.794059 | AB194: 0.680303 | AC194: 1.206886 | AD194: -0.78111 | AE194: .. | AF194: 0.174017 | AG194: 1.53385 | AH194: .. | AI194: 1.142035 | AJ194: 1.155917 | AK194: -0.567789 | AL194: .. | AM194: 0.424576 | AN194: 0.354756 | AO194: .. | AP194: .. | AQ194: 0.52199 | AR194: -0.174586 | AS194: 0.582267 | AT194: .. | AU194: 0.372623 | AV194: -1.543122 | AW194: .. | AX194: .. | AY194: .. | AZ194: .. | BA194: 5.370422 | BB194: .. | BC194: .. | BD194: .. | BE194: 0.361223
C195: Q2-1995 | D195: 0.36583 | E195: 0.424044 | F195: 0.419169 | G195: 0.040378 | H195: 2.757815 | I195: .. | J195: 0.395625 | K195: -0.286098 | L195: -0.993752 | M195: 2.699216 | N195: 0.418027 | O195: 0.745687 | P195: 0.945757 | Q195: -0.127885 | R195: 2.727119 | S195: 1.48048 | T195: 2.479855 | U195: 0.070151 | V195: 1.043504 | W195: 2.021825 | X195: 0.511314 | Y195: 2.094388 | Z195: -0.045947 | AA195: -4.85673 | AB195: 0.78455 | AC195: 1.298975 | AD195: 0.872484 | AE195: 1.793545 | AF195: 1.179904 | AG195: 1.642375 | AH195: 0.246609 | AI195: 0.620257 | AJ195: 0.690019 | AK195: 0.269555 | AL195: .. | AM195: 0.369617 | AN195: 0.298341 | AO195: 0.540662 | AP195: 1.069477 | AQ195: 0.463669 | AR195: -0.174102 | AS195: 0.618485 | AT195: .. | AU195: 0.383889 | AV195: -3.790304 | AW195: .. | AX195: 11.780249 | AY195: .. | AZ195: .. | BA195: 2.037695 | BB195: 0.456607 | BC195: .. | BD195: .. | BE195: 0.444021
C196: Q3-1995 | D196: 2.271779 | E196: 0.226813 | F196: 0.599515 | G196: 0.131785 | H196: 0.489261 | I196: .. | J196: 2.919067 | K196: 0.417052 | L196: -0.340539 | M196: -0.467034 | N196: 0.158103 | O196: 0.19478 | P196: 0.53673 | Q196: 0.03067 | R196: -0.382872 | S196: 3.065847 | T196: 1.218011 | U196: 0.444806 | V196: 1.165065 | W196: 2.075873 | X196: -1.110499 | Y196: -0.388232 | Z196: 0.278648 | AA196: 1.949221 | AB196: 0.785696 | AC196: 0.915691 | AD196: 2.356395 | AE196: 3.498459 | AF196: 0.434255 | AG196: 0.589071 | AH196: 0.219092 | AI196: 0.403677 | AJ196: 0.520455 | AK196: 0.711039 | AL196: .. | AM196: 0.924107 | AN196: 0.850678 | AO196: 0.220221 | AP196: 0.39461 | AQ196: 0.725836 | AR196: 0.888064 | AS196: 0.590038 | AT196: .. | AU196: 0.858836 | AV196: -0.3863 | AW196: .. | AX196: 0.495019 | AY196: .. | AZ196: .. | BA196: 0.388976 | BB196: 2.049338 | BC196: .. | BD196: .. | BE196: 0.431641
C197: Q4-1995 | D197: 0.065984 | E197: 0.344772 | F197: 0.206074 | G197: 0.409813 | H197: 1.839742 | I197: .. | J197: -0.770604 | K197: 0.731687 | L197: 1.167915 | M197: 0.097081 | N197: 0.181632 | O197: 0.012961 | P197: 0.579493 | Q197: -0.419157 | R197: 0.929585 | S197: 1.435485 | T197: 0.748505 | U197: 0.828153 | V197: 0.243377 | W197: 1.870552 | X197: 1.297719 | Y197: 2.504466 | Z197: 6.664823 | AA197: 1.8685 | AB197: 0.712376 | AC197: 0.676701 | AD197: 1.233616 | AE197: 1.441684 | AF197: 0.677616 | AG197: 1.891536 | AH197: 0.241843 | AI197: 0.760056 | AJ197: 0.841609 | AK197: 0.112866 | AL197: .. | AM197: 0.128709 | AN197: 0.679021 | AO197: 0.347176 | AP197: 0.559357 | AQ197: 0.45058 | AR197: 0.759375 | AS197: 0.391911 | AT197: .. | AU197: 0.561294 | AV197: 0.766785 | AW197: .. | AX197: 8.859343 | AY197: .. | AZ197: .. | BA197: 1.369193 | BB197: -2.77967 | BC197: .. | BD197: .. | BE197: 0.394653
C198: Q1-1996 | D198: 1.673673 | E198: 0.788649 | F198: -0.200092 | G198: 0.068806 | H198: 3.079252 | I198: .. | J198: 2.381027 | K198: 0.01503 | L198: 0.900385 | M198: 1.739299 | N198: 0.56411 | O198: -0.816382 | P198: 0.54386 | Q198: 0.511444 | R198: 2.702942 | S198: 2.108566 | T198: 1.008504 | U198: 0.162496 | V198: 0.81386 | W198: 1.908135 | X198: -1.319337 | Y198: 1.024893 | Z198: -4.35659 | AA198: 2.608201 | AB198: 0.410828 | AC198: 1.384235 | AD198: 1.510292 | AE198: 1.252627 | AF198: 0.789605 | AG198: 1.68699 | AH198: 0.671677 | AI198: 0.591061 | AJ198: 0.557047 | AK198: 0.243562 | AL198: .. | AM198: 0.918213 | AN198: 0.748947 | AO198: 0.131318 | AP198: -0.089631 | AQ198: 0.510677 | AR198: 0.856908 | AS198: 0.418749 | AT198: .. | AU198: 0.720585 | AV198: 2.74966 | AW198: .. | AX198: 1.132525 | AY198: .. | AZ198: .. | BA198: 1.687403 | BB198: 3.312315 | BC198: .. | BD198: .. | BE198: 1.403239
C199: Q2-1996 | D199: 0.701031 | E199: 0.741262 | F199: 0.700333 | G199: 0.696293 | H199: 1.184746 | I199: .. | J199: 0.707958 | K199: 2.708013 | L199: 1.700092 | M199: 0.317763 | N199: 0.245571 | O199: 1.358769 | P199: 0.573365 | Q199: -0.539169 | R199: 0.995529 | S199: 2.119151 | T199: 1.21402 | U199: -0.00901 | V199: 1.241617 | W199: 2.020152 | X199: -0.012026 | Y199: -0.60134 | Z199: 1.139207 | AA199: 1.38835 | AB199: 1.114967 | AC199: 0.89845 | AD199: -0.13699 | AE199: 2.159137 | AF199: 1.199317 | AG199: 1.198098 | AH199: 1.119744 | AI199: 0.738336 | AJ199: -0.556339 | AK199: -0.282476 | AL199: .. | AM199: 0.356152 | AN199: 1.667847 | AO199: 0.761693 | AP199: 0.779211 | AQ199: 1.197288 | AR199: 1.571114 | AS199: 0.672935 | AT199: .. | AU199: 1.164809 | AV199: 2.228766 | AW199: -0.475161 | AX199: -1.120462 | AY199: .. | AZ199: .. | BA199: 3.21657 | BB199: 1.843061 | BC199: .. | BD199: .. | BE199: 1.873041
C200: Q3-1996 | D200: 0.800383 | E200: 0.214976 | F200: 0.460415 | G200: 0.863973 | H200: 1.171628 | I200: .. | J200: 0.44457 | K200: 0.282819 | L200: 3.176585 | M200: 1.194172 | N200: 0.565834 | O200: 0.348029 | P200: 1.360367 | Q200: -0.084959 | R200: -1.343523 | S200: 0.085362 | T200: 1.180359 | U200: 0.119586 | V200: 0.04599 | W200: 1.758931 | X200: 3.469479 | Y200: 4.003955 | Z200: -0.751133 | AA200: 1.748996 | AB200: 1.400073 | AC200: 0.648542 | AD200: 3.332495 | AE200: 0.932279 | AF200: 1.356716 | AG200: 2.502705 | AH200: 1.29264 | AI200: 0.856899 | AJ200: 0.522455 | AK200: -0.275724 | AL200: .. | AM200: 0.88106 | AN200: 0.896991 | AO200: 0.517588 | AP200: 0.505245 | AQ200: 0.602683 | AR200: 0.968569 | AS200: 0.597352 | AT200: .. | AU200: 0.717067 | AV200: 2.296678 | AW200: 4.016458 | AX200: -4.821188 | AY200: .. | AZ200: 0.488981 | BA200: 1.872111 | BB200: 0.74759 | BC200: .. | BD200: .. | BE200: 1.13476
C201: Q4-1996 | D201: 0.905419 | E201: 0.36057 | F201: 0.789992 | G201: 0.805366 | H201: 1.323899 | I201: .. | J201: 0.096089 | K201: 0.034009 | L201: 2.029042 | M201: 2.162957 | N201: 0.142219 | O201: 0.745021 | P201: 1.058755 | Q201: 1.239555 | R201: 2.293128 | S201: 1.812029 | T201: 1.518276 | U201: -0.306911 | V201: 1.15675 | W201: 1.691579 | X201: 6.503962 | Y201: 0.489051 | Z201: 1.742489 | AA201: 2.95393 | AB201: 0.710941 | AC201: 1.327775 | AD201: -1.604247 | AE201: -2.354566 | AF201: 0.282345 | AG201: 1.973257 | AH201: 1.757576 | AI201: 0.533381 | AJ201: 0.489232 | AK201: 0.536791 | AL201: .. | AM201: 0.770455 | AN201: 1.038382 | AO201: 0.450725 | AP201: 0.386952 | AQ201: 0.833994 | AR201: 1.18888 | AS201: 0.554604 | AT201: .. | AU201: 0.940802 | AV201: 1.822266 | AW201: -1.072573 | AX201: -2.10361 | AY201: .. | AZ201: 1.585574 | BA201: 3.246264 | BB201: -0.203441 | BC201: .. | BD201: .. | BE201: 0.948474
C202: Q1-1997 | D202: 0.621524 | E202: 0.50946 | F202: 1.00228 | G202: 1.319174 | H202: 1.094454 | I202: .. | J202: -0.410133 | K202: 1.255106 | L202: 3.62231 | M202: 0.113365 | N202: 0.34099 | O202: -0.532365 | P202: 0.570057 | Q202: 0.90459 | R202: 3.69213 | S202: 3.712477 | T202: 1.283244 | U202: 0.358404 | V202: 0.295351 | W202: 0.468064 | X202: -2.112681 | Y202: 1.516769 | Z202: 1.590016 | AA202: 0.132891 | AB202: 1.090973 | AC202: -0.370087 | AD202: 2.685007 | AE202: 5.34025 | AF202: 1.644786 | AG202: 0.993019 | AH202: 0.540183 | AI202: 1.015319 | AJ202: 0.951141 | AK202: 0.74707 | AL202: .. | AM202: 1.38064 | AN202: 0.645564 | AO202: 0.228637 | AP202: 0.353946 | AQ202: 0.49056 | AR202: 0.64943 | AS202: 0.672737 | AT202: .. | AU202: 0.593734 | AV202: 2.100205 | AW202: 0.771558 | AX202: -10.131994 | AY202: .. | AZ202: 0.752362 | BA202: -1.251111 | BB202: -2.360777 | BC202: .. | BD202: .. | BE202: 0.287285
C203: Q2-1997 | D203: 2.955118 | E203: 0.318231 | F203: 1.545284 | G203: 1.129632 | H203: 2.347896 | I203: .. | J203: -0.303583 | K203: 1.717487 | L203: 4.209205 | M203: 3.084927 | N203: 1.13302 | O203: 1.281884 | P203: 1.715417 | Q203: 1.078219 | R203: 0.549023 | S203: 4.300145 | T203: 0.561786 | U203: 1.320606 | V203: -0.66909 | W203: 3.550553 | X203: 4.512733 | Y203: 2.94696 | Z203: 2.149841 | AA203: 2.33741 | AB203: 1.04123 | AC203: 1.983256 | AD203: 2.412173 | AE203: 1.375099 | AF203: 0.908657 | AG203: 1.480989 | AH203: 2.221527 | AI203: 0.907002 | AJ203: 1.161791 | AK203: 0.716372 | AL203: .. | AM203: 0.863254 | AN203: 1.662001 | AO203: 1.274002 | AP203: 1.255605 | AQ203: 1.072731 | AR203: 1.682447 | AS203: 1.311342 | AT203: .. | AU203: 1.305597 | AV203: 1.487514 | AW203: 0.987619 | AX203: -1.052188 | AY203: .. | AZ203: 0.409848 | BA203: 1.309338 | BB203: -1.78958 | BC203: .. | BD203: .. | BE203: 0.611664
C204: Q3-1997 | D204: 0.124656 | E204: 1.227514 | F204: 0.881374 | G204: 1.183434 | H204: 2.369165 | I204: .. | J204: -0.634806 | K204: -0.282299 | L204: 2.692892 | M204: 1.772407 | N204: 0.721068 | O204: 0.341733 | P204: 1.594936 | Q204: 0.912613 | R204: -0.620592 | S204: 2.113282 | T204: 0.08628 | U204: 0.659926 | V204: 0.227811 | W204: 0.791744 | X204: 1.656271 | Y204: 3.318399 | Z204: 2.337989 | AA204: 1.954788 | AB204: 1.45276 | AC204: -0.26649 | AD204: -0.107515 | AE204: -0.227469 | AF204: 1.300985 | AG204: 1.640448 | AH204: 0.903755 | AI204: 1.189482 | AJ204: 0.92045 | AK204: 1.195439 | AL204: .. | AM204: 0.734954 | AN204: 1.250848 | AO204: 0.768958 | AP204: 0.713106 | AQ204: 0.85477 | AR204: 1.308667 | AS204: 0.713754 | AT204: .. | AU204: 0.910326 | AV204: 2.517217 | AW204: 1.245894 | AX204: 2.233028 | AY204: .. | AZ204: 1.192832 | BA204: 1.871091 | BB204: -1.626745 | BC204: .. | BD204: .. | BE204: 0.208898
C205: Q4-1997 | D205: 1.418101 | E205: 1.169908 | F205: 0.558254 | G205: 0.968322 | H205: 2.045483 | I205: .. | J205: -0.222875 | K205: -0.013656 | L205: 3.134722 | M205: 2.126604 | N205: 1.14321 | O205: 0.744198 | P205: 0.953177 | Q205: 0.882286 | R205: 2.441713 | S205: 2.461252 | T205: 1.739723 | U205: 1.695681 | V205: 0.031944 | W205: -0.455994 | X205: 1.206719 | Y205: 1.895036 | Z205: 0.06254 | AA205: 2.418303 | AB205: 1.28298 | AC205: -0.215332 | AD205: 1.412948 | AE205: 3.012318 | AF205: 0.672339 | AG205: -0.518231 | AH205: 0.382223 | AI205: 1.379163 | AJ205: 1.805734 | AK205: 0.919728 | AL205: .. | AM205: 1.187646 | AN205: 0.858817 | AO205: 1.137663 | AP205: 1.145333 | AQ205: 0.815238 | AR205: 1.00684 | AS205: 1.265273 | AT205: .. | AU205: 0.928316 | AV205: 1.351458 | AW205: 0.735348 | AX205: -3.357688 | AY205: .. | AZ205: 1.600856 | BA205: -0.513921 | BB205: -0.619432 | BC205: .. | BD205: .. | BE205: 0.150986
C206: Q1-1998 | D206: 0.679534 | E206: 0.877418 | F206: 0.25986 | G206: 1.412415 | H206: -0.40595 | I206: .. | J206: -0.005993 | K206: 1.507788 | L206: 0.820196 | M206: -0.596989 | N206: 0.847356 | O206: 0.920176 | P206: 1.200955 | Q206: 0.829756 | R206: -2.598461 | S206: 1.291117 | T206: 1.537906 | U206: -0.589411 | V206: -1.11984 | W206: -6.818022 | X206: 4.636005 | Y206: 1.574327 | Z206: 1.408009 | AA206: 0.910494 | AB206: 1.349037 | AC206: -0.592681 | AD206: 0.96467 | AE206: 1.537556 | AF206: 1.447623 | AG206: 1.772675 | AH206: 0.619733 | AI206: 0.876199 | AJ206: 0.474218 | AK206: 0.676149 | AL206: .. | AM206: 0.867851 | AN206: 0.99948 | AO206: 0.679331 | AP206: 0.713986 | AQ206: 0.513074 | AR206: 1.021731 | AS206: 0.710366 | AT206: .. | AU206: 0.412569 | AV206: 0.517422 | AW206: -2.075375 | AX206: 11.696016 | AY206: .. | AZ206: 1.630075 | BA206: -7.35721 | BB206: 0.993061 | BC206: .. | BD206: .. | BE206: 0.126386
C207: Q2-1998 | D207: 0.980955 | E207: 1.129331 | F207: 0.332491 | G207: 0.053398 | H207: 2.002305 | I207: .. | J207: 0.290401 | K207: -0.755217 | L207: -0.581102 | M207: 1.968391 | N207: 0.912045 | O207: -0.421783 | P207: 0.442647 | Q207: 1.472898 | R207: 9.998217 | S207: 2.392165 | T207: 0.013125 | U207: 0.487452 | V207: -0.417305 | W207: -0.807932 | X207: -0.138559 | Y207: 2.004672 | Z207: 2.531814 | AA207: 0.772152 | AB207: 0.71569 | AC207: 0.49608 | AD207: 1.13311 | AE207: -0.19589 | AF207: 1.535727 | AG207: 0.023148 | AH207: 0.704773 | AI207: 1.12799 | AJ207: 1.352665 | AK207: 1.196073 | AL207: -0.095249 | AM207: 0.88229 | AN207: 0.925807 | AO207: 0.4448 | AP207: 0.424944 | AQ207: 0.484204 | AR207: 0.84747 | AS207: 0.505314 | AT207: 0.393691 | AU207: 0.504523 | AV207: 1.959505 | AW207: 1.608862 | AX207: -6.533145 | AY207: .. | AZ207: 1.310736 | BA207: -7.83899 | BB207: -1.207539 | BC207: .. | BD207: .. | BE207: 0.141419
C208: Q3-1998 | D208: 1.927661 | E208: 0.232115 | F208: 0.292249 | G208: 0.91021 | H208: -0.463898 | I208: .. | J208: -0.030559 | K208: 1.837315 | L208: -0.100677 | M208: 1.910666 | N208: 0.708762 | O208: 0.49832 | P208: 0.350709 | Q208: 0.896477 | R208: -0.383592 | S208: 3.967172 | T208: 0.807924 | U208: 0.112228 | V208: 0.177442 | W208: 1.747152 | X208: -1.071224 | Y208: 1.03024 | Z208: 1.469901 | AA208: 0.45739 | AB208: 0.853584 | AC208: 0.1582 | AD208: -1.793527 | AE208: 0.893556 | AF208: 1.108509 | AG208: -0.800784 | AH208: 0.853555 | AI208: 0.94474 | AJ208: 0.671216 | AK208: -0.091712 | AL208: 0.495544 | AM208: 0.682859 | AN208: 1.252567 | AO208: 0.546154 | AP208: 0.581112 | AQ208: 0.816197 | AR208: 1.155272 | AS208: 0.568744 | AT208: 0.706314 | AU208: 0.778412 | AV208: -0.304614 | AW208: 0.268442 | AX208: 0.774985 | AY208: .. | AZ208: 1.814746 | BA208: -1.114245 | BB208: -0.990795 | BC208: .. | BD208: .. | BE208: -0.219162
C209: Q4-1998 | D209: 1.544605 | E209: 0.391695 | F209: 0.222451 | G209: 1.36067 | H209: -3.508287 | I209: .. | J209: 0.079477 | K209: 0.320757 | L209: -1.831249 | M209: 1.213948 | N209: 0.733352 | O209: -0.446266 | P209: 0.787562 | Q209: 0.128895 | R209: 3.238256 | S209: -2.176766 | T209: 0.900914 | U209: -0.418108 | V209: 0.776905 | W209: 2.49605 | X209: -1.997838 | Y209: -0.111916 | Z209: 0.480026 | AA209: 0.155862 | AB209: 0.915112 | AC209: 0.994199 | AD209: 0.511433 | AE209: 0.76369 | AF209: 0.75322 | AG209: 7.447638 | AH209: 0.743763 | AI209: 1.098467 | AJ209: 0.957129 | AK209: -0.336799 | AL209: -2.592175 | AM209: 1.009396 | AN209: 1.61588 | AO209: 0.099954 | AP209: 0.14811 | AQ209: 0.991137 | AR209: 1.465529 | AS209: 0.143145 | AT209: 0.753866 | AU209: 0.804108 | AV209: -2.549266 | AW209: -1.194759 | AX209: -1.482982 | AY209: .. | AZ209: 1.31071 | BA209: -2.792811 | BB209: 0.170927 | BC209: .. | BD209: .. | BE209: 0.096626
C210: Q1-1999 | D210: 0.774103 | E210: 1.019024 | F210: 1.044885 | G210: 1.813816 | H210: -0.318761 | I210: .. | J210: 0.060137 | K210: 0.906036 | L210: -0.762814 | M210: 0.489044 | N210: 0.555099 | O210: 1.158067 | P210: 0.760693 | Q210: -0.042904 | R210: -0.121209 | S210: 5.42413 | T210: -0.82329 | U210: 0.628459 | V210: -1.266123 | W210: 3.034633 | X210: 2.782373 | Y210: -1.770512 | Z210: 2.640841 | AA210: 1.049295 | AB210: 1.666754 | AC210: 1.178662 | AD210: 0.723129 | AE210: 0.117497 | AF210: 1.329203 | AG210: -3.304526 | AH210: 1.673555 | AI210: 0.998461 | AJ210: 1.263902 | AK210: 0.056597 | AL210: -2.53035 | AM210: 0.630714 | AN210: 0.946472 | AO210: 1.049381 | AP210: 0.991527 | AQ210: 0.567757 | AR210: 1.0189 | AS210: 0.690742 | AT210: 0.890658 | AU210: 0.630076 | AV210: -1.245853 | AW210: -0.073516 | AX210: -2.325127 | AY210: .. | AZ210: 1.624153 | BA210: 5.647681 | BB210: -0.434437 | BC210: .. | BD210: .. | BE210: 0.919591
C211: Q2-1999 | D211: 0.331984 | E211: 0.969339 | F211: 1.368068 | G211: 0.836545 | H211: 0.273996 | I211: .. | J211: 0.401036 | K211: 0.516383 | L211: 0.915058 | M211: 0.957016 | N211: 0.849373 | O211: 3e-06 | P211: 0.935578 | Q211: 1.116868 | R211: -2.202791 | S211: 1.187157 | T211: 4.249935 | U211: 0.381715 | V211: 0.342012 | W211: 4.383165 | X211: -0.931498 | Y211: 0.827438 | Z211: 2.702373 | AA211: 0.611934 | AB211: 1.112902 | AC211: 0.842246 | AD211: 0.045591 | AE211: 2.339416 | AF211: 0.522081 | AG211: -1.684163 | AH211: 4.242262 | AI211: 1.186015 | AJ211: 0.504392 | AK211: 0.89915 | AL211: 0.827989 | AM211: 0.206315 | AN211: 0.769159 | AO211: 0.578077 | AP211: 0.603918 | AQ211: 0.558963 | AR211: 0.760108 | AS211: 0.608893 | AT211: 0.9322 | AU211: 0.739567 | AV211: -1.129907 | AW211: 0.593593 | AX211: -2.641358 | AY211: .. | AZ211: 2.582232 | BA211: -0.054983 | BB211: -0.277158 | BC211: .. | BD211: .. | BE211: 0.795848
C212: Q3-1999 | D212: 1.167218 | E212: 1.377681 | F212: 1.453518 | G212: 1.564676 | H212: 2.503275 | I212: .. | J212: 0.953318 | K212: 0.618053 | L212: 1.047168 | M212: 0.772897 | N212: 1.174051 | O212: 1.157065 | P212: 0.383309 | Q212: 1.847181 | R212: 0.566721 | S212: 4.726995 | T212: 0.45026 | U212: 0.819412 | V212: 0.564318 | W212: 2.781171 | X212: 3.061626 | Y212: -1.804742 | Z212: 3.315803 | AA212: 0.814327 | AB212: 1.377229 | AC212: 2.766407 | AD212: 2.054678 | AE212: 2.157822 | AF212: 0.980385 | AG212: -0.623748 | AH212: -2.573016 | AI212: 1.32946 | AJ212: 0.926988 | AK212: 0.642804 | AL212: 0.381461 | AM212: 1.838799 | AN212: 1.309665 | AO212: 1.151623 | AP212: 1.146835 | AQ212: 1.177475 | AR212: 1.28437 | AS212: 1.213798 | AT212: 1.204702 | AU212: 1.21647 | AV212: -0.28815 | AW212: 0.188565 | AX212: -0.839935 | AY212: .. | AZ212: 1.245329 | BA212: 0.273417 | BB212: 1.090803 | BC212: .. | BD212: .. | BE212: 1.092119
C213: Q4-1999 | D213: 1.697148 | E213: 0.847969 | F213: 1.184127 | G213: 1.406696 | H213: 2.235366 | I213: .. | J213: 1.078568 | K213: 1.398796 | L213: 2.608876 | M213: 1.491181 | N213: 1.370071 | O213: 0.778773 | P213: 1.599426 | Q213: 1.21572 | R213: 4.011253 | S213: 2.382782 | T213: 1.955979 | U213: 1.503664 | V213: 0.05633 | W213: 2.886255 | X213: 3.66042 | Y213: 0.090329 | Z213: 0.604439 | AA213: 1.039653 | AB213: 1.406875 | AC213: 1.245614 | AD213: 1.720367 | AE213: 2.147328 | AF213: 0.574361 | AG213: -0.451956 | AH213: 1.734821 | AI213: 1.134279 | AJ213: 1.781641 | AK213: 2.368032 | AL213: 0.280583 | AM213: 1.440921 | AN213: 1.699585 | AO213: 1.184724 | AP213: 1.230437 | AQ213: 1.272165 | AR213: 1.61955 | AS213: 1.250838 | AT213: 1.376392 | AU213: 1.315705 | AV213: 1.672821 | AW213: 1.490743 | AX213: -5.439363 | AY213: .. | AZ213: 1.65076 | BA213: 0.107212 | BB213: 0.879268 | BC213: .. | BD213: .. | BE213: 1.099653
...

Sheet US_GDP_deflator
A1: FRED Graph Observations
A2: Federal Reserve Economic Data
A3: Link: https://fred.stlouisfed.org
A4: Help: https://fred.stlouisfed.org/help-faq
A5: Economic Research Division
A6: Federal Reserve Bank of St. Louis
A8: GDPDEF | B8: Gross Domestic Product: Implicit Price Deflator, Index 2012=100, Quarterly, Seasonally Adjusted
A10: Frequency: Quarterly
A11: observation_date | B11: GDPDEF
A12: 17168 | B12: 11.96
A13: 17258 | B13: 12.131
A14: 17349 | B14: 12.335
A15: 17441 | B15: 12.639
A16: 17533 | B16: 12.739
A17: 17624 | B17: 12.854
A18: 17715 | B18: 13.092
A19: 17807 | B19: 13.132
A20: 17899 | B20: 13.062
A21: 17989 | B21: 12.931
A22: 18080 | B22: 12.872
A23: 18172 | B23: 12.873
... A305: 43922 | B305: 112.803

Sheet 3-month_Tbill
A1: FRED Graph Observations
A2: Federal Reserve Economic Data
A3: Link: https://fred.stlouisfed.org
A4: Help: https://fred.stlouisfed.org/help-faq
A5: Economic Research Division
A6: Federal Reserve Bank of St. Louis
A8: DGS3MO | B8: 3-Month Treasury Constant Maturity Rate, Percent, Monthly, Not Seasonally Adjusted
A10: Frequency: Monthly
A11: observation_date | B11: DGS3MO
A12: 29830 | B12: 15.607143
A13: 29860 | B13: 14.230952
A14: 29891 | B14: 11.345556
A15: 29921 | B15: 11.319048
A16: 29952 | B16: 12.918
A17: 29983 | B17: 14.279444
A18: 30011 | B18: 13.314783
A19: 30042 | B19: 13.344762
A20: 30072 | B20: 12.714
A21: 30103 | B21: 13.078636
A22: 30133 | B22: 11.863333
A23: 30164 | B23: 8.9972727
... A478: 44013 | B478: 0.12681818
A479: 44044 | B479: =NA() -> #N/A

Sheet oilprice
B1: PrecioPetro
A2: 36526 | B2: 22.84
A3: 36557 | B3: 24.26
A4: 36586 | B4: 24.88
A5: 36617 | B5: 21.79
A6: 36647 | B6: 24.35
A7: 36678 | B7: 26.59
A8: 36708 | B8: 24.19
A9: 36739 | B9: 25.74
A10: 36770 | B10: 27.96
A11: 36800 | B11: 27.91
A12: 36831 | B12: 27.27
A13: 36861 | B13: 20.58
... A241: 43800 | B241: 54.026274

Sheet oilprod
B1: Average daily barrels (thousands) | C1: Annualized production (million barrels)
A2: 39083 | B2: 517.08944 | C2: =B2*365/1000 -> 188.73765
A3: 39114 | B3: 507.22912 | C3: =B3*365/1000 -> 185.13863
A4: 39142 | B4: 482.07936 | C4: =B4*365/1000 -> 175.95897
A5: 39173 | B5: 502.05687 | C5: =B5*365/1000 -> 183.25076
A6: 39203 | B6: 511.69011 | C6: =B6*365/1000 -> 186.76689
A7: 39234 | B7: 514.6335 | C7: =B7*365/1000 -> 187.84123
A8: 39264 | B8: 509.66261 | C8: =B8*365/1000 -> 186.02685
A9: 39295 | B9: 508.26649 | C9: =B9*365/1000 -> 185.51727
A10: 39326 | B10: 516.86131 | C10: =B10*365/1000 -> 188.65438
A11: 39356 | B11: 513.58603 | C11: =B11*365/1000 -> 187.4589
A12: 39387 | B12: 518.04188 | C12: =B12*365/1000 -> 189.08529
A13: 39417 | B13: 531.71979 | C13: =B13*365/1000 -> 194.07772
... A215: 45566 | B215: 471.74557 | C215: =B215*365/1000 -> 172.18713

Sheet oilrevenue
B1: Revenue (million $) | C1: Annual average | D1: GDP Deflator USA | E1: Real annual average
A2: 39083 | B2: =oilprice!B86*oilprod!C2 -> 7591.0281
A3: 39114 | B3: =oilprice!B87*oilprod!C3 -> 8570.0672
A4: 39142 | B4: =oilprice!B88*oilprod!C4 -> 8511.1352
A5: 39173 | B5: =oilprice!B89*oilprod!C5 -> 9604.1722
A6: 39203 | B6: =oilprice!B90*oilprod!C6 -> 10044.323
A7: 39234 | B7: =oilprice!B91*oilprod!C7 -> 10695.68
A8: 39264 | B8: =oilprice!B92*oilprod!C8 -> 11855.491
A9: 39295 | B9: =oilprice!B93*oilprod!C9 -> 11357.367
A10: 39326 | B10: =oilprice!B94*oilprod!C10 -> 12202.165
A11: 39356 | B11: =oilprice!B95*oilprod!C11 -> 13377.067
A12: 39387 | B12: =oilprice!B96*oilprod!C12 -> 15090.897
A13: 39417 | B13: =oilprice!B97*oilprod!C13 -> 14984.741 | C13: =AVERAGE(B2:B13) -> 11157.011 | D13: 86.346 | E13: =C13/(D13/100) -> 12921.283
A14: 39448 | B14: =oilprice!B98*oilprod!C14 -> 14622.443
A15: 39479 | B15: =oilprice!B99*oilprod!C15 -> 15209.166
A16: 39508 | B16: =oilprice!B100*oilprod!C16 -> 16319.096
A17: 39539 | B17: =oilprice!B101*oilprod!C17 -> 17554.174
A18: 39569 | B18: =oilprice!B102*oilprod!C18 -> 19427.769
A19: 39600 | B19: =oilprice!B103*oilprod!C19 -> 21195.992
A20: 39630 | B20: =oilprice!B104*oilprod!C20 -> 20802.547
A21: 39661 | B21: =oilprice!B105*oilprod!C21 -> 18302.688
A22: 39692 | B22: =oilprice!B106*oilprod!C22 -> 16135.448
A23: 39722 | B23: =oilprice!B107*oilprod!C23 -> 11566.877
A24: 39753 | B24: =oilprice!B108*oilprod!C24 -> 8064.0193
A25: 39783 | B25: =oilprice!B109*oilprod!C25 -> 4834.1999 | C25: =AVERAGE(B14:B25) -> 15336.202 | D25: 88.016 | E25: =C25/(D25/100) -> 17424.334
A26: 39814 | B26: =oilprice!B110*oilprod!C26 -> 4923.5149
A27: 39845 | B27: =oilprice!B111*oilprod!C27 -> 4845.8741
A28: 39873 | B28: =oilprice!B112*oilprod!C28 -> 6588.0512
A29: 39904 | B29: =oilprice!B113*oilprod!C29 -> 7222.3683
A30: 39934 | B30: =oilprice!B114*oilprod!C30 -> 8891.1587
A31: 39965 | B31: =oilprice!B115*oilprod!C31 -> 11262.222
A32: 39995 | B32: =oilprice!B116*oilprod!C32 -> 9943.2665
A33: 40026 | B33: =oilprice!B117*oilprod!C33 -> 11069.965
A34: 40057 | B34: =oilprice!B118*oilprod!C34 -> 11118.33
A35: 40087 | B35: =oilprice!B119*oilprod!C35 -> 11965.948
A36: 40118 | B36: =oilprice!B120*oilprod!C36 -> 12264.268
A37: 40148 | B37: =oilprice!B121*oilprod!C37 -> 11633.218 | C37: =AVERAGE(B26:B37) -> 9310.682 | D37: 88.555 | E37: =C37/(D37/100) -> 10514.011
A38: 40179 | B38: =oilprice!B122*oilprod!C38 -> 12272.862
A39: 40210 | B39: =oilprice!B123*oilprod!C39 -> 11962.727
A40: 40238 | B40: =oilprice!B124*oilprod!C40 -> 12768.512
A41: 40269 | B41: =oilprice!B125*oilprod!C41 -> 13183.068
A42: 40299 | B42: =oilprice!B126*oilprod!C42 -> 11385.197
A43: 40330 | B43: =oilprice!B127*oilprod!C43 -> 11990.217
A44: 40360 | B44: =oilprice!B128*oilprod!C44 -> 12383.155
A45: 40391 | B45: =oilprice!B129*oilprod!C45 -> 12230.472
A46: 40422 | B46: =oilprice!B130*oilprod!C46 -> 12019.253
A47: 40452 | B47: =oilprice!B131*oilprod!C47 -> 13542.21
A48: 40483 | B48: =oilprice!B132*oilprod!C48 -> 14329.328
A49: 40513 | B49: =oilprice!B133*oilprod!C49 -> 14857.565 | C49: =AVERAGE(B38:B49) -> 12743.714 | D49: 89.629 | E49: =C49/(D49/100) -> 14218.293
A50: 40544 | B50: =oilprice!B134*oilprod!C50 -> 15142.118
A51: 40575 | B51: =oilprice!B135*oilprod!C51 -> 15520.221
A52: 40603 | B52: =oilprice!B136*oilprod!C52 -> 18226.469
A53: 40634 | B53: =oilprice!B137*oilprod!C53 -> 20240.578
A54: 40664 | B54: =oilprice!B138*oilprod!C54 -> 18637.577
A55: 40695 | B55: =oilprice!B139*oilprod!C55 -> 17563.394
A56: 40725 | B56: =oilprice!B140*oilprod!C56 -> 17538.118
A57: 40756 | B57: =oilprice!B141*oilprod!C57 -> 16009.06
A58: 40787 | B58: =oilprice!B142*oilprod!C58 -> 17022.64
A59: 40817 | B59: =oilprice!B143*oilprod!C59 -> 18565.492
A60: 40848 | B60: =oilprice!B144*oilprod!C60 -> 20585.013
A61: 40878 | B61: =oilprice!B145*oilprod!C61 -> 19245.842 | C61: =AVERAGE(B50:B61) -> 17858.044 | D61: 91.478 | E61: =C61/(D61/100) -> 19521.681
A62: 40909 | B62: =oilprice!B146*oilprod!C62 -> 18349.79
A63: 40940 | B63: =oilprice!B147*oilprod!C63 -> 19124.765
A64: 40969 | B64: =oilprice!B148*oilprod!C64 -> 20495.27
A65: 41000 | B65: =oilprice!B149*oilprod!C65 -> 20439.013
A66: 41030 | B66: =oilprice!B150*oilprod!C66 -> 18438.235
A67: 41061 | B67: =oilprice!B151*oilprod!C67 -> 15839.168
A68: 41091 | B68: =oilprice!B152*oilprod!C68 -> 16765.93
A69: 41122 | B69: =oilprice!B153*oilprod!C69 -> 17894.424
A70: 41153 | B70: =oilprice!B154*oilprod!C70 -> 18439.086
A71: 41183 | B71: =oilprice!B155*oilprod!C71 -> 17379.936
A72: 41214 | B72: =oilprice!B156*oilprod!C72 -> 16836.127
A73: 41244 | B73: =oilprice!B157*oilprod!C73 -> 17090.63 | C73: =AVERAGE(B62:B73) -> 18091.031 | D73: 93.184 | E73: =C73/(D73/100) -> 19414.31
A74: 41275 | B74: =oilprice!B158*oilprod!C74 -> 18518.967
A75: 41306 | B75: =oilprice!B159*oilprod!C75 -> 18668.302
A76: 41334 | B76: =oilprice!B160*oilprod!C76 -> 18008.658
A77: 41365 | B77: =oilprice!B161*oilprod!C77 -> 18052.24
A78: 41395 | B78: =oilprice!B162*oilprod!C78 -> 18399.425
A79: 41426 | B79: =oilprice!B163*oilprod!C79 -> 18144.409
A80: 41456 | B80: =oilprice!B164*oilprod!C80 -> 19649.88
A81: 41487 | B81: =oilprice!B165*oilprod!C81 -> 19189.722
A82: 41518 | B82: =oilprice!B166*oilprod!C82 -> 19058.85
A83: 41548 | B83: =oilprice!B167*oilprod!C83 -> 18167.373
A84: 41579 | B84: =oilprice!B168*oilprod!C84 -> 16834.73
A85: 41609 | B85: =oilprice!B169*oilprod!C85 -> 18155.525 | C85: =AVERAGE(B74:B85) -> 18404.007 | D85: 94.767 | E85: =C85/(D85/100) -> 19420.269
A86: 41640 | B86: =oilprice!B170*oilprod!C86 -> 18399.365
A87: 41671 | B87: =oilprice!B171*oilprod!C87 -> 19774.204
A88: 41699 | B88: =oilprice!B172*oilprod!C88 -> 19617.53
A89: 41730 | B89: =oilprice!B173*oilprod!C89 -> 20087.013
A90: 41760 | B90: =oilprice!B174*oilprod!C90 -> 19416.05
A91: 41791 | B91: =oilprice!B175*oilprod!C91 -> 20111.411
A92: 41821 | B92: =oilprice!B176*oilprod!C92 -> 18563.335
A93: 41852 | B93: =oilprice!B177*oilprod!C93 -> 17583.558
A94: 41883 | B94: =oilprice!B178*oilprod!C94 -> 16790.607
A95: 41913 | B95: =oilprice!B179*oilprod!C95 -> 14898.294
A96: 41944 | B96: =oilprice!B180*oilprod!C96 -> 12623.756
A97: 41974 | B97: =oilprice!B181*oilprod!C97 -> 9226.2708 | C97: =AVERAGE(B86:B97) -> 17257.616 | D97: 96.417 | E97: =C97/(D97/100) -> 17898.935
A98: 42005 | B98: =oilprice!B182*oilprod!C98 -> 8427.282
A99: 42036 | B99: =oilprice!B183*oilprod!C99 -> 8286.6063
A100: 42064 | B100: =oilprice!B184*oilprod!C100 -> 8627.0879
...

Sheet EMBI
B1: EMBI
A2: 36526 | B2: 3672.8
A3: 36557 | B3: 4043.05
A4: 36586 | B4: 3115.2174
A5: 36617 | B5: 3372.0526
A6: 36647 | B6: 3971.7273
A7: 36678 | B7: 4416.2273
A8: 36708 | B8: 3795.75
A9: 36739 | B9: 2574.6957
A10: 36770 | B10: 1297.05
A11: 36800 | B11: 1300.6667
A12: 36831 | B12: 1352.5238
A13: 36861 | B13: 1451.1
... A241: 43800 | B241: 937.87097

Sheet fiscal
B1: OPERACIONES DEL SECTOR PUBLICO NO FINANCIERO (base devengado)
B2: Millones de dólares
A4: Regresar
A5: Transacciones \ Período | B5: 2000 | N5: 2001 | Z5: 2002 | AL5: 2003 | AX5: 2004 | BJ5: 2005 | BV5: 2006 | CH5: 2007 | CT5: 2008(p) | DF5: 2009(p) | DR5: 2010(p) | ED5: 2011(p) | EP5: 2012(p) | FB5: 2013(p) | FN5: 2014(p) | FZ5: 2015(p) | GL5: 2016(p) | GX5: 2017 (p)
B6: ene | C6: feb | D6: mar | E6: abr | F6: may | G6: jun | H6: jul | I6: ago | J6: sep | K6: oct | L6: nov | M6: dic | N6: ene | O6: feb | P6: mar | Q6: abr | R6: may | S6: jun | T6: jul | U6: ago | V6: sep | W6: oct | X6: nov | Y6: dic | Z6: ene | AA6: feb | AB6: mar | AC6: abr | AD6: may | AE6: jun | AF6: jul | AG6: ago | AH6: sep | AI6: oct | AJ6: nov | AK6: dic | AL6: ene | AM6: feb | AN6: mar | AO6: abr | AP6: may | AQ6: jun | AR6: jul | AS6: ago | AT6: sep | AU6: oct | AV6: nov | AW6: dic | AX6: ene | AY6: feb | AZ6: mar | BA6: abr | BB6: may | BC6: jun | BD6: jul | BE6: ago | BF6: sep | BG6: oct | BH6: nov | BI6: dic | BJ6: ene | BK6: feb | BL6: mar | BM6: abr | BN6: may | BO6: jun | BP6: jul | BQ6: ago | BR6: sep | BS6: oct | BT6: nov | BU6: dic | BV6: ene | BW6: feb | BX6: mar | BY6: abr | BZ6: may | CA6: jun | CB6: jul | CC6: ago | CD6: sep | CE6: oct | CF6: nov | CG6: dic | CH6: ene | CI6: feb | CJ6: mar | CK6: abr | CL6: may | CM6: jun | CN6: jul | CO6: ago | CP6: sep | CQ6: oct | CR6: nov | CS6: dic | CT6: ene | CU6: feb | CV6: mar | CW6: abr | CX6: may | CY6: jun | CZ6: jul | DA6: ago | DB6: sep | DC6: oct | DD6: nov | DE6: dic | DF6: ene | DG6: feb | DH6: mar | DI6: abr | DJ6: may | DK6: jun | DL6: jul | DM6: ago | DN6: sep | DO6: oct | DP6: nov | DQ6: dic | DR6: ene | DS6: feb | DT6: mar | DU6: abr | DV6: may | DW6: jun | DX6: jul | DY6: ago | DZ6: sep | EA6: oct | EB6: nov | EC6: dic | ED6: ene | EE6: feb | EF6: mar | EG6: abr | EH6: may | EI6: jun | EJ6: jul | EK6: ago | EL6: sep | EM6: oct | EN6: nov | EO6: dic | EP6: ene | EQ6: feb | ER6: mar | ES6: abr | ET6: may | EU6: jun | EV6: jul | EW6: ago | EX6: sep | EY6: oct | EZ6: nov | FA6: dic | FB6: ene | FC6: feb | FD6: mar | FE6: abr | FF6: may | FG6: jun | FH6: jul | FI6: ago | FJ6: sep | FK6: oct | FL6: nov | FM6: dic | FN6: ene | FO6: feb | FP6: mar | FQ6: abr | FR6: may | FS6: jun | FT6: jul | FU6: ago | FV6: sep | FW6: oct | FX6: nov | FY6: dic | FZ6: ene | GA6: feb | GB6: mar | GC6: abr | GD6: may | GE6: jun | GF6: jul | GG6: ago | GH6: sep | GI6: oct | GJ6: nov | GK6: dic | GL6: ene | GM6: feb | GN6: mar | GO6: abr | GP6: may | GQ6: jun | GR6: jul | GS6: ago | GT6: sep | GU6: oct | GV6: nov | GW6: dic | GX6: ene | GY6: feb | GZ6: mar | HA6: abr | HB6: may | HC6: jun | HD6: jul | HE6: ago | HF6: sep | HG6: oct | HH6: nov | HI6: dic
A8: Total Ingresos | B8: 242.75826 | C8: 267.39158 | D8: 281.8634 | E8: 302.18365 | F8: 290.22926 | G8: 372.12609 | H8: 360.22563 | I8: 412.28131 | J8: 417.95036 | K8: 416.0813 | L8: 396.04892 | M8: 375.86743 | N8: 398.51058 | O8: 393.01389 | P8: 382.61056 | Q8: 535.72429 | R8: 406.57534 | S8: 406.52862 | T8: 396.759 | U8: 476.76594 | V8: 410.8935 | W8: 396.56073 | X8: 392.70707 | Y8: 357.95487 | Z8: 502.4135 | AA8: 490.38181 | AB8: 443.48845 | AC8: 640.62465 | AD8: 531.47698 | AE8: 522.95648 | AF8: 543.79836 | AG8: 482.49788 | AH8: 621.46729 | AI8: 607.48556 | AJ8: 482.82309 | AK8: 491.46232 | AL8: 585.31699 | AM8: 467.41172 | AN8: 552.87224 | AO8: 649.63277 | AP8: 497.51759 | AQ8: 582.32201 | AR8: 631.63957 | AS8: 553.98721 | AT8: 636.22056 | AU8: 627.87551 | AV8: 481.53596 | AW8: 643.91074 | AX8: 632.74382 | AY8: 521.38172 | AZ8: 688.42303 | BA8: 717.01715 | BB8: 683.6181 | BC8: 646.21449 | BD8: 675.54333 | BE8: 724.21677 | BF8: 768.06682 | BG8: 745.77128 | BH8: 713.26587 | BI8: 660.21419 | BJ8: 701.35057 | BK8: 639.0993 | BL8: 672.14153 | BM8: 998.63135 | BN8: 737.90325 | BO8: 691.54311 | BP8: 856.67139 | BQ8: 773.05299 | BR8: 749.33316 | BS8: 760.33609 | BT8: 761.15081 | BU8: 804.53002 | BV8: 965.68623 | BW8: 631.88142 | BX8: 944.37881 | BY8: 1131.5403 | BZ8: 1100.0516 | CA8: 867.04725 | CB8: 902.1569 | CC8: 758.16661 | CD8: 794.35046 | CE8: 1318.2641 | CF8: 993.08067 | CG8: 856.11426 | CH8: 1019.2328 | CI8: 831.52408 | CJ8: 877.99765 | CK8: 1375.9956 | CL8: 986.9742 | CM8: 937.97586 | CN8: 1238.1443 | CO8: 1317.7953 | CP8: 1258.8738 | CQ8: 1233.6912 | CR8: 1268.5912 | CS8: 1283.7966 | CT8: 1432.3735 | CU8: 1771.4709 | CV8: 1717.3492 | CW8: 2052.9382 | CX8: 2049.7223 | CY8: 1781.3367 | CZ8: 2146.4793 | DA8: 2319.5286 | DB8: 1789.6549 | DC8: 2058.7098 | DD8: 1507.9556 | DE8: 1480.8561 | DF8: 1214.0228 | DG8: 989.83274 | DH8: 1242.3095 | DI8: 1934.0359 | DJ8: 1415.3083 | DK8: 1432.591 | DL8: 1518.0217 | DM8: 1314.2621 | DN8: 1989.2162 | DO8: 1679.8888 | DP8: 2068.69 | DQ8: 1580.2339 | DR8: 1974.9008 | DS8: 1576.7587 | DT8: 2257.0031 | DU8: 2200.742 | DV8: 1991.4034 | DW8: 1682.5124 | DX8: 1953.3373 | DY8: 1754.7547 | DZ8: 1772.5639 | EA8: 1981.4012 | EB8: 1909.5161 | EC8: 2123.5082 | ED8: 2353.2268 | EE8: 2139.8585 | EF8: 2497.6567 | EG8: 2906.6329 | EH8: 2370.7732 | EI8: 2933.5933 | EJ8: 2528.679 | EK8: 2578.9366 | EL8: 2784.1152 | EM8: 2505.7208 | EN8: 2346.1658 | EO8: 3244.4143 | EP8: 2848.4995 | EQ8: 2743.6756 | ER8: 2962.6431 | ES8: 3535.5275 | ET8: 2944.4107 | EU8: 2739.751 | EV8: 2889.7993 | EW8: 2751.1133 | EX8: 2974.6689 | EY8: 2803.5549 | EZ8: 2663.5039 | FA8: 2712.4401 | FB8: 3228.9133 | FC8: 2505.9366 | FD8: 3058.8742 | FE8: 3777.4828 | FF8: 3084.4171 | FG8: 2667.6388 | FH8: 3577.8607 | FI8: 3044.7999 | FJ8: 3093.4515 | FK8: 3268.3003 | FL8: 3031.1972 | FM8: 2920.8824 | FN8: 3348.5439 | FO8: 2616.2871 | FP8: 3270.4763 | FQ8: 4089.1046 | FR8: 3193.6412 | FS8: 3498.3322 | FT8: 3349.5715 | FU8: 2827.1989 | FV8: 3238.199 | FW8: 3215.9854 | FX8: 3307.5028 | FY8: 3077.2071 | FZ8: 2847.8176 | GA8: 2650.8311 | GB8: 2733.1377 | GC8: 3406.4901 | GD8: 2958.1749 | GE8: 3163.1338 | GF8: 3683.7481 | GG8: 2492.8256 | GH8: 2499.9254 | GI8: 2490.5015 | GJ8: 2372.5349 | GK8: 2022.6006 | GL8: 2558.5489 | GM8: 2325.4254 | GN8: 2321.0814 | GO8: 2677.1545 | GP8: 2034.0975 | GQ8: 2521.1193 | GR8: 2426.3712 | GS8: 2667.4967 | GT8: 2458.1738 | GU8: 2505.728 | GV8: 2341.1074 | GW8: 3477.7807 | GX8: 3066.0511 | GY8: 2356.58 | GZ8: 2990.9841 | HA8: 3092.4012 | HB8: 2834.536 | HC8: 2649.0504 | HD8: 2828.3325 | HE8: 2559.8675 | HF8: 2551.4295 | HG8: 2487.0287 | HH8: 2762.3306 | HI8: 3247.9014
A10: Ingresos Petroleros | B10: 79.03934 | C10: 107.61062 | D10: 109.66714 | E10: 84.909837 | F10: 95.476957 | G10: 97.821557 | H10: 144.89246 | I10: 182.42186 | J10: 144.83298 | K10: 148.58708 | L10: 145.02692 | M10: 119.7806 | N10: 100.02423 | O10: 135.61923 | P10: 149.55723 | Q10: 112.28 | R10: 133.734 | S10: 138.809 | T10: 73.85 | U10: 148.643 | V10: 98.728 | W10: 105.072 | X10: 103.996 | Y10: 51.485 | Z10: 107.782 | AA10: 96.136 | AB10: 84.473 | AC10: 87.933192 | AD10: 130.95773 | AE10: 103.42 | AF10: 107.85223 | AG10: 125.19023 | AH10: 148.37023 | AI10: 146.19523 | AJ10: 111.66923 | AK10: 142.78223 | AL10: 141 | AM10: 129.2 | AN10: 163.6 | AO10: 63.9 | AP10: 105.57 | AQ10: 143.7 | AR10: 156.2 | AS10: 155.5 | AT10: 148.5 | AU10: 146.05793 | AV10: 114.12754 | AW10: 196.29727 | AX10: 164.16096 | AY10: 116.66979 | AZ10: 149.0285 | BA10: 127.707 | BB10: 195.8112 | BC10: 177.462 | BD10: 205.064 | BE10: 193.0627 | BF10: 212.72751 | BG10: 219.97 | BH10: 209.044 | BI10: 144.678 | BJ10: 137.614 | BK10: 153.235 | BL10: 141.096 | BM10: 210.174 | BN10: 182.71054 | BO10: 206.809 | BP10: 258.008 | BQ10: 225.736 | BR10: 156.458 | BS10: 257.45511 | BT10: 195.51212 | BU10: 86.789819 | BV10: 291.76078 | BW10: 206.912 | BX10: 232.84809 | BY10: 223.011 | BZ10: 365.32689 | CA10: 239.01207 | CB10: 277.40278 | CC10: 197.26423 | CD10: 72.342065 | CE10: 638.04295 | CF10: 332.80702 | CG10: 158.27674 | CH10: 226.5842 | CI10: 175.22393 | CJ10: 171.15802 | CK10: 255.56315 | CL10: 197.24108 | CM10: 238.83587 | CN10: 392.98832 | CO10: 225.6662 | CP10: 350.05521 | CQ10: 320.03272 | CR10: 352.47204 | CS10: 412.23911 | CT10: 432.19861 | CU10: 964.12493 | CV10: 676.67948 | CW10: 732.61388 | CX10: 1086.4721 | CY10: 928.85431 | CZ10: 910.81243 | DA10: 1078.9132 | DB10: 535.33104 | DC10: 681.34909 | DD10: 363.24154 | DE10: 284.68126 | DF10: 203.75662 | DG10: 136.94016 | DH10: 311.65983 | DI10: 367.55834 | DJ10: 389.01589 | DK10: 459.15527 | DL10: 520.54144 | DM10: 402.09624 | DN10: 655.21807 | DO10: 646.43227 | DP10: 591.07133 | DQ10: 528.05569 | DR10: 751.38674 | DS10: 515.60063 | DT10: 657.125 | DU10: 732.33735 | DV10: 730.31073 | DW10: 549.31657 | DX10: 730.48507 | DY10: 519.86296 | DZ10: 633.87623 | EA10: 703.06009 | EB10: 585.18833 | EC10: 736.47075 | ED10: 937.06377 | EE10: 899.20782 | EF10: 1080.9271 | EG10: 1099.1979 | EH10: 875.52452 | EI10: 1518.0536 | EJ10: 1045.9545 | EK10: 1138.3581 | EL10: 1117.1748 | EM10: 1042.3752 | EN10: 722.48646 | EO10: 1458.2778 | EP10: 924.78571 | EQ10: 954.17021 | ER10: 1214.7508 | ES10: 1358.2018 | ET10: 1257.2285 | EU10: 1110.0759 | EV10: 951.23641 | EW10: 897.05713 | EX10: 1042.2609 | EY10: 1031.5763 | EZ10: 865.224 | FA10: 613.13823 | FB10: 997.90466 | FC10: 790.97942 | FD10: 1152.2131 | FE10: 1089.2757 | FF10: 886.85181 | FG10: 727.77473 | FH10: 1138.0438 | FI10: 861.94832 | FJ10: 1087.3794 | FK10: 979.18124 | FL10: 921.8234 | FM10: 800.01258 | FN10: 841.96947 | FO10: 787.87034 | FP10: 1071.2252 | FQ10: 1119.4962 | FR10: 1010.4025 | FS10: 1072.9813 | FT10: 961.56037 | FU10: 558.55345 | FV10: 1073.037 | FW10: 920.65368 | FX10: 784.5237 | FY10: 703.55011 | FZ10: 573.37914 | GA10: 426.10287 | GB10: 519.05896 | GC10: 578.54753 | GD10: 587.72219 | GE10: 673.96114 | GF10: 726.34891 | GG10: 550.63994 | GH10: 512.79442 | GI10: 456.36867 | GJ10: 455.63435 | GK10: 426.82251 | GL10: 383.57016 | GM10: 590.51455 | GN10: 381.18811 | GO10: 375.5633 | GP10: 391.28896 | GQ10: 406.47304 | GR10: 369.63672 | GS10: 451.28008 | GT10: 453.16975 | GU10: 416.60365 | GV10: 461.82764 | GW10: 720.83582 | GX10: 364.74174 | GY10: 385.24342 | GZ10: 553.14742 | HA10: 435.8174 | HB10: 536.19947 | HC10: 462.81215 | HD10: 509.90378 | HE10: 498.16144 | HF10: 473.31349 | HG10: 444.17846 | HH10: 560.22847 | HI10: 616.26128
A11: Exportación (1) | B11: 79.03934 | C11: 107.61062 | D11: 109.66714 | E11: 84.909837 | F11: 95.476957 | G11: 75.276557 | H11: 104.29966 | I11: 155.68776 | J11: 121.01298 | K11: 124.87908 | L11: 118.77692 | M11: 110.2806 | N11: 69.165227 | O11: 97.708227 | P11: 95.699227 | Q11: 72.79 | R11: 84.596 | S11: 83.765 | T11: 42.833 | U11: 105.582 | V11: 76.178 | W11: 96.622 | X11: 89.333 | Y11: 41.098 | Z11: 62.813 | AA11: 56.663 | AB11: 39.977 | AC11: 66.194192 | AD11: 84.218731 | AE11: 74.22 | AF11: 78.852227 | AG11: 90.033227 | AH11: 118.36353 | AI11: 116.18823 | AJ11: 85.119227 | AK11: 101.24123 | AL11: 102.11111 | AM11: 89.8 | AN11: 100.6 | AO11: 63.9 | AP11: 54.57 | AQ11: 92.7 | AR11: 105.53333 | AS11: 97.2 | AT11: 95.5 | AU11: 95.257931 | AV11: 69.127538 | AW11: 129.29727 | AX11: 124.52596 | AY11: 75.010793 | AZ11: 104.3065 | BA11: 69.51 | BB11: 149.3762 | BC11: 134.8315 | BD11: 144.3165 | BE11: 152.7937 | BF11: 184.62005 | BG11: 181.111 | BH11: 181.22748 | BI11: 136.156 | BJ11: 100.814 | BK11: 151.617 | BL11: 126.296 | BM11: 186.374 | BN11: 172.01054 | BO11: 182.699 | BP11: 232.108 | BQ11: 211.775 | BR11: 156.458 | BS11: 257.45511 | BT11: 195.51212 | BU11: 160.06682 | BV11: 291.76078 | BW11: 206.912 | BX11: 232.84809 | BY11: 223.011 | BZ11: 365.32689 | CA11: 239.01207 | CB11: 277.40278 | CC11: 197.26423 | CD11: 72.342065 | CE11: 638.04295 | CF11: 332.80702 | CG11: 158.27674 | CH11: 226.5842 | CI11: 175.22393 | CJ11: 171.15802 | CK11: 255.56315 | CL11: 197.24108 | CM11: 238.83587 | CN11: 392.98832 | CO11: 225.6662 | CP11: 350.05521 | CQ11: 320.03272 | CR11: 352.47204 | CS11: 412.23911 | CT11: 432.19861 | CU11: 964.12493 | CV11: 676.67948 | CW11: 732.61388 | CX11: 1086.4721 | CY11: 928.85431 | CZ11: 910.81243 | DA11: 1078.9132 | DB11: 535.33104 | DC11: 681.34909 | DD11: 363.24154 | DE11: 284.68126 | DF11: 203.75662 | DG11: 136.94016 | DH11: 311.65983 | DI11: 367.55834 | DJ11: 389.01589 | DK11: 459.15527 | DL11: 520.54144 | DM11: 402.09624 | DN11: 655.21807 | DO11: 646.43227 | DP11: 591.07133 | DQ11: 528.05569 | DR11: 751.38674 | DS11: 515.60063 | DT11: 657.125 | DU11: 732.33735 | DV11: 730.31073 | DW11: 549.31657 | DX11: 730.48507 | DY11: 519.86296 | DZ11: 633.87623 | EA11: 703.06009 | EB11: 585.18833 | EC11: 736.47075 | ED11: 937.06377 | EE11: 899.20782 | EF11: 1080.9271 | EG11: 1099.1979 | EH11: 875.52452 | EI11: 1518.0536 | EJ11: 1045.9545 | EK11: 1138.3581 | EL11: 1117.1748 | EM11: 1042.3752 | EN11: 722.48646 | EO11: 1458.2778 | EP11: 924.78571 | EQ11: 954.17021 | ER11: 1214.7508 | ES11: 1358.2018 | ET11: 1257.2285 | EU11: 1110.0759 | EV11: 951.23641 | EW11: 897.05713 | EX11: 1042.2609 | EY11: 1031.5763 | EZ11: 865.224 | FA11: 613.13823 | FB11: 997.90466 | FC11: 790.97942 | FD11: 1152.2131 | FE11: 1089.2757 | FF11: 886.85181 | FG11: 727.77473 | FH11: 1138.0438 | FI11: 861.94832 | FJ11: 1087.3794 | FK11: 979.18124 | FL11: 921.8234 | FM11: 800.01258 | FN11: 841.96947 | FO11: 787.87034 | FP11: 1071.2252 | FQ11: 1119.4962 | FR11: 1010.4025 | FS11: 1072.9813 | FT11: 961.56037 | FU11: 558.55345 | FV11: 1073.037 | FW11: 920.65368 | FX11: 784.5237 | FY11: 703.55011 | FZ11: 573.37914 | GA11: 426.10287 | GB11: 519.05896 | GC11: 578.54753 | GD11: 587.72219 | GE11: 673.96114 | GF11: 726.34891 | GG11: 550.63994 | GH11: 512.79442 | GI11: 456.36867 | GJ11: 455.63435 | GK11: 426.82251 | GL11: 383.57016 | GM11: 590.51455 | GN11: 381.18811 | GO11: 375.5633 | GP11: 391.28896 | GQ11: 406.47304 | GR11: 369.63672 | GS11: 451.28008 | GT11: 453.16975 | GU11: 416.60365 | GV11: 461.82764 | GW11: 720.83582 | GX11: 364.74174 | GY11: 385.24342 | GZ11: 553.14742 | HA11: 435.8174 | HB11: 536.19947 | HC11: 462.81215 | HD11: 509.90378 | HE11: 498.16144 | HF11: 473.31349 | HG11: 444.17846 | HH11: 560.22847 | HI11: 616.26128
A12: Venta Derivados | B12: 0 | C12: 0 | D12: 0 | E12: 0 | F12: 0 | G12: 22.545 | H12: 40.5928 | I12: 26.7341 | J12: 23.82 | K12: 23.708 | L12: 26.25 | M12: 9.5 | N12: 30.859 | O12: 37.911 | P12: 53.858 | Q12: 39.49 | R12: 49.138 | S12: 55.044 | T12: 31.017 | U12: 43.061 | V12: 22.55 | W12: 8.45 | X12: 14.663 | Y12: 10.387 | Z12: 44.969 | AA12: 39.473 | AB12: 44.496 | AC12: 21.739 | AD12: 46.739 | AE12: 29.2 | AF12: 29 | AG12: 35.157 | AH12: 30.0067 | AI12: 30.007 | AJ12: 26.55 | AK12: 41.541 | AL12: 38.888889 | AM12: 39.4 | AN12: 63 | AO12: 0 | AP12: 51 | AQ12: 51 | AR12: 50.666667 | AS12: 58.3 | AT12: 53 | AU12: 50.8 | AV12: 45 | AW12: 67 | AX12: 39.635 | AY12: 41.659 | AZ12: 44.722 | BA12: 58.197 | BB12: 46.435 | BC12: 42.6305 | BD12: 60.7475 | BE12: 40.269 | BF12: 28.107466 | BG12: 38.859 | BH12: 27.81652 | BI12: 8.522 | BJ12: 36.8 | BK12: 1.618 | BL12: 14.8 | BM12: 23.8 | BN12: 10.7 | BO12: 24.11 | BP12: 25.9 | BQ12: 13.961 | BR12: 0 | BS12: 0 | BT12: 0 | BU12: -73.277 | BV12: 0 | BW12: 0 | BX12: 0 | BY12: 0 | BZ12: 0 | CA12: 0 | CB12: 0 | CC12: 0 | CD12: 0 | CE12: 0 | CF12: 0 | CG12: 0 | CH12: 0 | CI12: 0 | CJ12: 0 | CK12: 0 | CL12: 0 | CM12: 0 | CN12: 0 | CO12: 0 | CP12: 0 | CQ12: 0 | CR12: 0 | CS12: 0 | DR12: 0 | DS12: 0 | DT12: 0 | DU12: 0 | DV12: 0 | DW12: 0 | DX12: 0 | DY12: 0 | DZ12: 0 | EA12: 0 | EB12: 0 | EC12: 0 | ED12: 0 | EE12: 0 | EF12: 0 | EG12: 0 | EH12: 0 | EI12: 0 | EJ12: 0 | EK12: 0 | EL12: 0 | EP12: 0 | EQ12: 0 | ER12: 0 | ES12: 0 | ET12: 0 | EU12: 0 | EV12: 0 | EW12: 0 | EX12: 0 | EY12: 0 | EZ12: 0 | FA12: 0 | FB12: 0 | FC12: 0 | FH12: 0 | FN12: 0 | FO12: 0 | FP12: 0 | FQ12: 0 | FR12: 0 | FS12: 0 | FT12: 0 | FU12: 0 | FV12: 0 | FW12: 0 | FX12: 0 | FY12: 0 | FZ12: 0 | GA12: 0 | GB12: 0 | GC12: 0 | GD12: 0 | GE12: 0 | GF12: 0 | GG12: 0 | GH12: 0 | GI12: 0 | GJ12: 0 | GK12: 0 | GL12: 0 | GM12: 0 | GN12: 0 | GO12: 0 | GP12: 0 | GQ12: 0 | GR12: 0 | GS12: 0 | GT12: 0 | GU12: 0 | GV12: 0 | GW12: 0 | GX12: 0 | GY12: 0 | GZ12: 0 | HA12: 0 | HB12: 0 | HC12: 0 | HD12: 0 | HE12: 0 | HF12: 0 | HG12: 0 | HH12: 0 | HI12: 0
A14: Ingresos no petroleros | B14: 159.45958 | C14: 155.34242 | D14: 160.29204 | E14: 206.89047 | F14: 181.69417 | G14: 231.23975 | H14: 224.69635 | I14: 222.80452 | J14: 239.57204 | K14: 253.15274 | L14: 243.168 | M14: 246.90799 | N14: 277.58674 | O14: 235.68157 | P14: 223.97414 | Q14: 404.81549 | R14: 274.75534 | S14: 272.79043 | T14: 310.07817 | U14: 303.57106 | V14: 314.73591 | W14: 286.37614 | X14: 281.40848 | Y14: 311.10428 | Z14: 373.44646 | AA14: 371.49855 | AB14: 349.1685 | AC14: 541.88227 | AD14: 366.77679 | AE14: 408.87317 | AF14: 398.05195 | AG14: 346.11475 | AH14: 461.04229 | AI14: 449.91365 | AJ14: 355.07112 | AK14: 359.07298 | AL14: 435.59453 | AM14: 340.40278 | AN14: 394.69087 | AO14: 525.48104 | AP14: 403.4157 | AQ14: 416.23758 | AR14: 453.3027 | AS14: 397.96373 | AT14: 464.07903 | AU14: 472.59067 | AV14: 391.85047 | AW14: 460.26351 | AX14: 446.69275 | AY14: 374.50867 | AZ14: 494.52823 | BA14: 585.68049 | BB14: 458.83033 | BC14: 442.32859 | BD14: 483.67672 | BE14: 489.05582 | BF14: 526.45243 | BG14: 513.99017 | BH14: 485.97209 | BI14: 523.03638 | BJ14: 553.84757 | BK14: 418.3764 | BL14: 521.78153 | BM14: 794.88861 | BN14: 522.75111 | BO14: 489.89511 | BP14: 603.13882 | BQ14: 532.25206 | BR14: 627.62486 | BS14: 596.64084 | BT14: 512.95154 | BU14: 696.37014 | BV14: 658.03129 | BW14: 425.54179 | BX14: 681.41926 | BY14: 994.34731 | BZ14: 712.2577 | CA14: 680.00231 | CB14: 655.70928 | CC14: 594.32739 | CD14: 764.03796 | CE14: 681.3346 | CF14: 672.04322 | CG14: 814.16017 | CH14: 710.14874 | CI14: 552.67778 | CJ14: 656.96391 | CK14: 1107.7111 | CL14: 674.24119 | CM14: 698.84978 | CN14: 760.2422 | CO14: 791.91168 | CP14: 927.11899 | CQ14: 829.5587 | CR14: 850.95389 | CS14: 902.44239 | CT14: 953.79694 | CU14: 737.65128 | CV14: 954.42442 | CW14: 1284.1184 | CX14: 873.87804 | CY14: 803.25596 | CZ14: 1106.0607 | DA14: 1202.5041 | DB14: 1171.6117 | DC14: 1233.9422 | DD14: 1082.9714 | DE14: 1136.2368 | DF14: 953.594 | DG14: 724.5349 | DH14: 889.22326 | DI14: 1486.5988 | DJ14: 940.56002 | DK14: 874.0806 | DL14: 1013.0692 | DM14: 831.52977 | DN14: 1268.3617 | DO14: 963.37819 | DP14: 1385.3033 | DQ14: 1042.43 | DR14: 1117.9945 | DS14: 956.19833 | DT14: 1469.1035 | DU14: 1385.0679 | DV14: 1147.0038 | DW14: 1077.8721 | DX14: 1143.7745 | DY14: 1018.9334 | DZ14: 1158.2801 | EA14: 1127.1628 | EB14: 1086.7801 | EC14: 1298.8805 | ED14: 1202.6397 | EE14: 1107.4301 | EF14: 1318.2572 | EG14: 1689.8113 | EH14: 1342.4557 | EI14: 1302.7305 | EJ14: 1330.1016 | EK14: 1242.0099 | EL14: 1556.0551 | EM14: 1323.1451 | EN14: 1409.4847 | EO14: 1664.7864 | EP14: 1653.6016 | EQ14: 1380.7927 | ER14: 1559.3617 | ES14: 2155.959 | ET14: 1536.6806 | EU14: 1490.1554 | EV14: 1724.4525 | EW14: 1607.5461 | EX14: 1654.9079 | EY14: 1570.4812 | EZ14: 1591.1968 | FA14: 1857.3971 | FB14: 1912.5713 | FC14: 1467.5695 | FD14: 1798.3141 | FE14: 2484.8901 | FF14: 1861.0182 | FG14: 1712.0524 | FH14: 2009.282 | FI14: 1800.772 | FJ14: 1835.3878 | FK14: 1880.5823 | FL14: 1866.9747 | FM14: 2000.9535 | FN14: 2045.1314 | FO14: 1599.0541 | FP14: 1875.0605 | FQ14: 2583.1266 | FR14: 1906.38 | FS14: 1896.3297 | FT14: 2102.7762 | FU14: 1862.3013 | FV14: 1818.0654 | FW14: 2012.4297 | FX14: 2057.8266 | FY14: 2180.7066 | FZ14: 2223.6599 | GA14: 2105.7763 | GB14: 2016.4008 | GC14: 2685.8306 | GD14: 2192.3461 | GE14: 2272.216 | GF14: 2786.8823 | GG14: 1859.8144 | GH14: 1952.9651 | GI14: 1949.531 | GJ14: 1930.9795 | GK14: 1781.7724 | GL14: 2114.017 | GM14: 1664.9029 | GN14: 1934.7484 | GO14: 2275.34 | GP14: 1631.5973 | GQ14: 2027.4871 | GR14: 2029.7648 | GS14: 2095.7433 | GT14: 1944.1663 | GU14: 2046.8945 | GV14: 1806.4125 | GW14: 2723.2065 | GX14: 2393.142 | GY14: 1892.339 | GZ14: 2174.2189 | HA14: 2609.574 | HB14: 2183.1448 | HC14: 2019.676 | HD14: 2138.4854 | HE14: 1945.5831 | HF14: 1966.073 | HG14: 2011.6868 | HH14: 2073.5403 | HI14: 2066.2331
A15: Ingresos tributarios | B15: 90.974793 | C15: 88.993016 | D15: 97.413619 | E15: 132.33153 | F15: 101.98498 | G15: 126.60797 | H15: 131.9135 | I15: 138.6597 | J15: 147.57787 | K15: 145.8456 | L15: 153.4546 | M15: 166.6216 | N15: 187.40184 | O15: 156.81926 | P15: 166.30811 | Q15: 326.42274 | R15: 191.31734 | S15: 196.80843 | T15: 234.09827 | U15: 210.47787 | V15: 220.09901 | W15: 201.45414 | X15: 204.40959 | Y15: 212.13328 | Z15: 248.86259 | AA15: 203.27867 | AB15: 223.51667 | AC15: 351.80531 | AD15: 219.09005 | AE15: 227.32935 | AF15: 248.91106 | AG15: 224.48867 | AH15: 251.22467 | AI15: 233.85567 | AJ15: 213.45317 | AK15: 260.48667 | AL15: 297.84598 | AM15: 213.69365 | AN15: 230.9346 | AO15: 357.74097 | AP15: 249.0654 | AQ15: 250.81144 | AR15: 290.17404 | AS15: 240.28537 | AT15: 263.38362 | AU15: 263.33746 | AV15: 243.38746 | AW15: 262.8565 | AX15: 303.37783 | AY15: 222.5127 | AZ15: 280.3631 | BA15: 437.41984 | BB15: 269.05142 | BC15: 267.68453 | BD15: 325.22996 | BE15: 280.90174 | BF15: 304.96979 | BG15: 291.86917 | BH15: 305.70674 | BI15: 305.78199 | BJ15: 362.9932 | BK15: 264.69251 | BL15: 299.23368 | BM15: 627.15534 | BN15: 321.90807 | BO15: 303.87693 | BP15: 399.51728 | BQ15: 321.61849 | BR15: 391.89732 | BS15: 336.44428 | BT15: 315.90876 | BU15: 338.03519 | BV15: 412.20943 | BW15: 251.86427 | BX15: 375.88433 | BY15: 757.62769 | BZ15: 408.51326 | CA15: 358.80179 | CB15: 448.18765 | CC15: 374.30821 | CD15: 446.20029 | CE15: 358.81112 | CF15: 384.60876 | CG15: 375.75388 | CH15: 465.83711 | CI15: 323.48742 | CJ15: 367.4177 | CK15: 751.20343 | CL15: 410.89906 | CM15: 364.03247 | CN15: 499.95395 | CO15: 440.43783 | CP15: 541.13617 | CQ15: 434.61761 | CR15: 468.60104 | CS15: 497.65195 | CT15: 622.20126 | CU15: 381.20475 | CV15: 488.69491 | CW15: 856.1707 | CX15: 516.69095 | CY15: 456.33025 | CZ15: 665.77181 | DA15: 528.37338 | DB15: 697.50541 | DC15: 604.5433 | DD15: 557.85255 | DE15: 543.87028 | DF15: 631.40107 | DG15: 424.89829 | DH15: 573.10359 | DI15: 1074.7948 | DJ15: 541.51808 | DK15: 520.05482 | DL15: 711.44172 | DM15: 524.44572 | DN15: 709.04556 | DO15: 568.11955 | DP15: 634.35872 | DQ15: 640.25243 | DR15: 752.49703 | DS15: 587.33143 | DT15: 768.28175 | DU15: 1024.3518 | DV15: 670.08838 | DW15: 659.92565 | DX15: 749.08191 | DY15: 633.08187 | DZ15: 758.36667 | EA15: 652.69597 | EB15: 687.04775 | EC15: 724.71225 | ED15: 827.24573 | EE15: 594.43597 | EF15: 791.86486 | EG15: 1147.916 | EH15: 781.60364 | EI15: 747.85953 | EJ15: 779.11546 | EK15: 715.61217 | EL15: 880.43734 | EM15: 788.87731 | EN15: 808.22841 | EO15: 901.7821 | EP15: 1086.1642 | EQ15: 827.9123 | ER15: 933.6382 | ES15: 1513.4132 | ET15: 950.25237 | EU15: 913.186 | EV15: 1034.5408 | EW15: 984.10711 | EX15: 1027.0197 | EY15: 900.99974 | EZ15: 966.0787 | FA15: 1117.3735 | FB15: 1267.5035 | FC15: 939.96333 | FD15: 1022.7851 | FE15: 1717.5959 | FF15: 1066.2658 | FG15: 1008.9231 | FH15: 1219.4983 | FI15: 1061.6476 | FJ15: 1144.0545 | FK15: 1074.7737 | FL15: 1059.1786 | FM15: 1085.3646 | FN15: 1305.3562 | FO15: 986.82683 | FP15: 1066.2825 | FQ15: 1799.2402 | FR15: 1103.0256 | FS15: 1043.5834 | FT15: 1272.1823 | FU15: 1114.6738 | FV15: 1229.368 | FW15: 1160.6691 | FX15: 1172.6801 | FY15: 1206.0913 | FZ15: 1526.8414 | GA15: 1075.3081 | GB15: 1227.1185 | GC15: 1920.9754 | GD15: 1200.3652 | GE15: 1187.3128 | GF15: 1938.2205 | GG15: 1092.9084 | GH15: 1227.414 | GI15: 1075.1919 | GJ15: 1073.6984 | GK15: 1042.9281 | GL15: 1291.4777 | GM15: 869.59989 | GN15: 1030.3915 | GO15: 1483.1992 | GP15: 931.39795 | GQ15: 1154.1407 | GR15: 1332.768 | GS15: 1278.7885 | GT15: 1184.6008 | GU15: 1169.7673 | GV15: 1100.2997 | GW15: 1190.9909 | GX15: 1405.8596 | GY15: 982.30564 | GZ15: 1129.2681 | HA15: 1733.2873 | HB15: 1086.7746 | HC15: 1107.9284 | HD15: 1145.8566 | HE15: 1048.8194 | HF15: 1150.9686 | HG15: 1063.804 | HH15: 1112.576 | HI15: 1110.8399
A16: Impuesto a la renta | B16: 14.718192 | C16: 15.147921 | D16: 20.428913 | E16: 51.6756 | F16: 21.1506 | G16: 22.9136 | H16: 29.887 | I16: 24.4976 | J16: 30.5666 | K16: 26.8746 | L16: 26.8096 | M16: 29.7756 | N16: 36.239055 | O16: 20.843335 | P16: 33.182321 | Q16: 175.5421 | R16: 36.244828 | S16: 27.638618 | T16: 59.028351 | U16: 22.111566 | V16: 50.501549 | W16: 24.868292 | X16: 25.037734 | Y16: 28.55438 | Z16: 36.911 | AA16: 27.62 | AB16: 41.507 | AC16: 147.781 | AD16: 34.541 | AE16: 31.534 | AF16: 63.16 | AG16: 30.064 | AH16: 59.143 | AI16: 35.691 | AJ16: 31.9 | AK16: 56.1 | AL16: 56.955207 | AM16: 35.228908 | AN16: 51.370656 | AO16: 171.16763 | AP16: 45.247304 | AQ16: 43.015018 | AR16: 82.166331 | AS16: 43.017701 | AT16: 74.966485 | AU16: 45.764317 | AV16: 42.224219 | AW16: 44.720197 | AX16: 72.610462 | AY16: 38.421948 | AZ16: 62.750851 | BA16: 223.01681 | BB16: 50.654987 | BC16: 44.696483 | BD16: 98.026181 | BE16: 49.869471 | BF16: 90.792025 | BG16: 49.554508 | BH16: 51.782222 | BI16: 48.071305 | BJ16: 79.92819 | BK16: 44.738459 | BL16: 61.654735 | BM16: 384.37268 | BN16: 58.465847 | BO16: 49.824975 | BP16: 141.45779 | BQ16: 54.353883 | BR16: 130.58667 | BS16: 52.674083 | BT16: 54.865928 | BU16: 72.711581 | BV16: 105.81071 | BW16: 43.039057 | BX16: 79.488128 | BY16: 481.8667 | BZ16: 110.49869 | CA16: 60.359357 | CB16: 153.30089 | CC16: 62.140853 | CD16: 141.10162 | CE16: 64.954085 | CF16: 64.254488 | CG16: 86.10664 | CH16: 107.28244 | CI16: 60.013202 | CJ16: 85.440691 | CK16: 453.58813 | CL16: 103.53926 | CM16: 64.671861 | CN16: 181.39598 | CO16: 97.537799 | CP16: 203.39091 | CQ16: 101.7735 | CR16: 105.44141 | CS16: 124.63777 | CT16: 166.51224 | CU16: 106.95375 | CV16: 150.56013 | CW16: 518.8991 | CX16: 154.60858 | CY16: 104.79683 | CZ16: 273.37745 | DA16: 121.89 | DB16: 279.13163 | DC16: 238.8308 | DD16: 135.58634 | DE16: 118.05 | DF16: 173.1913 | DG16: 89.0459 | DH16: 162.3773 | DI16: 701.6436 | DJ16: 163.153 | DK16: 113.5584 | DL16: 292.2319 | DM16: 127.8486 | DN16: 275.2802 | DO16: 132.827 | DP16: 164.2285 | DQ16: 122.1185 | DR16: 204.244 | DS16: 96.4975 | DT16: 174.5724 | DU16: 516.0768 | DV16: 142.0263 | DW16: 123.0419 | DX16: 260.8861 | DY16: 136.6146 | DZ16: 252.3406 | EA16: 157.007 | EB16: 142.8551 | EC16: 146.949 | ED16: 244.02808 | EE16: 134.67411 | EF16: 304.9043 | EG16: 653.1478 | EH16: 198.0846 | EI16: 206.2679 | EJ16: 246.8509 | EK16: 179.5121 | EL16: 297.5975 | EM16: 182.4183 | EN16: 174.7116 | EO16: 208.0057 | EP16: 304.0222 | EQ16: 147.9673 | ER16: 241.5082 | ES16: 825.6595 | ET16: 213.455 | EU16: 174.517 | EV16: 284.985 | EW16: 193.2772 | EX16: 302.277 | EY16: 195.3438 | EZ16: 198.8134 | FA16: 231.107 | FB16: 341.7083 | FC16: 181.4729 | FD16: 265.6984 | FE16: 924.4258 | FF16: 231.9975 | FG16: 204.6052 | FH16: 392.7602 | FI16: 223.58031 | FJ16: 345.3929 | FK16: 230.5631 | FL16: 228.4221 | FM16: 276.8135 | FN16: 351.59541 | FO16: 203.54504 | FP16: 297.96725 | FQ16: 979.57789 | FR16: 267.42685 | FS16: 223.4706 | FT16: 403.7043 | FU16: 253.258 | FV16: 384.4827 | FW16: 259.3313 | FX16: 241.9158 | FY16: 294.422 | FZ16: 418.18635 | GA16: 188.25251 | GB16: 313.44998 | GC16: 983.23107 | GD16: 316.37059 | GE16: 317.41656 | GF16: 906.83771 | GG16: 225.47354 | GH16: 359.122 | GI16: 236.251 | GJ16: 228.807 | GK16: 240.7595 | GL16: 318.54963 | GM16: 180.87046 | GN16: 328.626 | GO16: 778.82269 | GP16: 238.13593 | GQ16: 212.18038 | GR16: 320.74084 | GS16: 219.1891 | GT16: 329.123 | GU16: 246.28507 | GV16: 220.69154 | GW16: 246.45167 | GX16: 308.43684 | GY16: 202.355 | GZ16: 287.64861 | HA16: 883.034 | HB16: 235.299 | HC16: 232.776 | HD16: 321.516 | HE16: 222.88067 | HF16: 342.41651 | HG16: 241.632 | HH16: 234.778 | HI16: 251.257
A17: IVA | B17: 58.6795 | C17: 54.1018 | D17: 54.9787 | E17: 60.9971 | F17: 59.8532 | G17: 77.8555 | H17: 74.6074 | I17: 84.8458 | J17: 85.685 | K17: 85.556 | L17: 94.1 | M17: 102.173 | N17: 103.96378 | O17: 99.213928 | P17: 102.37579 | Q17: 105.36964 | R17: 116.59852 | S17: 131.71381 | T17: 134.01592 | U17: 145.35531 | V17: 127.23847 | W17: 127.23885 | X17: 132.20785 | Y17: 131.4789 | Z17: 158.029 | AA17: 128.396 | AB17: 131.5 | AC17: 148.177 | AD17: 134.74 | AE17: 143.67 | AF17: 134.8 | AG17: 140.466 | AH17: 133.268 | AI17: 142.378 | AJ17: 128.921 | AK17: 145.5 | AL17: 177.0392 | AM17: 129.08007 | AN17: 130.20217 | AO17: 132.31187 | AP17: 142.66393 | AQ17: 150.05685 | AR17: 146.56771 | AS17: 141.92607 | AT17: 130.36876 | AU17: 160.68817 | AV17: 143.70376 | AW17: 152.46773 | AX17: 172.89347 | AY17: 127.09125 | AZ17: 157.70375 | BA17: 156.815 | BB17: 152.47 | BC17: 154.445 | BD17: 156.32125 | BE17: 155.68648 | BF17: 146.23769 | BG17: 168.53662 | BH17: 166.99415 | BI17: 171.6275 | BJ17: 207.25749 | BK17: 156.46938 | BL17: 162.5425 | BM17: 167.38125 | BN17: 183.2643 | BO17: 174.32802 | BP17: 184.59644 | BQ17: 178.47976 | BR17: 188.3278 | BS17: 201.32528 | BT17: 180.5782 | BU17: 182.33003 | BV17: 218.73856 | BW17: 146.15889 | BX17: 210.19876 | BY17: 197.21214 | BZ17: 203.05311 | CA17: 212.24387 | CB17: 201.55596 | CC17: 219.23547 | CD17: 207.04982 | CE17: 203.70308 | CF17: 225.31531 | CG17: 200.3915 | CH17: 262.98547 | CI17: 190.71222 | CJ17: 195.89452 | CK17: 204.91899 | CL17: 215.99864 | CM17: 215.57678 | CN17: 224.02149 | CO17: 246.74751 | CP17: 248.03837 | CQ17: 234.15373 | CR17: 257.07716 | CS17: 256.5525 | CT17: 315.58229 | CU17: 182.45741 | CV17: 230.38474 | CW17: 227.51012 | CX17: 244.7894 | CY17: 242.95561 | CZ17: 269.60824 | DA17: 285.94919 | DB17: 301.99152 | DC17: 235.4594 | DD17: 300.93569 | DE17: 278.82201 | DF17: 337.00733 | DG17: 215.48267 | DH17: 286.373 | DI17: 244.58489 | DJ17: 251.29993 | DK17: 260.69816 | DL17: 271.57078 | DM17: 254.9037 | DN17: 277.5836 | DO17: 277.0847 | DP17: 300.3193 | DQ17: 311.272 | DR17: 395.5011 | DS17: 257.8607 | DT17: 355.1231 | DU17: 294.822 | DV17: 320.5756 | DW17: 327.6548 | DX17: 274.8368 | DY17: 277.1485 | DZ17: 295.4775 | EA17: 307.7281 | EB17: 302.8886 | EC17: 349.8409 | ED17: 357.8386 | EE17: 277.6311 | EF17: 292.2001 | EG17: 308.2284 | EH17: 367.4647 | EI17: 328.8028 | EJ17: 330.22429 | EK17: 326.7838 | EL17: 367.9695 | EM17: 386.6337 | EN17: 423.297 | EO17: 433.2621 | EP17: 508.7767 | EQ17: 406.1428 | ER17: 408.4794 | ES17: 406.3255 | ET17: 449.2582 | EU17: 441.655 | EV17: 449.454 | EW17: 473.6965 | EX17: 439.8195 | EY17: 437.6589 | EZ17: 472.5724 | FA17: 521.1391 | FB17: 603.4331 | FC17: 448.9386 | FD17: 448.1342 | FE17: 488.6835 | FF17: 519.2453 | FG17: 485.3536 | FH17: 507.6102 | FI17: 518.85369 | FJ17: 494.0098 | FK17: 531.9547 | FL17: 513.5019 | FM17: 496.3621 | FN17: 625.05697 | FO17: 485.52135 | FP17: 467.92723 | FQ17: 512.62798 | FR17: 516.89648 | FS17: 509.8691 | FT17: 540.744 | FU17: 523.6028 | FV17: 529.195 | FW17: 556.9481 | FX17: 547.0271 | FY17: 560.2293 | FZ17: 708.6582 | GA17: 553.318 | GB17: 540.585 | GC17: 564.49 | GD17: 497.31 | GE17: 480.365 | GF17: 555.38 | GG17: 497.38 | GH17: 500.264 | GI17: 479.931 | GJ17: 504.312 | GK17: 470.344 | GL17: 581.35216 | GM17: 401.25305 | GN17: 413.80418 | GO17: 406.38758 | GP17: 409.48553 | GQ17: 453.40695 | GR17: 418.03235 | GS17: 465.56085 | GT17: 424.89512 | GU17: 482.3704 | GV17: 457.52642 | GW17: 485.60566 | GX17: 652.2715 | GY17: 415.51615 | GZ17: 458.90135 | HA17: 477.607 | HB17: 480.861 | HC17: 487.954 | HD17: 495.892 | HE17: 501.303 | HF17: 479.421 | HG17: 494.665 | HH17: 519.771 | HI17: 514.70878
A18: ICE | B18: 2.620929 | C18: 4.369787 | D18: 3.181176 | E18: 5.5129565 | F18: 4.3705 | G18: 7.0995 | H18: 5.3307 | I18: 6.7436 | J18: 8.244 | K18: 8.668 | L18: 9.209 | M18: 9.216 | N18: 13.008 | O18: 12.708 | P18: 9.012 | Q18: 15.793 | R18: 8.644 | S18: 5.543 | T18: 11.059 | U18: 9.917 | V18: 12.08 | W18: 13.643 | X18: 12.775 | Y18: 13.1 | Z18: 18.4883 | AA18: 16.173 | AB18: 18.7 | AC18: 18.157 | AD18: 19.381 | AE18: 15.5 | AF18: 16.652 | AG18: 17.976 | AH18: 20.027 | AI18: 18 | AJ18: 20.4 | AK18: 20.6 | AL18: 24.6175 | AM18: 19.859 | AN18: 18.6667 | AO18: 18.139 | AP18: 20.2041 | AQ18: 18.6716 | AR18: 19.0528 | AS18: 20.7933 | AT18: 20.6777 | AU18: 19.7928 | AV18: 21.0204 | AW18: 21.3099 | AX18: 24.468166 | AY18: 17.993772 | AZ18: 19.002768 | BA18: 20.852595 | BB18: 23.291003 | BC18: 22.162609 | BD18: 21.357093 | BE18: 26.330353 | BF18: 19.788608 | BG18: 24.513571 | BH18: 25.282931 | BI18: 25.056747 | BJ18: 27.8 | BK18: 23.138 | BL18: 23.273 | BM18: 26.6 | BN18: 24.627 | BO18: 25.3968 | BP18: 24.8993 | BQ18: 27.6451 | BR18: 25.5472 | BS18: 27.8765 | BT18: 26.3608 | BU18: 24.4649 | BV18: 34.2661 | BW18: 21.1087 | BX18: 26.6536 | BY18: 27.4422 | BZ18: 27.2482 | CA18: 26.5996 | CB18: 30.7356 | CC18: 27.567 | CD18: 39.092 | CE18: 25.754 | CF18: 29.8865 | CG18: 28.608 | CH18: 35.341167 | CI18: 25.9899 | CJ18: 26.7791 | CK18: 29.7452 | CL18: 28.206 | CM18: 26.7622 | CN18: 24.5181 | CO18: 28.456 | CP18: 29.0783 | CQ18: 29.1857 | CR18: 33.6198 | CS18: 31.7249 | CT18: 62.1642 | CU18: 29.5884 | CV18: 37.8578 | CW18: 26.6236 | CX18: 36.3566 | CY18: 32.1393 | CZ18: 30.2912 | DA18: 40.5461 | DB18: 37.561 | DC18: 55.753 | DD18: 41.2339 | DE18: 43.786 | DF18: 53.920843 | DG18: 32.4317 | DH18: 31.9599 | DI18: 33.2236 | DJ18: 29.3865 | DK18: 34.3619 | DL18: 32.2166 | DM18: 34.6037 | DN18: 37.9768 | DO18: 42.5967 | DP18: 41.7849 | DQ18: 43.6671 | DR18: 44.3796 | DS18: 33.8131 | DT18: 38.9379 | DU18: 41.9789 | DV18: 45.9225 | DW18: 46.7983 | DX18: 44.3174 | DY18: 42.0038 | DZ18: 42.5861 | EA18: 45.5654 | EB18: 51.4009 | EC18: 52.6043 | ED18: 54.6965 | EE18: 44.9581 | EF18: 40.2961 | EG18: 48.1277 | EH18: 53.0826 | EI18: 49.5309 | EJ18: 55.175 | EK18: 46.4775 | EL18: 51.0028 | EM18: 49.7179 | EN18: 50.9447 | EO18: 73.8608 | EP18: 55.8293 | EQ18: 46.2367 | ER18: 49.4748 | ES18: 57.1138 | ET18: 56.773 | EU18: 60.98 | EV18: 62.249 | EW18: 60.8995 | EX18: 57.0611 | EY18: 52.063 | EZ18: 58.9664 | FA18: 66.8562 | FB18: 65.2475 | FC18: 63.1636 | FD18: 57.7876 | FE18: 59.9475 | FF18: 62.3414 | FG18: 59.4014 | FH18: 60.5182 | FI18: 59.36239 | FJ18: 61.6529 | FK18: 62.5049 | FL18: 64.3623 | FM18: 67.3365 | FN18: 74.90401 | FO18: 56.99575 | FP18: 59.58716 | FQ18: 60.14347 | FR18: 65.19119 | FS18: 64.7303 | FT18: 67.7 | FU18: 69.1598 | FV18: 70.7807 | FW18: 75.5492 | FX18: 70.0068 | FY18: 68.4578 | FZ18: 89.1672 | GA18: 61.958 | GB18: 65.662 | GC18: 67.188 | GD18: 60.282 | GE18: 73.184 | GF18: 116.196 | GG18: 63.904 | GH18: 58.582 | GI18: 59.661 | GJ18: 64.213 | GK18: 59.646 | GL18: 82.35791 | GM18: 50.19243 | GN18: 47.36459 | GO18: 59.92199 | GP18: 56.26657 | GQ18: 59.74514 | GR18: 76.64875 | GS18: 66.3244 | GT18: 66.88082 | GU18: 84.81362 | GV18: 73.39046 | GW18: 65.710596 | GX18: 89.844547 | GY18: 64.388662 | GZ18: 64.06 | HA18: 73.844 | HB18: 73.563 | HC18: 79.36164 | HD18: 81.861 | HE18: 79.24231 | HF18: 80.52161 | HG18: 76.87328 | HH18: 91.89597 | HI18: 81.294
A19: Arancelarios | B19: 12.407172 | C19: 13.078665 | D19: 16.390559 | E19: 12.9538 | F19: 15.212456 | G19: 17.423292 | H19: 20.257 | I19: 20.811 | J19: 21.20227 | K19: 21.439 | L19: 21.712 | M19: 24.043 | N19: 32.4 | O19: 22.7 | P19: 20.1 | Q19: 28.1 | R19: 28.3 | S19: 30.3 | T19: 28.1 | U19: 31.1 | V19: 28.7 | W19: 34.1 | X19: 32.9 | Y19: 37.6 | Z19: 33.486667 | AA19: 29.486667 | AB19: 30.086667 | AC19: 37.386667 | AD19: 30.286667 | AE19: 36.486667 | AF19: 34.186667 | AG19: 35.886667 | AH19: 38.686667 | AI19: 37.686667 | AJ19: 32.086667 | AK19: 37.986667 | AL19: 36.777972 | AM19: 26.777972 | AN19: 25.777972 | AO19: 30.277972 | AP19: 35.677972 | AQ19: 33.277972 | AR19: 32.478 | AS19: 31.478 | AT19: 34.977972 | AU19: 34.777972 | AV19: 34.277972 | AW19: 39.277972 | AX19: 28.105727 | AY19: 32.105727 | AZ19: 33.105727 | BA19: 29.535433 | BB19: 34.835433 | BC19: 37.435433 | BD19: 37.135433 | BE19: 42.835433 | BF19: 42.835463 | BG19: 44.135463 | BH19: 54.235433 | BI19: 53.235433 | BJ19: 44.378334 | BK19: 35.313269 | BL19: 45.784802 | BM19: 43.738513 | BN19: 49.880802 | BO19: 47.228824 | BP19: 40.8302 | BQ19: 55.013687 | BR19: 44.206697 | BS19: 51.377672 | BT19: 51.473062 | BU19: 51.532513 | BV19: 49.283357 | BW19: 37.59503 | BX19: 54.71696 | BY19: 45.031262 | BZ19: 60.26303 | CA19: 51.328707 | CB19: 53.318593 | CC19: 58.895466 | CD19: 54.897815 | CE19: 60.355403 | CF19: 60.998766 | CG19: 51.229815 | CH19: 54.422627 | CI19: 42.564237 | CJ19: 54.896228 | CK19: 56.488177 | CL19: 56.3403 | CM19: 50.457676 | CN19: 60.207931 | CO19: 55.732098 | CP19: 56.790392 | CQ19: 65.789006 | CR19: 68.867113 | CS19: 77.672827 | CT19: 70.481632 | CU19: 49.109779 | CV19: 56.346062 | CW19: 71.174037 | CX19: 70.904374 | CY19: 63.665062 | CZ19: 74.794205 | DA19: 66.808719 | DB19: 69.764254 | DC19: 63.662465 | DD19: 71.467703 | DE19: 88.171966 | DF19: 55.326067 | DG19: 59.752028 | DH19: 61.780327 | DI19: 61.116421 | DJ19: 65.818939 | DK19: 75.125504 | DL19: 77.033631 | DM19: 78.111515 | DN19: 91.442858 | DO19: 91.293773 | DP19: 103.17902 | DQ19: 130.52112 | DR19: 74.094027 | DS19: 77.186435 | DT19: 111.88485 | DU19: 93.396012 | DV19: 104.29218 | DW19: 101.21175 | DX19: 94.412912 | DY19: 98.260272 | DZ19: 97.513069 | EA19: 90.284666 | EB19: 105.08695 | EC19: 105.08695 | ED19: 86.591099 | EE19: 75.921556 | EF19: 87.283157 | EG19: 79.193766 | EH19: 107.58474 | EI19: 99.445033 | EJ19: 88.87947 | EK19: 108.71127 | EL19: 101.88354 | EM19: 110.38151 | EN19: 105.32521 | EO19: 104.5 | EP19: 102.23889 | EQ19: 89.742 | ER19: 100.713 | ES19: 94.744455 | ET19: 110.03547 | EU19: 106.631 | EV19: 112.60578 | EW19: 126.14091 | EX19: 98.3 | EY19: 97.955443 | EZ19: 104.721 | FA19: 117.28345 | FB19: 111.55 | FC19: 97.588 | FD19: 103.80316 | FE19: 107.84253 | FF19: 115.118 | FG19: 119.4713 | FH19: 119.4713 | FI19: 118.98613 | FJ19: 103.9121 | FK19: 119.50003 | FL19: 120.45075 | FM19: 114.54236 | FN19: 99.15593 | FO19: 95.468553 | FP19: 92.102726 | FQ19: 104.91776 | FR19: 123.04627 | FS19: 111.54074 | FT19: 113.44438 | FU19: 123.59482 | FV19: 106.23355 | FW19: 125.839 | FX19: 128.863 | FY19: 132.91835 | FZ19: 141.201 | GA19: 115.93459 | GB19: 149.3938 | GC19: 164.09055 | GD19: 192.58661 | GE19: 189.66822 | GF19: 196.11881 | GG19: 178.04785 | GH19: 186.86 | GI19: 176.56193 | GJ19: 167.67843 | GK19: 167.57961 | GL19: 138.68147 | GM19: 116.29054 | GN19: 120.87638 | GO19: 122.43216 | GP19: 124.78198 | GQ19: 122.79206 | GR19: 130.29651 | GS19: 143.50138 | GT19: 140.97603 | GU19: 159.77923 | GV19: 154.27159 | GW19: 157.99126 | GX19: 136.24336 | GY19: 117.6993 | GZ19: 137.14809 | HA19: 112.99334 | HB19: 111.68259 | HC19: 115.94684 | HD19: 114.61888 | HE19: 124.22265 | HF19: 116.34655 | HG19: 121.38547 | HH19: 141.94835 | HI19: 117.6959
A20: Otros Impuestos | B20: 2.549 | C20: 2.294844 | D20: 2.4342709 | E20: 1.1920772 | F20: 1.398224 | G20: 1.3160739 | H20: 1.8314 | I20: 1.7617 | J20: 1.88 | K20: 3.308 | L20: 1.624 | M20: 1.414 | N20: 1.791 | O20: 1.354 | P20: 1.638 | Q20: 1.618 | R20: 1.53 | S20: 1.613 | T20: 1.895 | U20: 1.994 | V20: 1.579 | W20: 1.604 | X20: 1.489 | Y20: 1.4 | Z20: 1.947623 | AA20: 1.603 | AB20: 1.723 | AC20: 0.303647 | AD20: 0.14138633 | AE20: 0.13867951 | AF20: 0.1123902 | AG20: 0.096 | AH20: 0.1 | AI20: 0.1 | AJ20: 0.1455075 | AK20: 0.3 | AL20: 2.4561 | AM20: 2.7477 | AN20: 4.9171 | AO20: 5.8445 | AP20: 5.2721 | AQ20: 5.79 | AR20: 9.9092 | AS20: 3.0703 | AT20: 2.3927 | AU20: 2.3142 | AV20: 2.1611 | AW20: 5.0807 | AX20: 5.3 | AY20: 6.9 | AZ20: 7.8 | BA20: 7.2 | BB20: 7.8 | BC20: 8.945 | BD20: 12.39 | BE20: 6.18 | BF20: 5.316 | BG20: 5.129 | BH20: 7.412 | BI20: 7.791 | BJ20: 3.6291932 | BK20: 5.0334034 | BL20: 5.9786465 | BM20: 5.0629022 | BN20: 5.6701224 | BO20: 7.098311 | BP20: 7.7335512 | BQ20: 6.1260616 | BR20: 3.2289555 | BS20: 3.1907506 | BT20: 2.6307717 | BU20: 6.9961758 | BV20: 4.1107056 | BW20: 3.9625966 | BX20: 4.8268812 | BY20: 6.075385 | BZ20: 7.4502316 | CA20: 8.270262 | CB20: 9.27661 | CC20: 6.4694208 | CD20: 4.0590387 | CE20: 4.0445557 | CF20: 4.1536999 | CG20: 9.41793 | CH20: 5.8054083 | CI20: 4.2078612 | CJ20: 4.4071566 | CK20: 6.4629308 | CL20: 6.8148679 | CM20: 6.563954 | CN20: 9.8104542 | CO20: 11.964421 | CP20: 3.8381925 | CQ20: 3.7156815 | CR20: 3.5955644 | CS20: 7.0639547 | CT20: 7.460896 | CU20: 13.095409 | CV20: 13.546183 | CW20: 11.963835 | CX20: 10.031997 | CY20: 12.773444 | CZ20: 17.700721 | DA20: 13.179371 | DB20: 9.057 | DC20: 10.837633 | DD20: 8.6289212 | DE20: 15.0403 | DF20: 11.955531 | DG20: 28.185988 | DH20: 30.613063 | DI20: 34.226263 | DJ20: 31.859716 | DK20: 36.310856 | DL20: 38.388805 | DM20: 28.9782 | DN20: 26.7621 | DO20: 24.317379 | DP20: 24.847 | DQ20: 32.673711 | DR20: 34.2783 | DS20: 121.9737 | DT20: 87.7635 | DU20: 78.0781 | DV20: 57.2718 | DW20: 61.2189 | DX20: 74.6287 | DY20: 79.0547 | DZ20: 70.4494 | EA20: 52.1108 | EB20: 84.8162 | EC20: 70.2311 | ED20: 84.091457 | EE20: 61.2511 | EF20: 67.1812 | EG20: 59.2183 | EH20: 55.387 | EI20: 63.8129 | EJ20: 57.9858 | EK20: 54.1275 | EL20: 61.984 | EM20: 59.7259 | EN20: 53.9499 | EO20: 82.1535 | EP20: 115.2971 | EQ20: 137.8235 | ER20: 133.4628 | ES20: 129.5699 | ET20: 120.7307 | EU20: 129.403 | EV20: 125.247 | EW20: 130.093 | EX20: 129.5621 | EY20: 117.9786 | EZ20: 131.0055 | FA20: 180.9878 | FB20: 145.56464 | FC20: 148.80023 | FD20: 147.36178 | FE20: 136.69654 | FF20: 137.56364 | FG20: 140.09163 | FH20: 139.13843 | FI20: 140.86512 | FJ20: 139.0868 | FK20: 130.251 | FL20: 132.4415 | FM20: 130.3101 | FN20: 154.64386 | FO20: 145.29614 | FP20: 148.69817 | FQ20: 141.97315 | FR20: 130.46484 | FS20: 133.9727 | FT20: 146.5896 | FU20: 145.0584 | FV20: 138.6761 | FW20: 143.00153 | FX20: 184.8674 | FY20: 150.0639 | FZ20: 169.6287 | GA20: 155.845 | GB20: 158.0277 | GC20: 141.9758 | GD20: 133.816 | GE20: 126.679 | GF20: 163.688 | GG20: 128.103 | GH20: 122.586 | GI20: 122.787 | GJ20: 108.688 | GK20: 104.599 | GL20: 170.53654 | GM20: 120.99342 | GN20: 119.72036 | GO20: 115.63481 | GP20: 102.72795 | GQ20: 306.01622 | GR20: 387.0496 | GS20: 384.21273 | GT20: 222.72583 | GU20: 196.51901 | GV20: 194.41966 | GW20: 235.23177 | GX20: 219.06339 | GY20: 182.34652 | GZ20: 181.51 | HA20: 185.80893 | HB20: 185.369 | HC20: 191.88996 | HD20: 131.96874 | HE20: 121.1708 | HF20: 132.26292 | HG20: 129.24827 | HH20: 124.18273 | HI20: 145.88421
A21: Contribuciones Seguridad Social | B21: 13.36616 | C21: 11.47372 | D21: 11.41948 | E21: 18.21568 | F21: 18.2944 | G21: 16.38296 | H21: 20.281 | I21: 21.217004 | J21: 22.77132 | K21: 33.3154 | L21: 21.16494 | M21: 20.000351 | N21: 32.809762 | O21: 37.48242 | P21: 18.29152 | Q21: 38.677967 | R21: 38.592 | S21: 36.49 | T21: 35.4416 | U21: 38.7926 | V21: 61.515 | W21: 40.095 | X21: 39.191028 | Y21: 37.239 | Z21: 49.125 | AA21: 58.776 | AB21: 30.561 | AC21: 62.804 | AD21: 62.86 | AE21: 55.936 | AF21: 56.772 | AG21: 56.831 | AH21: 126.44721 | AI21: 96.120755 | AJ21: 59.030953 | AK21: 52.052366 | AL21: 64.889072 | AM21: 65.192822 | AN21: 76.230072 | AO21: 79.558822 | AP21: 59.693072 | AQ21: 66.051822 | AR21: 66.907325 | AS21: 70.6412 | AT21: 106.88575 | AU21: 116.61425 | AV21: 64.53725 | AW21: 62.308507 | AX21: 65.796631 | AY21: 66.257196 | AZ21: 120.03685 | BA21: 55.622541 | BB21: 69.607032 | BC21: 69.070616 | BD21: 60.509764 | BE21: 94.312787 | BF21: 126.16087 | BG21: 140.356 | BH21: 75.550517 | BI21: 80.323392 | BJ21: 77.351779 | BK21: 59.147624 | BL21: 111.13279 | BM21: 74.957198 | BN21: 78.090126 | BO21: 76.382046 | BP21: 76.190171 | BQ21: 90.178593 | BR21: 148.99387 | BS21: 151.12266 | BT21: 75.676414 | BU21: 89.747078 | BV21: 112.3713 | BW21: 71.431712 | BX21: 150.86755 | BY21: 101.64379 | BZ21: 104.17256 | CA21: 107.80416 | CB21: 94.919366 | CC21: 100.73645 | CD21: 183.79395 | CE21: 173.05257 | CF21: 149.57942 | CG21: 205.5827 | CH21: 96.390418 | CI21: 109.42737 | CJ21: 176.15515 | CK21: 157.82588 | CL21: 120.86196 | CM21: 147.12632 | CN21: 123.14301 | CO21: 137.68429 | CP21: 217.05493 | CQ21: 192.4001 | CR21: 175.45039 | CS21: 138.27177 | CT21: 123.6659 | CU21: 171.77518 | CV21: 230.19795 | CW21: 174.3274 | CX21: 75.051545 | CY21: 112.89388 | CZ21: 160.25444 | DA21: 187.60735 | DB21: 274.34384 | DC21: 244.64384 | DD21: 139.83484 | DE21: 202.21684 | DF21: 140.10814 | DG21: 149.81744 | DH21: 138.5072 | DI21: 240.5967 | DJ21: 160.90263 | DK21: 128.58595 | DL21: 120.73119 | DM21: 126.87082 | DN21: 378.30833 | DO21: 183.9302 | DP21: 155.47526 | DQ21: 137.12859 | DR21: 185.95507 | DS21: 196.25457 | DT21: 342.46215 | DU21: 164.71055 | DV21: 235.58279 | DW21: 211.15657 | DX21: 206.7131 | DY21: 197.1519 | DZ21: 188.3056 | EA21: 219.30757 | EB21: 157.7347 | EC21: 235.27838 | ED21: 210.06442 | EE21: 305.22984 | EF21: 318.87867 | EG21: 345.88442 | EH21: 348.19098 | EI21: 313.54046 | EJ21: 339.18661 | EK21: 302.75866 | EL21: 464.78004 | EM21: 305.45952 | EN21: 351.50267 | EO21: 365.36148 | EP21: 338.42187 | EQ21: 363.46376 | ER21: 424.51896 | ES21: 428.95578 | ET21: 394.85701 | EU21: 341.27168 | EV21: 448.69395 | EW21: 404.0977 | EX21: 440.71617 | EY21: 390.80797 | EZ21: 395.93179 | FA21: 384.20282 | FB21: 315.16515 | FC21: 217.85087 | FD21: 480.40585 | FE21: 413.48107 | FF21: 345.10862 | FG21: 371.82552 | FH21: 379.85913 | FI21: 361.40949 | FJ21: 383.80209 | FK21: 411.90096 | FL21: 396.46493 | FM21: 469.24937 | FN21: 369.0051 | FO21: 334.60599 | FP21: 440.05583 | FQ21: 354.81896 | FR21: 396.50937 | FS21: 454.59621 | FT21: 362.25748 | FU21: 394.2209 | FV21: 243.88326 | FW21: 498.3115 | FX21: 482.56273 | FY21: 387.25518 | FZ21: 413.3197 | GA21: 393.30177 | GB21: 377.21671 | GC21: 419.25004 | GD21: 408.69648 | GE21: 634.37014 | GF21: 407.66659 | GG21: 403.41078 | GH21: 405.33444 | GI21: 422.81291 | GJ21: 411.79334 | GK21: 360.13541 | GL21: 399.08003 | GM21: 398.4132 | GN21: 496.74475 | GO21: 404.0673 | GP21: 288.73432 | GQ21: 317.9272 | GR21: 374.38355 | GS21: 404.66829 | GT21: 401.39255 | GU21: 368.46363 | GV21: 360.59058 | GW21: 526.89532 | GX21: 503.97722 | GY21: 503.55471 | GZ21: 557.76099 | HA21: 445.26122 | HB21: 433.21795 | HC21: 437.66827 | HD21: 477.30569 | HE21: 424.00799 | HF21: 403.57088 | HG21: 436.30168 | HH21: 353.08343 | HI21: 438.93352
